Workbook
Name Actual_Expenses: #REF!
Name Actual_Income: #REF!
Name Centralize: 'BRD & EPIC'!#REF!
Name Centralize: 'BRD & EPIC (2)'!#REF!
Name Centralize: #REF!
Name ColumnTitle1: #REF!
Name ColumnTitleRegion1..B4.1: #REF!
Name ColumnTitleRegion2..C9.1: #REF!
Name Company_Name: #REF!
Name Create_and_edit_plan: 'BRD & EPIC'!#REF!
Name Create_and_edit_plan: 'BRD & EPIC (2)'!#REF!
Name Create_and_edit_plan: #REF!
Name List_Categories: #REF!
Name Map_view_and_route: 'BRD & EPIC'!#REF!
Name Map_view_and_route: 'BRD & EPIC (2)'!#REF!
Name Map_view_and_route: #REF!
Name Projected_Expenses: #REF!
Name Projected_Income: #REF!
Name Rule_based_upsell_capability: 'BRD & EPIC'!#REF!
Name Rule_based_upsell_capability: 'BRD & EPIC (2)'!#REF!
Name Rule_based_upsell_capability: #REF!
Name SHDR_Options: '1_Standard Part'!#REF!
Name SHDR_Options: #REF!
Name SHDR_Options: #REF!
Name SHDR_Options: #REF!
Name SHDR_Options: #REF!
Name US_Options: '1_Standard Part'!#REF!
Name US_Options: #REF!
Name US_Options: #REF!
Name US_Options: #REF!
Name US_Options: #REF!
Name Vendor_Options: '1_Standard Part'!#REF!
Name Vendor_Options: #REF!
Name Vendor_Options: #REF!
Name Vendor_Options: #REF!
Name Vendor_Options: #REF!
Name WeekStart: 'BRD & EPIC'!#REF!
Name WeekStart: 'BRD & EPIC (2)'!#REF!

Sheet DE_Cost
A1: Sprint Buffer | B1: 1.2 | C1: 1.4
A2: PM Ratio of Developer | B2: 0.18 | C2: 1.18
A3: DM Ratio of Developer | B3: 0.15 | C3: 0.1
A4: QA Ratio of Developer | B4: 1.5 | C4: 0.1
A5: Android Ratio of Developer | B5: 1.2 | C5: 1.2
A6: Front Ratio of Developer | B6: 1 | C6: 1.2
A7: Backend Ratio of Developer | B7: 1 | C7: 1
A8: DM Tech Ratio of Developer | B8: 0.15 | C8: 0.1
A9: UI Design Ratio of Developer | B9: 0.12 | C9: 1.2
A10: OTE Ratio | B10: 0.5 | C10: 0.5
A11: Type | B11: Hour | C11: RMB | D11: USD | F11: Role(ND) | G11: Days | H11: Hours | I11: Cost/H | J11: RMB | K11: Rate | L11: USD
A12: SE | B12: 320 | C12: =B12*314 -> 100480 | D12: =C12/6.84 -> 14690.058 | F12: Back-End | G12: 272 | H12: =G12*8 -> 2176 | I12: 314 | J12: =H12*I12 -> 683264 | K12: 6.84 | L12: =J12/K12 -> 99892.398
A13: Coupon | B13: =400+400 -> 800 | C13: =B13*314 -> 251200 | D13: =C13/6.84 -> 36725.146 | F13: Back-End | G13: 272 | H13: =G13*8 -> 2176 | I13: 314 | J13: =H13*I13 -> 683264 | K13: 6.84 | L13: =J13/K13 -> 99892.398
A14: Shopping Cart | B14: =480+480 -> 960 | C14: =B14*314 -> 301440 | D14: =C14/6.84 -> 44070.175 | F14: Front-End | G14: 272 | H14: =G14*8 -> 2176 | I14: 314 | J14: =H14*I14 -> 683264 | K14: 6.84 | L14: =J14/K14 -> 99892.398
A15: Ticketing | B15: =400+320 -> 720 | C15: =B15*314 -> 226080 | D15: =C15/6.84 -> 33052.632 | F15: Front-End | G15: 272 | H15: =G15*8 -> 2176 | I15: 314 | J15: =H15*I15 -> 683264 | K15: 6.84 | L15: =J15/K15 -> 99892.398
A16: Other | B16: =440 + 16 + 160 + 264 + 480 + 16 -> 1376 | C16: =B16*314 -> 432064 | D16: =C16/6.84 -> 63167.251 | F16: QA | G16: 272 | H16: =G16*8 -> 2176 | I16: 266 | J16: =H16*I16 -> 578816 | K16: 6.84 | L16: =J16/K16 -> 84622.222
A17: Total | B17: =SUM(B10:B16) -> 4176.5 | C17: =B17*314 -> 1311421 | D17: =C17/6.84 -> 191728.22 | F17: QA | G17: 272 | H17: =G17*8 -> 2176 | I17: 266 | J17: =H17*I17 -> 578816 | K17: 6.84 | L17: =J17/K17 -> 84622.222
F18: QA | G18: 272 | H18: =G18*8 -> 2176 | I18: 266 | J18: =H18*I18 -> 578816 | K18: 6.84 | L18: =J18/K18 -> 84622.222
F19: Total | G19: =SUM(G12:G18) -> 1904 | H19: =G19*8 -> 15232 | J19: =SUM(J12:J18) -> 4469504 | K19: 6.84 | L19: =SUM(L12:L18) -> 653436.26
I21: Cost/H | K21: Rate | L21: USD | M21: USD/Month
F22: Team Cost | I22: =SUM(I12:I18) -> 2054 | K22: 6.84 | L22: =I22/K22 -> 300.2924 | M22: =I22/K22*8*21.75 -> 52250.877
F24: Timeline ND Cost | L24: =F80 -> 450720
F25: Planned ND Capex Cost | L25: =GETPIVOTDATA("Sum of Amount USD",$A$89,"CAPEX/ OTE","CAPEX","Asset","Tmall Gift Card","Team","Digital Engineering")-L26 -> 724294.81
F26: Planned CM Capex Cost | L26: =GETPIVOTDATA("Sum of Amount USD",$A$89,"CAPEX/ OTE","CAPEX","Vendor/SHDR","SHDR","Asset","Tmall Gift Card","Team","Digital Engineering","Role list","Delivery Manager") -> 84911.118
F27: Planned CM OTE Cost | L27: =GETPIVOTDATA("Sum of Amount USD",$A$89,"CAPEX/ OTE","OTE","Asset","Tmall Gift Card","Team","Digital Engineering") -> 68565.727
F28: Planned OTHER ASSET Capex Cost | L28: =GETPIVOTDATA("Sum of Amount USD",$A$89,"CAPEX/ OTE","CAPEX","Asset","Ticketing Commerce","Team","Digital Engineering") +GETPIVOTDATA("Sum of Amount USD",$A$89,"CAPEX/ OTE","CAPEX","Asset","Shopping Cart","Team","Digital Engineering") -> 71402.005
F29: Planned OTHER ASSET OTE Cost | L29: =GETPIVOTDATA("Sum of Amount USD",$A$89,"CAPEX/ OTE","OTE","Asset","Ticketing Commerce","Team","Digital Engineering") +GETPIVOTDATA("Sum of Amount USD",$A$89,"CAPEX/ OTE","OTE","Asset","Shopping Cart","Team","Digital Engineering") -> 21510.816
F30: Min Over Cost | L30: =L25+L26+L27-L24-L28-L29 -> 334138.84 | M30: =L30/M22 -> 6.3948943
F31: Max Over Cost | L31: =L25+L26+L27-L24 -> 427051.66 | M31: =L31/M22 -> 8.1731002
F32: Min Over Cost(CAPEX Only) | L32: =L25+L26-L24-L28-L29 -> 265573.11 | M32: =L32/M22 -> 5.0826536
A34: BRD Overview | B34: BRD Priority | C34: BRD Detailed Requirement | D34: EPIC Title | E34: EPIC Story | F34: Task / Description | G34: CAPEX/ OTE | H34: Release | I34: Vendor/SHDR | J34: Cost Type | K34: Asset | L34: Team | M34: Role list | N34: Contractor (Y/N) | O34: Contractor Level | P34: New Hiring (Y/N) | Q34: Refresh/Replacement (Y/N) | R34: Labor Hours/ Quantities | S34: Rate / Unit Price RMB | T34: Amount RMB | U34: Amount USD | V34: Comments
A35: 1. Card Manufacture 礼品卡制造 | B35: 5 | C35: 1.1 Card Foundation Data Mgmt. and Purchase | D35: 1.1.2 Card Foundation Data|sales information | E35: 1.1.2 As Tmall Gift Card operation, I need define card data format, as manage card foundation data with sales information 作为天猫礼品卡运营，需要定义礼品卡数据格式，以便实现按卡号管理的礼品卡数据基础 | F35: Requirment Analysis | G35: CAPEX | H35: Release 1 | I35: SHDR | J35: Labor | K35: Tmall Gift Card | L35: Digital Product | M35: Product Manager | N35: {=Contractor(I35,J35)} -> #NAME? | P35: N | R35: 44 | S35: 0 | T35: =S35*R35 -> 0 | U35: 0
A36: 1. Card Manufacture 礼品卡制造 | B36: 5 | C36: 1.1 Card Foundation Data Mgmt. and Purchase | D36: 1.1.2 Card Foundation Data|sales information | E36: 1.1.2 As Tmall Gift Card operation, I need define card data format, as manage card foundation data with sales information 作为天猫礼品卡运营，需要定义礼品卡数据格式，以便实现按卡号管理的礼品卡数据基础 | F36: Project Management | G36: OTE | H36: Release 1 | I36: SHDR | J36: Labor | K36: Tmall Gift Card | L36: Digital Engineering | M36: Product Manager | N36: {=Contractor(I36,J36)} -> #NAME? | P36: N | R36: 36 | S36: 483.99337 | T36: =S36*R36 -> 17423.761 | U36: 2547.3335
A37: 1. Card Manufacture 礼品卡制造 | B37: 5 | C37: 1.1 Card Foundation Data Mgmt. and Purchase | D37: 1.1.2 Card Foundation Data|sales information | E37: 1.1.2 As Tmall Gift Card operation, I need define card data format, as manage card foundation data with sales information 作为天猫礼品卡运营，需要定义礼品卡数据格式，以便实现按卡号管理的礼品卡数据基础 | F37: Front-End Development | G37: CAPEX | H37: Release 1 | I37: Vendor | J37: Labor | K37: Tmall Gift Card | L37: Digital Engineering | M37: Front-end Developer | N37: {=Contractor(I37,J37)} -> #NAME? | O37: Level 4 (5-8Years) | P37: Y | R37: 240 | S37: 383.99994 | T37: =S37*R37 -> 92159.986 | U37: 13473.682
A38: 1. Card Manufacture 礼品卡制造 | B38: 5 | C38: 1.1 Card Foundation Data Mgmt. and Purchase | D38: 1.1.2 Card Foundation Data|sales information | E38: 1.1.2 As Tmall Gift Card operation, I need define card data format, as manage card foundation data with sales information 作为天猫礼品卡运营，需要定义礼品卡数据格式，以便实现按卡号管理的礼品卡数据基础 | F38: Back-End Development | G38: CAPEX | H38: Release 1 | I38: Vendor | J38: Labor | K38: Tmall Gift Card | L38: Digital Engineering | M38: Back-end Developer | N38: {=Contractor(I38,J38)} -> #NAME? | O38: Level 4 (5-8Years) | P38: Y | R38: 240 | S38: 0 | T38: =S38*R38 -> 0 | U38: 0
A39: 1. Card Manufacture 礼品卡制造 | B39: 5 | C39: 1.1 Card Foundation Data Mgmt. and Purchase | D39: 1.1.2 Card Foundation Data|sales information | E39: 1.1.2 As Tmall Gift Card operation, I need define card data format, as manage card foundation data with sales information 作为天猫礼品卡运营，需要定义礼品卡数据格式，以便实现按卡号管理的礼品卡数据基础 | F39: Function Testing | G39: CAPEX | H39: Release 1 | I39: Vendor | J39: Labor | K39: Tmall Gift Card | L39: Digital Engineering | M39: Quality Assurance | N39: {=Contractor(I39,J39)} -> #NAME? | O39: Level 4 (5-8Years) | P39: Y | R39: 240 | S39: 0 | T39: =S39*R39 -> 0 | U39: 0
A42: Project | B42: Resource Name | C42: Total person / Days | D42: Total person / hours | E42: Rate (usd) | F42: Cost (usd) | G42: w1 | H42: w2 | I42: w3 | J42: w4 | K42: w5 | L42: w6 | M42: w7 | N42: w8 | O42: w9 | P42: w10 | Q42: w11 | R42: w12 | S42: w13 | T42: w14 | U42: w15 | V42: w16 | W42: w17 | X42: w18 | Y42: w19 | Z42: w20 | AA42: w21 | AB42: w22 | AC42: w23 | AD42: w24 | AE42: w25 | AF42: w26 | AG42: w27 | AH42: w28 | AI42: w21 | AJ42: w22 | AK42: w23 | AL42: w24 | AM42: w25 | AN42: w26 | AO42: w27
G43: 45689 | H43: =G43+7 -> 45696 | I43: =H43+7 -> 45703 | J43: =I43+7 -> 45710 | K43: =J43+7 -> 45717 | L43: =K43+7 -> 45724 | M43: =L43+7 -> 45731 | N43: =M43+7 -> 45738 | O43: =N43+7 -> 45745 | ... AZ43: =AY43+7 -> 46004
G44: Sprint 1 | I44: Sprint 2 | K44: Sprint 3 | M44: Sprint 4 | O44: Sprint 5 | Q44: Sprint 6 | S44: Sprint 7 | U44: Sprint 8 | W44: Sprint 9 | Y44: Sprint 10 | AA44: Sprint 11 | AC44: Sprint 12 | AE44: Sprint 13 | AG44: Sprint 14 | AI44: Sprint 15 | AK44: Sprint 16 | AM44: Sprint 17 | AO44: Sprint 18 | AQ44: Sprint 19 | AS44: Sprint 20 | AU44: Sprint 21 | AW44: Sprint 22 | AY44: Sprint 23
G45: Development | AI45: SIT | AM45: UAT | AO45: FIT
A47: Oversight & Sharing Service | B47: SE | C47: 320 | D47: =C47*314 -> 100480 | E47: =D47/6.84 -> 14690.058 | P47: Holiday | AK47: RT | AL47: Holiday | AM47: FIT | AN47: 不超过1个月
B48: Coupon | C48: =400+400 -> 800 | D48: =C48*314 -> 251200 | E48: =D48/6.84 -> 36725.146
B49: Shopping Cart | C49: =480+480 -> 960 | D49: =C49*314 -> 301440 | E49: =D49/6.84 -> 44070.175
B50: Ticketing | C50: =400+320 -> 720 | D50: =C50*314 -> 226080 | E50: =D50/6.84 -> 33052.632
B51: Other | C51: =440 + 16 + 160 + 264 + 480 + 16 -> 1376 | D51: =C51*314 -> 432064 | E51: =D51/6.84 -> 63167.251 | H51: =266/6.8 -> 39.117647
B52: total | C52: =SUM(C46:C51) -> 4176 | D52: =C52*314 -> 1311264 | E52: =D52/6.84 -> 191705.26
A54: Product Manager | B54: TBD | C54: =D54/8 -> 90 | D54: =SUM(G54:BZ54) -> 720 | E54: 54 | F54: =D54*E54 -> 38880 | G54: 20 | H54: 20 | I54: 20 | J54: 20 | K54: 20 | L54: 20 | M54: 20 | N54: 20 | O54: 20 | P54: 20 | Q54: 20 | R54: 20 | S54: 20 | T54: 20 | U54: 20 | V54: 20 | W54: 20 | X54: 20 | Y54: 20 | Z54: 20 | AA54: 20 | AB54: 20 | AC54: 20 | AD54: 20 | AE54: 20 | AF54: 20 | AG54: 20 | AH54: 20 | AI54: 20 | AJ54: 20 | AK54: 20 | AL54: 20 | AM54: 20 | AN54: 20 | AO54: 20 | AP54: 20
A55: Delivery Manager | B55: TBD | C55: =D55/8 -> 90 | D55: =SUM(G55:BZ55) -> 720 | E55: 54 | F55: =D55*E55 -> 38880 | G55: 20 | H55: 20 | I55: 20 | J55: 20 | K55: 20 | L55: 20 | M55: 20 | N55: 20 | O55: 20 | P55: 20 | Q55: 20 | R55: 20 | S55: 20 | T55: 20 | U55: 20 | V55: 20 | W55: 20 | X55: 20 | Y55: 20 | Z55: 20 | AA55: 20 | AB55: 20 | AC55: 20 | AD55: 20 | AE55: 20 | AF55: 20 | AG55: 20 | AH55: 20 | AI55: 20 | AJ55: 20 | AK55: 20 | AL55: 20 | AM55: 20 | AN55: 20 | AO55: 20 | AP55: 20
A56: System Engineering | B56: TBD | C56: =D56/8 -> 27.5 | D56: =SUM(G56:BZ56) -> 220 | E56: 54 | F56: =D56*E56 -> 11880 | G56: 20 | H56: 20 | I56: 20 | J56: 20 | K56: 20 | L56: 20 | M56: 20 | N56: 20 | O56: 20 | P56: 20 | Q56: 20
A57: Security/Network | B57: TBD | C57: =D57/8 -> 20 | D57: =SUM(G57:BZ57) -> 160 | E57: 54 | F57: =D57*E57 -> 8640 | G57: 20 | H57: 20 | I57: 20 | J57: 20 | K57: 20 | L57: 20 | M57: 20 | N57: 20
A58: SDET/RM | B58: TBD | C58: =D58/8 -> 20 | D58: =SUM(G58:BZ58) -> 160 | E58: 54 | F58: =D58*E58 -> 8640 | G58: 20 | H58: 20 | I58: 20 | J58: 20 | K58: 20 | L58: 20 | M58: 20 | N58: 20
A59: Total: | F59: =SUM(F54:F58) -> 106920 | G59: =SUM(G54:G58) -> 100 | H59: =SUM(H54:H58) -> 100 | I59: =SUM(I54:I58) -> 100 | J59: =SUM(J54:J58) -> 100 | K59: =SUM(K54:K58) -> 100 | L59: =SUM(L54:L58) -> 100 | M59: =SUM(M54:M58) -> 100 | ... AP59: =SUM(AP54:AP58) -> 40
A60: RFID Tracking Platform
A62: Back-End | B62: TBD | C62: =D62/8 -> 180 | D62: =SUM(G62:BZ62) -> 1440 | E62: 49 | F62: =D62*E62 -> 70560 | G62: 40 | H62: 40 | I62: 40 | J62: 40 | K62: 40 | L62: 40 | M62: 40 | N62: 40 | O62: 40 | P62: 40 | Q62: 40 | R62: 40 | S62: 40 | T62: 40 | U62: 40 | V62: 40 | W62: 40 | X62: 40 | Y62: 40 | Z62: 40 | AA62: 40 | AB62: 40 | AC62: 40 | AD62: 40 | AE62: 40 | AF62: 40 | AG62: 40 | AH62: 40 | AI62: 40 | AJ62: 40 | AK62: 40 | AL62: 40 | AM62: 40 | AN62: 40 | AO62: 40 | AP62: 40
A63: Back-End | B63: TBD | C63: =D63/8 -> 180 | D63: =SUM(G63:BZ63) -> 1440 | E63: 49 | F63: =D63*E63 -> 70560 | G63: 40 | H63: 40 | I63: 40 | J63: 40 | K63: 40 | L63: 40 | M63: 40 | N63: 40 | O63: 40 | P63: 40 | Q63: 40 | R63: 40 | S63: 40 | T63: 40 | U63: 40 | V63: 40 | W63: 40 | X63: 40 | Y63: 40 | Z63: 40 | AA63: 40 | AB63: 40 | AC63: 40 | AD63: 40 | AE63: 40 | AF63: 40 | AG63: 40 | AH63: 40 | AI63: 40 | AJ63: 40 | AK63: 40 | AL63: 40 | AM63: 40 | AN63: 40 | AO63: 40 | AP63: 40
A64: Front-End | B64: TBD | C64: =D64/8 -> 180 | D64: =SUM(G64:BZ64) -> 1440 | E64: 49 | F64: =D64*E64 -> 70560 | G64: 40 | H64: 40 | I64: 40 | J64: 40 | K64: 40 | L64: 40 | M64: 40 | N64: 40 | O64: 40 | P64: 40 | Q64: 40 | R64: 40 | S64: 40 | T64: 40 | U64: 40 | V64: 40 | W64: 40 | X64: 40 | Y64: 40 | Z64: 40 | AA64: 40 | AB64: 40 | AC64: 40 | AD64: 40 | AE64: 40 | AF64: 40 | AG64: 40 | AH64: 40 | AI64: 40 | AJ64: 40 | AK64: 40 | AL64: 40 | AM64: 40 | AN64: 40 | AO64: 40 | AP64: 40
A65: Front-End | B65: TBD | C65: =D65/8 -> 180 | D65: =SUM(G65:BZ65) -> 1440 | E65: 49 | F65: =D65*E65 -> 70560 | G65: 40 | H65: 40 | I65: 40 | J65: 40 | K65: 40 | L65: 40 | M65: 40 | N65: 40 | O65: 40 | P65: 40 | Q65: 40 | R65: 40 | S65: 40 | T65: 40 | U65: 40 | V65: 40 | W65: 40 | X65: 40 | Y65: 40 | Z65: 40 | AA65: 40 | AB65: 40 | AC65: 40 | AD65: 40 | AE65: 40 | AF65: 40 | AG65: 40 | AH65: 40 | AI65: 40 | AJ65: 40 | AK65: 40 | AL65: 40 | AM65: 40 | AN65: 40 | AO65: 40 | AP65: 40
A66: Total: | F66: =SUM(F62:F65) -> 282240 | G66: =SUM(G62:G65) -> 160 | H66: =SUM(H62:H65) -> 160 | I66: =SUM(I62:I65) -> 160 | J66: =SUM(J62:J65) -> 160 | K66: =SUM(K62:K65) -> 160 | L66: =SUM(L62:L65) -> 160 | M66: =SUM(M62:M65) -> 160 | ... AP66: =SUM(AP62:AP65) -> 160
E68: `
A69: QA
A71: Onsite-QA App | B71: TBD | C71: =D71/8 -> 180 | D71: =SUM(G71:BZ71) -> 1440 | E71: 39 | F71: =D71*E71 -> 56160 | G71: 40 | H71: 40 | I71: 40 | J71: 40 | K71: 40 | L71: 40 | M71: 40 | N71: 40 | O71: 40 | P71: 40 | Q71: 40 | R71: 40 | S71: 40 | T71: 40 | U71: 40 | V71: 40 | W71: 40 | X71: 40 | Y71: 40 | Z71: 40 | AA71: 40 | AB71: 40 | AC71: 40 | AD71: 40 | AE71: 40 | AF71: 40 | AG71: 40 | AH71: 40 | AI71: 40 | AJ71: 40 | AK71: 40 | AL71: 40 | AM71: 40 | AN71: 40 | AO71: 40 | AP71: 40
A72: Onsite-QA App | B72: TBD | C72: =D72/8 -> 180 | D72: =SUM(G72:BZ72) -> 1440 | E72: 39 | F72: =D72*E72 -> 56160 | G72: 40 | H72: 40 | I72: 40 | J72: 40 | K72: 40 | L72: 40 | M72: 40 | N72: 40 | O72: 40 | P72: 40 | Q72: 40 | R72: 40 | S72: 40 | T72: 40 | U72: 40 | V72: 40 | W72: 40 | X72: 40 | Y72: 40 | Z72: 40 | AA72: 40 | AB72: 40 | AC72: 40 | AD72: 40 | AE72: 40 | AF72: 40 | AG72: 40 | AH72: 40 | AI72: 40 | AJ72: 40 | AK72: 40 | AL72: 40 | AM72: 40 | AN72: 40 | AO72: 40 | AP72: 40
A73: Onsite-QA App | B73: TBD | C73: =D73/8 -> 180 | D73: =SUM(G73:BZ73) -> 1440 | E73: 39 | F73: =D73*E73 -> 56160 | G73: 40 | H73: 40 | I73: 40 | J73: 40 | K73: 40 | L73: 40 | M73: 40 | N73: 40 | O73: 40 | P73: 40 | Q73: 40 | R73: 40 | S73: 40 | T73: 40 | U73: 40 | V73: 40 | W73: 40 | X73: 40 | Y73: 40 | Z73: 40 | AA73: 40 | AB73: 40 | AC73: 40 | AD73: 40 | AE73: 40 | AF73: 40 | AG73: 40 | AH73: 40 | AI73: 40 | AJ73: 40 | AK73: 40 | AL73: 40 | AM73: 40 | AN73: 40 | AO73: 40 | AP73: 40
A74: Total: | F74: =SUM(F71:F73) -> 168480 | G74: =SUM(G71:G73) -> 120 | H74: =SUM(H71:H73) -> 120 | I74: =SUM(I71:I73) -> 120 | J74: =SUM(J71:J73) -> 120 | K74: =SUM(K71:K73) -> 120 | L74: =SUM(L71:L73) -> 120 | M74: =SUM(M71:M73) -> 120 | ... AP74: =SUM(AP71:AP73) -> 120
A77: Allocated Effort (man-day): | C77: =ROUND(SUM(C54:C73), 0) -> 1508 | D77: =SUM(D54:D73) -> 12060 | F77: =SUM(F59, F66,F74) -> 557640
A78: Forecast Effort (man-day): | C78: 0
A79: Delta: | C79: =C77-C78 -> 1508
A80: Summary | B80: Oversight & Sharing Service | D80: =F59 -> 106920 | E80: Development Cost | F80: =F77-D80 -> 450720
A84: Note
A85: The timeline is subject to changed and for reference only
A89: Row Labels | B89: Sum of Labor Hours/ Quantities | C89: Sum of Amount USD
A90: Digital Engineering | B90: 28014 | C90: 1283988.5
A91: Coupon Commerce | B91: 6948 | C91: 313304.06
A92: CAPEX | B92: 6748 | C92: 299152.2
A93: Back-end Developer | B93: 3804 | C93: 174351.29
A94: Vendor | B94: 3804 | C94: 174351.29
A95: Front-end Developer | B95: 800 | C95: 36666.938
A96: Vendor | B96: 800 | C96: 36666.938
A97: Product Manager | B97: 480 | C97: 23068.964
A98: Vendor | B98: 480 | C98: 23068.964
A99: Quality Assurance | B99: 1616 | C99: 62758.114
A100: Vendor | B100: 1616 | C100: 62758.114
A101: Solution Manager | B101: 48 | C101: 2306.8964
... A178: WDP&R Technology | B178: 25 | C178: 6000.2918
A179: (blank) | C179: 0
A180: (blank) | C180: 0
A181: Grand Total | B181: 32015 | C181: 1508347.1

Sheet Cost Breakdown
A1: Project Category | B1: 点击返回说明页 Back to Instructions
A2: Commercial
A4: BRD Overview | B4: BRD Priority | C4: BRD Detailed Requirement | D4: EPIC Title | E4: EPIC Story | F4: Task / Description | G4: CAPEX/ OTE | H4: Release | I4: Vendor/SHDR | J4: Cost Type | K4: Asset | L4: Team | M4: Role list | N4: Contractor (Y/N) | O4: Contractor Level | P4: New Hiring (Y/N) | Q4: Refresh/Replacement (Y/N) | R4: Labor Hours/ Quantities | S4: Rate / Unit Price RMB | T4: Amount RMB | U4: Amount USD | V4: Comments
A5: 1. Card Manufacture 礼品卡制造 | B5: 5 | C5: 1.1 Card Foundation Data Mgmt. and Purchase | D5: 1.1.2 Card Foundation Data|sales information | E5: 1.1.2 As Tmall Gift Card operation, I need define card data format, as manage card foundation data with sales information 作为天猫礼品卡运营，需要定义礼品卡数据格式，以便实现按卡号管理的礼品卡数据基础 | F5: Requirment Analysis | G5: CAPEX | H5: Release 1 | I5: SHDR | J5: Labor | K5: Unified Gift Card - Card Foundation Data Mgt | L5: Digital Product | M5: Product Manager | N5: {=Contractor(I5,J5)} -> #NAME? | P5: N | R5: 44 | S5: 0 | T5: =S5*R5 -> 0 | U5: 0

Sheet BRD & EPIC (2)
A1: EPIC - Project Name | F1: 点击返回说明页 Back to Instructions | Y1: 0
A2: LOB VP Signature | C2: Tony Castillo/Steve Sulaski | D2: Date
A3: PM Diretctor Level Sigature | C3: Jimmy Lee | D3: Date
A4: DM Diretctor Level Sigature | C4: Peter Zhang | D4: Date
A6: BRD Priority | B6: 0. BRD Overview | C6: 0.0 BRD Detailed Requirement | D6: 0.0.0 EPIC Title | E6: 0.0.0.0 EPIC Story | F6: Description | G6: Dependencies | H6: EPIC Story(CN) | I6: Description(CN) | J6: Comment | K6: Follow-up Group | L6: Follow-up | M6: Follow-up with vendor | N6: Task Title | O6: Task Description | P6: system type | Q6: system tpye ultimately | R6: system type2 | S6: follw up PM | T6: follow up | U6: Develop Labor(man/day) | V6: Real Develop Labor(Man/Hour) | W6: Real Develop Labor(Man/Day) | X6: 表设计 | Y6: 表个数 | Z6: task count | AA6: Review Pass | AB6: Lucky Comment | AC6: check content change | AD6: task sum count
A7: 0 | B7: 0. Project Foundation | C7: 0.1 SE|Hosting | D7: 0.1.1 SE|System deployment in Cloud | E7: 0.1.1.1 Services/systems set up in cloud, Create new cloud accounts, New vendor system support in Cloud | G7: SE | H7: 0.1.1.1 在云中设置的服务/系统，创建新的云账户，在云中支持新的供应商系统 | Q7: =BRD_EPIC2[[#This Row],[system type]]&BRD_EPIC2[[#This Row],[system type2]] | V7: =$U7*DE_Cost!$B$1*8 -> 0 | W7: =$U7*DE_Cost!$B$1 -> 0 | AA7: Y
D8: 0.1.2 SE|System deployment on-premise | E8: 0.1.2.1 Services/systems deployment/configurition/automation for new servers in on-premise datacenter | G8: SE | H8: 0.1.2.1 本地数据中心新服务器部署/配置/自动化服务/系统 | Q8: =BRD_EPIC2[[#This Row],[system type]]&BRD_EPIC2[[#This Row],[system type2]] | V8: =$U8*DE_Cost!$B$1*8 -> 0 | W8: =$U8*DE_Cost!$B$1 -> 0 | AA8: Y
D9: 0.1.3 SE|Database deployment in Cloud | E9: 0.1.3.1 Database set up in cloud, dashboard requirements, database schema changes, data migration | G9: SE | H9: 0.1.3.1 云端数据库设置，仪表板需求，数据库架构变更，数据迁移 | Q9: =BRD_EPIC2[[#This Row],[system type]]&BRD_EPIC2[[#This Row],[system type2]] | V9: =$U9*DE_Cost!$B$1*8 -> 0 | W9: =$U9*DE_Cost!$B$1 -> 0 | AA9: Y
D10: 0.1.4 SE|Cloud Hosting | E10: 0.1.4.1 Hosting fee in AliCloud, AWS | G10: SE | H10: 0.1.4.1 阿里云、AWS 托管费用 | Q10: =BRD_EPIC2[[#This Row],[system type]]&BRD_EPIC2[[#This Row],[system type2]] | V10: =$U10*DE_Cost!$B$1*8 -> 0 | W10: =$U10*DE_Cost!$B$1 -> 0 | AA10: Y
D11: 0.1.5 SE|Hardware purchase | E11: 0.1.5.1 New servers/storage/devices in on-premise datacenter | G11: SE | H11: 0.1.5.1 本地数据中心中的新服务器/存储设备 | Q11: =BRD_EPIC2[[#This Row],[system type]]&BRD_EPIC2[[#This Row],[system type2]] | V11: =$U11*DE_Cost!$B$1*8 -> 0 | W11: =$U11*DE_Cost!$B$1 -> 0 | AA11: Y
D12: 0.1.6 SE|Vendor Service | E12: 0.1.6.1 3rd party vendor services | G12: SE | H12: 0.1.6.1 第三方供应商服务 | Q12: =BRD_EPIC2[[#This Row],[system type]]&BRD_EPIC2[[#This Row],[system type2]] | V12: =$U12*DE_Cost!$B$1*8 -> 0 | W12: =$U12*DE_Cost!$B$1 -> 0 | AA12: Y
D13: 0.1.7 SE|License|Software | E13: 0.1.7.1 License cost for hardware/software | G13: SE | H13: 0.1.7.1 硬件/软件的许可费用 | Q13: =BRD_EPIC2[[#This Row],[system type]]&BRD_EPIC2[[#This Row],[system type2]] | V13: =$U13*DE_Cost!$B$1*8 -> 0 | W13: =$U13*DE_Cost!$B$1 -> 0 | AA13: Y
C14: 0.2 QO|GQE | D14: 0.2.1 GQE |Manual Testing | E14: 0.2.1.1 Design test cases, execute test cases, analyze defects, write test reports for Manual Testing. | G14: QO | H14: 0.2.1.1 设计测试用例，执行测试用例，分析缺陷，编写手动测试报告。 | K14: QO | Q14: =BRD_EPIC2[[#This Row],[system type]]&BRD_EPIC2[[#This Row],[system type2]] | V14: =$U14*DE_Cost!$B$1*8 -> 0 | W14: =$U14*DE_Cost!$B$1 -> 0 | AA14: Y
D15: 0.2.2 GQE |Automation Testing | E15: 0.2.2.1 Design test cases, encode test cases, execute automation scripts, analyze defects, write test reports for Automation Testing. | G15: QO | H15: 0.2.2.1 设计测试用例，编码测试用例，执行自动化脚本，分析缺陷，编写自动化测试报告。 | K15: QO | Q15: =BRD_EPIC2[[#This Row],[system type]]&BRD_EPIC2[[#This Row],[system type2]] | V15: =$U15*DE_Cost!$B$1*8 -> 0 | W15: =$U15*DE_Cost!$B$1 -> 0 | AA15: Y
D16: 0.2.3 GQE |Performance Testing | E16: 0.2.3.1 Design test cases, encode test cases, execute performance test cases, analyze defects, write test reports for Performance Testing. | G16: QO | H16: 0.2.3.1 设计测试用例，编码测试用例，执行性能测试用例，分析缺陷，编写性能测试报告。 | K16: QO | Q16: =BRD_EPIC2[[#This Row],[system type]]&BRD_EPIC2[[#This Row],[system type2]] | V16: =$U16*DE_Cost!$B$1*8 -> 0 | W16: =$U16*DE_Cost!$B$1 -> 0 | AA16: Y
D17: 0.2.4 GQE |Command Center Support | E17: 0.2.4.1 Support command centers during launch and hypercare period. | G17: QO | H17: 0.2.4.1 在发布和超保支持期间支持指挥中心。 | K17: QO | Q17: =BRD_EPIC2[[#This Row],[system type]]&BRD_EPIC2[[#This Row],[system type2]] | V17: =$U17*DE_Cost!$B$1*8 -> 0 | W17: =$U17*DE_Cost!$B$1 -> 0 | AA17: Y
C18: 0.3 QO|Release Management | D18: 0.3.1 RM |Change and Release Support | E18: 0.3.1.1 Plan, design, schedule, validate, deploy and control system changes and releases to support system launches. | G18: QO | H18: 0.3.1.1 计划、设计、安排、验证、部署和控制系统变更与发布，以支持系统上线。 | K18: QO | Q18: =BRD_EPIC2[[#This Row],[system type]]&BRD_EPIC2[[#This Row],[system type2]] | V18: =$U18*DE_Cost!$B$1*8 -> 0 | W18: =$U18*DE_Cost!$B$1 -> 0 | AA18: Y
D19: 0.3.2 RM |Command Center Support | E19: 0.3.2.1 Support command centers during hypercare period. | G19: QO | H19: 0.3.2.1 在超保期间支持指挥中心。 | K19: QO | Q19: =BRD_EPIC2[[#This Row],[system type]]&BRD_EPIC2[[#This Row],[system type2]] | V19: =$U19*DE_Cost!$B$1*8 -> 0 | W19: =$U19*DE_Cost!$B$1 -> 0 | AA19: Y
C20: 0.4 QO|Incident Management | D20: 0.4.1 L2 |Configuration Management | E20: 0.4.1.1 Perform configuration changes on TYK, ACP, UAP, VDM. | G20: QO | H20: 0.4.1.1 在 TYK、ACP、UAP、VDM 上执行配置更改。 | J20: 确认Onsite时间， L2需要规划成员支持 7天，7:~23 | K20: QO | Q20: =BRD_EPIC2[[#This Row],[system type]]&BRD_EPIC2[[#This Row],[system type2]] | V20: =$U20*DE_Cost!$B$1*8 -> 0 | W20: =$U20*DE_Cost!$B$1 -> 0 | AA20: Y
D21: 0.4.2 L2 |Command Center Coordination and Support | E21: 0.4.2.1 Plan and implement command centers to support launches. | G21: QO | H21: 0.4.2.1 规划并实施支持发射的指挥中心。 | J21: 确认try run时间，住酒店40人/1000 | K21: QO | Q21: =BRD_EPIC2[[#This Row],[system type]]&BRD_EPIC2[[#This Row],[system type2]] | V21: =$U21*DE_Cost!$B$1*8 -> 0 | W21: =$U21*DE_Cost!$B$1 -> 0 | AA21: Y
C22: 0.5 QO|Problem Management | D22: 0.5.1 Problem Management |Proactive Problem Management | E22: 0.5.1.1 Follow all opened defects that will move to production with the launch and drive the resolution of defects before they turn into incidents. | G22: QO | H22: 0.5.1.1 跟踪所有将随发布移至生产环境的缺陷，并在其演变为事件前推动解决这些缺陷。 | J22: 需要确认我们自己是否介入测试 | K22: QO | Q22: =BRD_EPIC2[[#This Row],[system type]]&BRD_EPIC2[[#This Row],[system type2]] | V22: =$U22*DE_Cost!$B$1*8 -> 0 | W22: =$U22*DE_Cost!$B$1 -> 0 | AA22: Y
C23: 0.6 InfoSec|Information Security | D23: 0.6.1 InfoSec|Security Terms Review in the Contract | E23: 0.6.1.1 Whenever the 3rd party provider would like to change the default information security terms and schedules, the project team needs to contact InfoSec for change review. | G23: Security | H23: 0.6.1.1 当第三方提供商希望更改默认信息安全条款和时间表时，项目团队需要联系信息安全部门进行变更审核。 | Q23: =BRD_EPIC2[[#This Row],[system type]]&BRD_EPIC2[[#This Row],[system type2]] | V23: =$U23*DE_Cost!$B$1*8 -> 0 | W23: =$U23*DE_Cost!$B$1 -> 0 | AA23: Y
D24: 0.6.2 InfoSec|Information Security Assessment (ISA) | E24: 0.6.2.1 All the new applications and significant change to the existing applications need to complete the information security assessment. | G24: Security | H24: 0.6.2.1 所有新应用及对现有应用的重大变更均需完成信息安全评估。 | Q24: =BRD_EPIC2[[#This Row],[system type]]&BRD_EPIC2[[#This Row],[system type2]] | V24: =$U24*DE_Cost!$B$1*8 -> 0 | W24: =$U24*DE_Cost!$B$1 -> 0 | AA24: Y
D25: 0.6.3 InfoSec|RFP Security Questionnaire and/or Third Party Assessment (TPA) | E25: 0.6.3.1 If a 3rd party provider is involved, RFP security questionnaire is mandatory to be filled, and if necessary the Third Party Assessment should be conducted. | G25: Security | H25: 0.6.3.1 如果涉及第三方供应商，则必须填写 RFP 安全问卷，并在必要时进行第三方评估。 | Q25: =BRD_EPIC2[[#This Row],[system type]]&BRD_EPIC2[[#This Row],[system type2]] | V25: =$U25*DE_Cost!$B$1*8 -> 0 | W25: =$U25*DE_Cost!$B$1 -> 0 | AA25: Y
D26: 0.6.4 InfoSec|Application Security Enrollment and Testing | E26: 0.6.4.1 This includes the applicable enrollment and testing, such as SAST, DAST, Pen-Test, Privacy Scan, Mobile Shield and etc. | G26: Security | H26: 0.6.4.1 这包括适用的注册和测试，例如 SAST、DAST、渗透测试、隐私扫描、移动防护等。 | Q26: =BRD_EPIC2[[#This Row],[system type]]&BRD_EPIC2[[#This Row],[system type2]] | V26: =$U26*DE_Cost!$B$1*8 -> 0 | W26: =$U26*DE_Cost!$B$1 -> 0 | AA26: Y
D27: 0.6.5 InfoSec|Security Operation Monitoring and Verificiation | E27: 0.6.5.1 This includes: Network Connection Review (Firewall); Endpoint Security Verification and Testing; Scripting for MyJira Sync; Review Application Hosting and Cloud Infrastructure SCS; Vulnerability Scanning. | G27: Security | H27: 0.6.5.1 这包括：网络连接审查（防火墙）；终端安全验证和测试；MyJira Sync 的脚本编写；审查应用程序托管和云基础设施 SCS；漏洞扫描。 | Q27: =BRD_EPIC2[[#This Row],[system type]]&BRD_EPIC2[[#This Row],[system type2]] | U27: 0 | V27: =$U27*DE_Cost!$B$1*8 -> 0 | W27: =$U27*DE_Cost!$B$1 -> 0 | AA27: Y
D28: 0.6.6 InfoSec|Identity and Access Management | E28: 0.6.6.1 Integration with central authentication and authorization platforms. | G28: Security | H28: 0.6.6.1 与中央身份验证和授权平台的集成。 | Q28: =BRD_EPIC2[[#This Row],[system type]]&BRD_EPIC2[[#This Row],[system type2]] | V28: =$U28*DE_Cost!$B$1*8 -> 0 | W28: =$U28*DE_Cost!$B$1 -> 0 | AA28: Y
D29: 0.6.7 InfoSec|Online Fraud Detection | E29: 0.6.7.1 Online fraud rules review and integration with AOFD platform | G29: Security | H29: 0.6.7.1 在线欺诈规则审查并与 AOFD 平台集成 | Q29: =BRD_EPIC2[[#This Row],[system type]]&BRD_EPIC2[[#This Row],[system type2]] | V29: =$U29*DE_Cost!$B$1*8 -> 0 | W29: =$U29*DE_Cost!$B$1 -> 0 | AA29: Y
D30: 0.6.8 InfoSec|Disaster Recovery and Business Continuity Management | E30: 0.6.8.1 Conduct a Business Impact Analysis (BIA) to identify critical IT services and determine the IT service continuity strategy. Develop and test comprehensive IT Service Continuity Plans to maintain business operations in the event of security incidents or system downtime | G30: Security | H30: 0.6.8.1 进行业务影响分析（BIA）以识别关键 IT 服务并确定 IT 服务连续性策略。制定并测试全面的 IT 服务连续性计划，以在发生安全事件或系统停机时维持业务运营。 | Q30: =BRD_EPIC2[[#This Row],[system type]]&BRD_EPIC2[[#This Row],[system type2]] | V30: =$U30*DE_Cost!$B$1*8 -> 0 | W30: =$U30*DE_Cost!$B$1 -> 0 | AA30: Y
C31: 0.7 EA|Enterprise Architecture | D31: 0.7.1 EA|Solution Architecture Review | E31: 0.7.1.1 Collaborative work for appropriate design of availability, resilience, integrations and ensure all EA standards are aligned and complied | G31: EA | H31: 0.7.1.1 协同工作，确保可用性、弹性、集成设计的合理性，并确保所有企业架构标准保持一致并得到遵守 | Q31: =BRD_EPIC2[[#This Row],[system type]]&BRD_EPIC2[[#This Row],[system type2]] | V31: =$U31*DE_Cost!$B$1*8 -> 0 | W31: =$U31*DE_Cost!$B$1 -> 0 | AA31: Y
C32: 0.8 F&IT|Data Technology | D32: 0.8.1 Data|Database deployment on-premises | E32: 0.8.1.1 Database deploy on-premises, database schema changes, data migration and database optimization | G32: FIT | H32: 0.8.1.1 本地数据库部署、数据库架构变更、数据迁移和数据库优化 | Q32: =BRD_EPIC2[[#This Row],[system type]]&BRD_EPIC2[[#This Row],[system type2]] | V32: =$U32*DE_Cost!$B$1*8 -> 0 | W32: =$U32*DE_Cost!$B$1 -> 0 | AA32: Y
D33: 0.8.2 Data|Database deployment in cloud | E33: 0.8.2.1 Database deploy in cloud database schema changes, data migration and database optimization | G33: FIT | H33: 0.8.2.1 数据库部署在云数据库模式变更、数据迁移和数据库优化 | Q33: =BRD_EPIC2[[#This Row],[system type]]&BRD_EPIC2[[#This Row],[system type2]] | V33: =$U33*DE_Cost!$B$1*8 -> 0 | W33: =$U33*DE_Cost!$B$1 -> 0 | AA33: Y
D34: 0.8.3 Data|Data migration & synchronization | E34: 0.8.3.1 During the transition between the old POS and the new POS, the old POS data needs to be migrated to the New POS. Historical data from the past six months will be migrated in one batch. Incremental data will be synchronized in near real-time (within 15 minutes). Currently, there are three proposed solutions (choose one): Directly connect to the old POS database in the cloud or migrate the old POS sales data tables as-is into the New POS database, with the New POS handling the old tables’ data for interface display. Based on option 1, transform the data into the New POS format and write it into the New POS sales tables. Directly use Javis APIs to query old POS sales data to support order data inquiries, refunds, and exchange/return operations. 0.8.3.1 新老POS切换期间，需要将老POS数据迁移至New POS里，历史近半年数据一次性迁移，增量数据近实时同步（15分钟内）。目前有三种方案（选其一）： 1. 云上直连老POS数据库或将老POS的销售数据表原样迁移至New POS的库中，由New POS处理老表数据用于界面展示 2. 在1的基础上，将数据转换成New POS的数据，写入到New POS的销售表里 3. 直接使用Javis的接口查询老POS销售数据，完成订单数据查询、退款、退换货操作 | G34: Data & Jarvis | H34: 0.8.3.1 在旧 POS 系统和新 POS 系统过渡期间，旧 POS 数据需要迁移到新 POS 系统。 过去六个月的历史数据将一次性迁移。 增量数据将进行近实时同步（15 分钟内）。 目前，提出了三种解决方案（选择其一）： 直接连接到云端的旧 POS 数据库，或将旧 POS 销售数据表原样迁移到新 POS 数据库中，由新 POS 处理这些旧表的数据以进行界面显示。 根据选项 1，将数据转换为新的 POS 格式并写入新的 POS 销售表中。 直接使用 Javis API 查询旧的 POS 销售数据，以支持订单数据查询、退款以及换货/退货操作。 | K34: Jarvis | Q34: =BRD_EPIC2[[#This Row],[system type]]&BRD_EPIC2[[#This Row],[system type2]] | V34: =$U34*DE_Cost!$B$1*8 -> 0 | W34: =$U34*DE_Cost!$B$1 -> 0 | AA34: Y
A35: 1(Minimum scope) | B35: 2. Foundation operational functions 基础运营功能 | C35: 2.1 Merch & FnB product ordering 商品&餐饮点单 | D35: 2.1.1 [Merch] Add/delete product|Add product to shopping list 添加商品 | E35: 2.1.1.1 As Merch cashier, I need New POS will be able to add product to shopping list by barcode scanning or tap button, as to process shopping in store ordering. | F35: Items in one transaction may more than one thousand lines. | H35: 2.1.1.1 作为收银员，我需要新 POS 系统能够通过条形码扫描或点击按钮将商品添加到购物清单，以便处理店内购物订单。 | I35: 一个交易中的商品可能超过一千行。 | N35: 购物清单-添加+清单联动 | O35: 不包含优惠券等促销计算逻辑（需其他EPIC计算工时间） | P35: Android | Q35: =BRD_EPIC2[[#This Row],[system type]]&BRD_EPIC2[[#This Row],[system type2]] -> Android & QA & PM & DM & UI | R35: & QA & PM & DM & UI | U35: 5 | V35: =$U35*DE_Cost!$B$1*8 -> 48 | W35: =$U35*DE_Cost!$B$1 -> 6 | X35: 0 | Y35: 0 | Z35: =LEN(Q35) - LEN(SUBSTITUTE(Q35, "&", "")) + 1 -> 5 | AA35: =LEN(R35) - LEN(SUBSTITUTE(R35, "&", "")) + 1 -> 5 | AB35: =LEN(S35) - LEN(SUBSTITUTE(S35, "&", "")) + 1 -> 1 | AC35: =LEN(T35) - LEN(SUBSTITUTE(T35, "&", "")) + 1 -> 1
A36: 1(Minimum scope) | B36: 2. Foundation operational functions 基础运营功能 | C36: 2.1 Merch & FnB product ordering 商品&餐饮点单 | D36: 2.1.1 [Merch] Add/delete product|Delete product in shopping list 删除商品 | E36: 2.1.1.2 As Merch cashier, I need New POS will be able to delete product in shopping list by slide w/ tap button, as to process shopping in store ordering. | H36: 2.1.1.2 作为收银员，我需要新 POS 系统能够通过滑动并点击按钮来删除购物清单中的商品，以便处理店内订单购物。 | N36: 购物清单-删除 | O36: (删除（0.5天） | P36: Android | Q36: =BRD_EPIC2[[#This Row],[system type]]&BRD_EPIC2[[#This Row],[system type2]] -> Android & QA & PM & DM & UI | R36: & QA & PM & DM & UI | U36: 2 | V36: =$U36*DE_Cost!$B$1*8 -> 19.2 | W36: =$U36*DE_Cost!$B$1 -> 2.4 | X36: 0 | Y36: 0 | Z36: =LEN(Q36) - LEN(SUBSTITUTE(Q36, "&", "")) + 1 -> 5 | AA36: Y
A37: 1(Minimum scope) | B37: 2. Foundation operational functions 基础运营功能 | C37: 2.1 Merch & FnB product ordering 商品&餐饮点单 | D37: 2.1.1 [Merch] Add/delete product|Modify product quantity/price in shopping list 修改商品数量或价格 | E37: 2.1.1.3 As Merch cashier, I need New POS will be able to modify product quantity/price in shopping list by tap button , as to process shopping in store ordering. | F37: 1. Press “+, -” or entering number to adjust item quantity 2. Repeated scanning same item or continuous scanning in X seconds will accumulate quantity(X is configurable) 3. Pricing change can only be process by GSM/Lead authorized, and not impact its price in foundation data. GSM/Lead authorized needed. | H37: 2.1.1.3 作为收银员，我需要新 POS 系统能够通过点击按钮修改购物清单中的产品数量/价格，以便处理店内订单购物。 | I37: 1. 按“+、-”或输入数字调整商品数量 2. 在X秒内重复扫描同一商品或连续扫描将累积数量（X可配置） 3. 价格更改只能由GSM/主管授权处理，且不影响基础数据中的价格。需要GSM/主管授权。 | N37: 购物清单-修改-产品数量/价格 | O37: 1.权限校验 2.修改发起授权（弹窗输入主管工号/密码？这个功能应该是有单独工时跟进） | P37: Android | Q37: =BRD_EPIC2[[#This Row],[system type]]&BRD_EPIC2[[#This Row],[system type2]] -> Android & QA & PM & DM & UI | R37: & QA & PM & DM & UI | U37: 2 | V37: =$U37*DE_Cost!$B$1*8 -> 19.2 | W37: =$U37*DE_Cost!$B$1 -> 2.4 | X37: 0 | Y37: 0 | Z37: =LEN(Q37) - LEN(SUBSTITUTE(Q37, "&", "")) + 1 -> 5 | AA37: Y
A38: 1(Minimum scope) | B38: 2. Foundation operational functions 基础运营功能 | C38: 2.1 Merch & FnB product ordering 商品&餐饮点单 | D38: 2.1.1 [Merch] Add/delete product|Save/get product in shopping list 暂存与提取购物清单 | E38: 2.1.1.4 As Merch cashier, I need New POS will be able to save/get product list as draft when guest would like to order pending, as to process shopping in store ordering. | F38: 1. Modify draft shopping list: item/discount/coupon, and search 2. Delete shopping list | H38: 2.1.1.4 作为收银员，我需要新 POS 系统能够在客人想要暂存订单时保存/获取产品清单草稿，以便处理店内购物订单。 | I38: 1. 修改草稿购物车：商品/折扣/优惠券，以及搜索 2. 删除购物车 | N38: 购物清单-修改 | O38: 1.Android本地修改 2.销售信息联动，存在系统对接。实时试算。主要耗时在联调上(2)。 | P38: Android & Back-End | Q38: =BRD_EPIC2[[#This Row],[system type]]&BRD_EPIC2[[#This Row],[system type2]] -> Android & Back-End & QA & PM & DM & UI | R38: & QA & PM & DM & UI | U38: 5 | V38: =$U38*DE_Cost!$B$1*8 -> 48 | W38: =$U38*DE_Cost!$B$1 -> 6 | X38: 0 | Y38: 0 | Z38: =LEN(Q38) - LEN(SUBSTITUTE(Q38, "&", "")) + 1 -> 6 | AA38: Y
A39: 1(Minimum scope) | B39: 2. Foundation operational functions 基础运营功能 | C39: 2.1 Merch & FnB product ordering 商品&餐饮点单 | D39: 2.1.1 [Merch] Add/delete product|Check product saleable in shopping list 检查商品售卖状态 | E39: 2.1.1.5 As Merch cashier, I need New POS will be able to check product saleable when add into shopping list, display message when its unsaleable , as to make sure non-saleable product in shopping list. | F39: Finance | H39: 2.1.1.5 作为收银员，我需要新 POS 系统能够在商品添加到购物清单时检查其是否可销售，并在不可销售时显示提示信息，以确保购物清单中不会包含不可销售的商品。 | I39: 财务 | N39: 购物清单-添加时校验商品可用状态 | O39: 商品售卖状态在初始化时售卖状态应该拿到，直接校验（0.5） | P39: Android | Q39: =BRD_EPIC2[[#This Row],[system type]]&BRD_EPIC2[[#This Row],[system type2]] -> Android & QA & PM & DM & UI | R39: & QA & PM & DM & UI | U39: 2 | V39: =$U39*DE_Cost!$B$1*8 -> 19.2 | W39: =$U39*DE_Cost!$B$1 -> 2.4 | X39: 0 | Y39: 0 | Z39: =LEN(Q39) - LEN(SUBSTITUTE(Q39, "&", "")) + 1 -> 5 | AA39: Y
A40: 1(Minimum scope) | B40: 2. Foundation operational functions 基础运营功能 | C40: 2.1 Merch & FnB product ordering 商品&餐饮点单 | D40: 2.1.2 [FnB] QSR ordering|Ordering with add/delete meal on QSR 开单与添加删除商品 | E40: 2.1.2.1 As FnB cashier, I need New POS will be able to add/delete meal to shopping list by barcode scanning or tap button, as to process shopping in restaurant ordering. | F40: 1. Add single item/meal/service to list. 2. Delete product in shopping list. | H40: 2.1.2.1 作为餐饮收银员，我需要新 POS 系统能够通过条形码扫描或点击按钮来添加/删除购物清单中的餐品，以便处理餐厅订单。 | I40: 1. 将单个商品/餐点/服务添加到列表。 2. 删除购物车中的产品。 | N40: 购物清单-添加+清单联动 | O40: 扫码触发逻辑、增删查同步、本地缓存 不包含硬件集成 | P40: Android | Q40: =BRD_EPIC2[[#This Row],[system type]]&BRD_EPIC2[[#This Row],[system type2]] -> Android & QA & PM & DM & UI | R40: & QA & PM & DM & UI | U40: 5 | V40: =$U40*DE_Cost!$B$1*8 -> 48 | W40: =$U40*DE_Cost!$B$1 -> 6 | X40: 0 | Y40: 0 | Z40: =LEN(Q40) - LEN(SUBSTITUTE(Q40, "&", "")) + 1 -> 5 | AA40: N | AB40: 推荐5人天, 见2.1.1.1
A41: 1(Minimum scope) | B41: 2. Foundation operational functions 基础运营功能 | C41: 2.1 Merch & FnB product ordering 商品&餐饮点单 | D41: 2.1.2 [FnB] QSR ordering|Modify meal/set/Condiments configuration 调整单品、套餐与调料 | E41: 2.1.2.2 As FnB cashier, I need New POS will be able to modify meal/set/condiments configuration in shopping list, as to process shopping in restaurant ordering. | F41: Sync to kitchen printer for order detail. Condiments may deduct inventory or not deduct(depending on the case) | H41: 2.1.2.2 作为餐饮收银员，我需要新 POS 系统能够在购物清单中修改餐食/套餐/调味品配置，以便处理餐厅订单的购物流程。 | I41: 同步到厨房打印机以获取订单详情。 调味品可能会扣除库存，也可能不扣除（视情况而定） | N41: 购物清单-获取厨房订单信息 | O41: 配置的增删改查开发（2） 可视库存检查（1） 【无库存概念，部分餐饮有可售库存（不在这里估），打印同步不在这里估】 | P41: Android & Back-End | Q41: =BRD_EPIC2[[#This Row],[system type]]&BRD_EPIC2[[#This Row],[system type2]] -> Android & Back-End & QA & PM & DM & UI | R41: & QA & PM & DM & UI | U41: 3 | V41: =$U41*DE_Cost!$B$1*8 -> 28.8 | W41: =$U41*DE_Cost!$B$1 -> 3.6 | X41: 0 | Y41: 0 | Z41: =LEN(Q41) - LEN(SUBSTITUTE(Q41, "&", "")) + 1 -> 6 | AA41: Y
A42: 1(Minimum scope) | B42: 2. Foundation operational functions 基础运营功能 | C42: 2.1 Merch & FnB product ordering 商品&餐饮点单 | D42: 2.1.2 [FnB] QSR ordering|Add remark for kitchen 增加厨房备注 | E42: 2.1.2.3 As FnB cashier, I need New POS will be able to add kitchen remark or special information on order/items level, as to process shopping in restaurant ordering. | F42: Sync to kitchen printer for order detail | H42: 2.1.2.3 作为餐饮收银员，我需要新 POS 系统能够在订单/项目级别添加厨房备注或特殊信息，以便处理餐厅购物订单。 | I42: 同步到厨房打印机以获取订单详情 | N42: 订单中菜品的备注信息 | O42: 厨房备注修改 | P42: Android | Q42: =BRD_EPIC2[[#This Row],[system type]]&BRD_EPIC2[[#This Row],[system type2]] -> Android & QA & PM & DM & UI | R42: & QA & PM & DM & UI | U42: 2 | V42: =$U42*DE_Cost!$B$1*8 -> 19.2 | W42: =$U42*DE_Cost!$B$1 -> 2.4 | X42: 0 | Y42: 0 | Z42: =LEN(Q42) - LEN(SUBSTITUTE(Q42, "&", "")) + 1 -> 5 | AA42: Y
A43: 1(Minimum scope) | B43: 2. Foundation operational functions 基础运营功能 | C43: 2.1 Merch & FnB product ordering 商品&餐饮点单 | D43: 2.1.2 [FnB] QSR ordering|Modify meal quantity/price in shopping list 调整数量与复制，修改价格 | E43: 2.1.2.4 As FnB cashier, I need New POS will be able to modify meal quantity or price in shopping list, as to process shopping in restaurant ordering. | F43: 1. Press “+, -” or entering number to adjust item qty 2. Able to duplicate added product 3. Pricing change can only be process by GSM/Lead authorized, and not impact its price in foundation data. GSM/Lead authorized needed. | H43: 2.1.2.4 作为餐饮收银员，我需要新 POS 系统能够修改购物清单中的餐品数量或价格，以便处理餐厅订单的购物流程。 | I43: 1. 按“+、-”或输入数字调整商品数量 2. 能够复制添加的产品 3. 价格更改只能由GSM/主管授权处理，且不影响基础数据中的价格。需要GSM/主管授权。 | N43: 购物清单-餐厅订单 | O43: 1.调整数量，2.复制商品（1） 3.权限校验（弹窗输入主管工号/密码？这个功能应该是有单独工时跟进）（1） | P43: Android & Back-End | Q43: =BRD_EPIC2[[#This Row],[system type]]&BRD_EPIC2[[#This Row],[system type2]] -> Android & Back-End & QA & PM & DM & UI | R43: & QA & PM & DM & UI | U43: 2 | V43: =$U43*DE_Cost!$B$1*8 -> 19.2 | W43: =$U43*DE_Cost!$B$1 -> 2.4 | X43: 0 | Y43: 0 | Z43: =LEN(Q43) - LEN(SUBSTITUTE(Q43, "&", "")) + 1 -> 6 | AA43: Y
A44: 1(Minimum scope) | B44: 2. Foundation operational functions 基础运营功能 | C44: 2.1 Merch & FnB product ordering 商品&餐饮点单 | D44: 2.1.2 [FnB] QSR ordering|Display inventory and prompt sold out 显示库存并提示即将售罄 | E44: 2.1.2.5 As FnB cashier, I need New POS will be able to display inventory and prompt sell out when remaining qty is below a certain threshold by meal, as to prevent over sales in restaurant ordering. | F44: Inventory prompt threshold is configurable. | H44: 2.1.2.5 作为餐饮收银员，我需要新 POS 系统能够按餐次显示库存并在剩余数量低于特定阈值时提示售罄，以防止餐厅订单中的超量销售。 | I44: 库存提示阈值可配置。 | N44: 购物清单-库存 | O44: 1.Android购物清单需要校验提示售罄 2.服务端取库存信息，正常来说是个查询 | P44: Android & Back-End | Q44: =BRD_EPIC2[[#This Row],[system type]]&BRD_EPIC2[[#This Row],[system type2]] -> Android & Back-End & QA & PM & DM & UI | R44: & QA & PM & DM & UI | U44: 2 | V44: =$U44*DE_Cost!$B$1*8 -> 19.2 | W44: =$U44*DE_Cost!$B$1 -> 2.4 | X44: 0 | Y44: 0 | Z44: =LEN(Q44) - LEN(SUBSTITUTE(Q44, "&", "")) + 1 -> 6 | AA44: Y
A45: 1(Minimum scope) | B45: 2. Foundation operational functions 基础运营功能 | C45: 2.1 Merch & FnB product ordering 商品&餐饮点单 | D45: 2.1.3 [FnB] TSR ordering|Add/delete meal to table order w/service fee on TSR TSR桌台点单（部分点位含服务费） | E45: 2.1.3.1 As FnB cashier, I need New POS will be able to add/delete meal/set/service (w/ service fee) to order after open table, as to process shopping in dinning . | F45: 1. Input number of guests to open table, and guest type is optional(walk-in/hotel/reserved) 2. Enable to add/delete meal, seat, change quantity/service fee, change table, merge tables, pending to draft/get from draft, re-purchase 3.Condiments may deduct inventory or not deduct(depending on the case) 4. Customize product and kitchen remark to item/order level 5. Inventory deduction or not when editing saved check | H45: 2.1.3.1 作为餐饮收银员，我需要新 POS 系统能够在开台后向订单中添加/删除餐品/套餐/服务（含服务费），以便处理餐饮消费。 | I45: 1. 输入客人人数以打开餐桌，客人类型可选（散客/酒店/预订） 2. 能够添加/删除餐点、座位，更改数量/服务费，更改餐桌，合并餐桌，挂起到草稿/从草稿中获取，重新购买 3. 调味品可能会扣除库存，也可能不扣除（视情况而定） 4. 自定义产品和厨房备注到商品/订单级别 5. 编辑已保存的账单时是否扣除库存 | N45: 开台-订单 | O45: TSR业务 1.客数修改，类型调整（1） 2.（3） 3.（1） 4.（1） 5.（1） | P45: Android & Back-End | Q45: =BRD_EPIC2[[#This Row],[system type]]&BRD_EPIC2[[#This Row],[system type2]] -> Android & Back-End & QA & PM & DM & UI | R45: & QA & PM & DM & UI | S45: 按商品属性去控制是否扣库存 有库存管理的就扣 | U45: 15 | V45: =$U45*DE_Cost!$B$1*8 -> 144 | W45: =$U45*DE_Cost!$B$1 -> 18 | X45: 0 | Y45: 0 | Z45: =LEN(Q45) - LEN(SUBSTITUTE(Q45, "&", "")) + 1 -> 6 | AA45: Y
A46: 1(Minimum scope) | B46: 2. Foundation operational functions 基础运营功能 | C46: 2.1 Merch & FnB product ordering 商品&餐饮点单 | D46: 2.1.3 [FnB] TSR ordering|Buffet order(Cast-serve and guest-self service) 自助餐点单(CM上菜/客人自助) | E46: 2.1.3.2 As FnB cashier, I need New POS will be able to add/delete buffet order after open table by cast, as to process shopping in dinning. | F46: 1. Enable to order buffet products and items 2. Enable to order a-la-carte item | H46: 2.1.3.2 作为餐饮收银员，我需要新 POS 系统能够按班次在开台后添加/删除自助餐订单，以便处理餐饮消费。 | I46: 1. 能够订购自助餐产品和商品 2. 能够点菜 | N46: 开台-订单-添加商品 | O46: TSR业务 继续增加在原有订单上（2） | P46: Android & Back-End | Q46: =BRD_EPIC2[[#This Row],[system type]]&BRD_EPIC2[[#This Row],[system type2]] -> Android & Back-End & QA & PM & DM & UI | R46: & QA & PM & DM & UI | U46: 3 | V46: =$U46*DE_Cost!$B$1*8 -> 28.8 | W46: =$U46*DE_Cost!$B$1 -> 3.6 | X46: 0 | Y46: 0 | Z46: =LEN(Q46) - LEN(SUBSTITUTE(Q46, "&", "")) + 1 -> 6 | AA46: Y
A47: 1(Minimum scope) | B47: 2. Foundation operational functions 基础运营功能 | C47: 2.1 Merch & FnB product ordering 商品&餐饮点单 | D47: 2.1.3 [FnB] TSR ordering|Banquet order 宴会点单 | E47: 2.1.3.4 As FnB cashier, I need New POS will be able to add/delete banquet order to after open tables, as to process shopping in dinning. | F47: 1. Input number of tables, guest count, order comments to open tables 2. Enable to add sales package/F&B/Misc/Merc/Ticketing /Rental to order | H47: 2.1.3.4 作为餐饮收银员，我需要新 POS 系统能够在开台后添加/删除宴会订单，以便处理餐饮消费。 | I47: 1. 输入餐桌数量、客人人数、订单备注以打开餐桌 2. 能够将销售套餐/餐饮/杂项/商品/票务/租赁添加到订单 | N47: 开台-订单-宴会订单 | O47: 宴会订单 1.（1） 2.将各类信息添加到订单中（2）（这些信息来源需要工时单独计算） | P47: Android & Back-End | Q47: =BRD_EPIC2[[#This Row],[system type]]&BRD_EPIC2[[#This Row],[system type2]] -> Android & Back-End & QA & PM & DM & UI | R47: & QA & PM & DM & UI | U47: 3 | V47: =$U47*DE_Cost!$B$1*8 -> 28.8 | W47: =$U47*DE_Cost!$B$1 -> 3.6 | X47: 0 | Y47: 0 | Z47: =LEN(Q47) - LEN(SUBSTITUTE(Q47, "&", "")) + 1 -> 6 | AA47: Y
A48: 1(Minimum scope) | B48: 2. Foundation operational functions 基础运营功能 | C48: 2.1 Merch & FnB product ordering 商品&餐饮点单 | D48: 2.1.3 [FnB] TSR ordering|Hotel room order(charge to room) 酒店客房点餐(挂房账) | E48: 2.1.3.5 As FnB cashier, I need New POS will be able to add/delete hotel order to room service, as to process shopping in hotel room dinning. | F48: [Similar as TSR ordering] 1. Number of guests needed to open table 2. Enable to add/delete meal, change quantity/service fee, pending to draft/get from draft, re-purchase 3. Customize product and kitchen remark to item/order level 4. Display the room charges status if refunded or not | G48: PMS-Opera | H48: 2.1.3.5 作为餐饮收银员，我需要新 POS 系统能够添加/删除酒店订单到客房服务，以便处理酒店客房内的餐饮消费。 | I48: 【类似于TSR订购】 1. 打开餐桌所需的客人人数 2. 能够添加/删除餐点，更改数量/服务费，挂起到草稿/从草稿中获取，重新购买 3. 自定义产品和厨房备注到商品/订单级别 4. 如果已退款，则显示房间费用状态 | N48: 酒店订单到客房服务 | O48: 1.落座人数update（0.5） 2.（1） 3.（1） 4.（0.5） | P48: Android & Back-End | Q48: =BRD_EPIC2[[#This Row],[system type]]&BRD_EPIC2[[#This Row],[system type2]] -> Android & Back-End & QA & PM & DM & UI | R48: & QA & PM & DM & UI | U48: 3 | V48: =$U48*DE_Cost!$B$1*8 -> 28.8 | W48: =$U48*DE_Cost!$B$1 -> 3.6 | X48: 0 | Y48: 0 | Z48: =LEN(Q48) - LEN(SUBSTITUTE(Q48, "&", "")) + 1 -> 6 | AA48: Y
A49: 1(Minimum scope) | B49: 2. Foundation operational functions 基础运营功能 | C49: 2.1 Merch & FnB product ordering 商品&餐饮点单 | D49: 2.1.3 [FnB] TSR ordering|Change/cancel table order on TSR 合并桌台/变更桌台/取消桌台 | E49: 2.1.3.6 As FnB cashier, I need New POS will be able to change table or cancel meal/set/service to order after open table, as to fulfill guest request in dinning. | H49: 2.1.3.6 作为餐饮收银员，我需要新 POS 系统能够在开台后更改餐桌或取消餐点/套餐/服务，以满足客人在用餐过程中的需求。 | N49: TSR 合并桌台/变更桌台/取消桌台 | O49: 餐桌状态流转，伴随着订单状态流转 | P49: Android & Back-End | Q49: =BRD_EPIC2[[#This Row],[system type]]&BRD_EPIC2[[#This Row],[system type2]] -> Android & Back-End & QA & PM & DM & UI | R49: & QA & PM & DM & UI | U49: 4 | V49: =$U49*DE_Cost!$B$1*8 -> 38.4 | W49: =$U49*DE_Cost!$B$1 -> 4.8 | X49: 0 | Y49: 0 | Z49: =LEN(Q49) - LEN(SUBSTITUTE(Q49, "&", "")) + 1 -> 6 | AA49: Y
A50: 1(Minimum scope) | B50: 2. Foundation operational functions 基础运营功能 | C50: 2.10 Operational reports 运营报表 | D50: 2.10.1 Sales report|Location sales report 门店销售报表 | E50: 2.10.1.1 As Ops admin & cashier, I need New POS will be able to customized reports output format and result fields, as to fulfill operations reporting requirements. | F50: Including custom report formats, custom data sources and fields, binding fields to the compound, designing report styles, adding custom events and publishing reports. | G50: report | H50: 2.10.1.1 作为运营管理员和收银员，我需要新 POS 系统能够自定义报表输出格式和结果字段，以满足运营报告需求。 | I50: 包括自定义报表格式、自定义数据源和字段、将字段绑定到复合项、设计报表样式、添加自定义事件和发布报表。 | N50: 在POS后台展示报表需求 | O50: 报表筛选，数据准确性 | P50: Front-End & Back-End | Q50: =BRD_EPIC2[[#This Row],[system type]]&BRD_EPIC2[[#This Row],[system type2]] -> Front-End & Back-End & QA & PM & DM & UI | R50: & QA & PM & DM & UI | T50: 待确定 | U50: 10 | V50: =$U50*DE_Cost!$B$1*8 -> 96 | W50: =$U50*DE_Cost!$B$1 -> 12 | Z50: =LEN(Q50) - LEN(SUBSTITUTE(Q50, "&", "")) + 1 -> 6 | AA50: N | AB50: PM: 涉及系统端有争议，报表理论无收银员无关
A51: 1(Minimum scope) | B51: 2. Foundation operational functions 基础运营功能 | C51: 2.10 Operational reports 运营报表 | D51: 2.10.1 Sales report|Merch sales/management reports 商品销售报表 | E51: 2.10.1.2 As Merch admin & cashier, I need New POS will be able to summary sales record as Merch current operations report with 9 categories (40 reports), as to fulfill operations reporting requirements. | F51: 包含9类共40张报表 1. Account info include: PERNER, name, phone, email, store, business type, joining time, title, button group, is ND. 2. Each account has a identifier field(e.g. PERNER/Email address) for identity. 3. Account creation require corresponding Line Manager approval. GSM/Lead/Administrator authorized needed | G51: report | H51: 2.10.1.2 作为商户管理员和收银员，我需要新 POS 系统能够将销售记录汇总为商户当前运营报告，包含 9 个类别（40 份报告），以满足运营报告需求。 | I51: 包含9类共40张报表 1. 帐户信息包括：PERNER、姓名、电话、电子邮件、商店、业务类型、加入时间、职称、按钮组、是否为ND。 2. 每个帐户都有一个标识符字段（例如PERNER/电子邮件地址）用于身份验证。 3. 帐户创建需要相应的直线经理批准。需要GSM/主管/管理员授权 | N51: 按照不同类型划分过滤出不同的结果集合，才生40份reports | O51: 1. UI（1） + 数据组合（1） 3.授权（1） | P51: Front-End & Back-End | Q51: =BRD_EPIC2[[#This Row],[system type]]&BRD_EPIC2[[#This Row],[system type2]] -> Front-End & Back-End & QA & PM & DM & UI | R51: & QA & PM & DM & UI | T51: 待确定 | U51: 100 | V51: =$U51*DE_Cost!$B$1*8 -> 960 | W51: =$U51*DE_Cost!$B$1 -> 120 | Z51: =LEN(Q51) - LEN(SUBSTITUTE(Q51, "&", "")) + 1 -> 6 | AA51: N | AB51: PM: 涉及系统端有争议，报表理论无收银员无关
A52: 1(Minimum scope) | B52: 2. Foundation operational functions 基础运营功能 | C52: 2.10 Operational reports 运营报表 | D52: 2.10.1 Sales report|FnB location sales report 餐饮销售报表 | E52: 2.10.1.3 As FnB admin & cashier, I need New POS will be able to summary sales record as FnB current operations report for location closed, as to fulfill operations reporting requirements. | F52: 1. Field including: sales report/transaction report(by payment method)/cash drawer report/coupon and discount report, and actual receipt statements for payment methods, and the accounts receivable statements for sales categories. 2. Display daily report, but POS frontend stores 3 days of report data) | G52: report | H52: 2.10.1.3 作为餐饮部管理员和收银员，我需要新 POS 系统能够为已关闭的门店汇总销售记录作为餐饮部当前运营报告，以满足运营报告要求。 | I52: 1. 字段包括：销售报告/交易报告（按支付方式）/收银机报告/优惠券和折扣报告，以及支付方式的实际收据报表，以及销售类别的应收账款报表。 2. 显示每日报告，但POS前端存储3天的报告数据） | N52: 基础报表+POS端报告数据 | O52: 1.基础报表 2.Android本地缓存数据 | P52: Android & Front-End & Back-End | Q52: =BRD_EPIC2[[#This Row],[system type]]&BRD_EPIC2[[#This Row],[system type2]] -> Android & Front-End & Back-End & QA & PM & DM & UI | R52: & QA & PM & DM & UI | U52: 15 | V52: =$U52*DE_Cost!$B$1*8 -> 144 | W52: =$U52*DE_Cost!$B$1 -> 18 | Z52: =LEN(Q52) - LEN(SUBSTITUTE(Q52, "&", "")) + 1 -> 7 | AA52: N | AB52: PM: 这报表也涉及收银端么？
A53: 1(Minimum scope) | B53: 2. Foundation operational functions 基础运营功能 | C53: 2.11 Finance Processing and Configuration 财务处理和配置 | D53: 2.11.1 Refund Finance Processing| Auto refund of single payment 由退货触发自动退款（单一支付方式） | E53: 2.11.1.1 As Finance admin, I want to accept auto refund of products paid through single payment method so that I can refund through original payment method. | F53: 1. Preconditions as Merch/FnB operations requirements, need to input return reason 2. If auto refund fails, should pop up system message to prompt manual refund, 3. Refund transaction should link back to original transaction. 4. Backend scenarios include: 1) Same store refund, 2) Different store same company refund (store ID should be captured), 3) Different store different company refund (store ID should be captured) | G53: Finance | H53: 2.11.1.1 作为财务管理员，我希望接受通过单一支付方式支付的产品自动退款，以便能够通过原始支付方式进行退款。 | I53: 1. 作为Merch/FnB运营要求的前提条件，需要输入退货原因 2. 如果自动退款失败，应弹出系统消息提示手动退款， 3. 退款交易应链接回原始交易。 4. 后端场景包括：1) 同店退款，2) 不同店同公司退款（应捕获商店ID），3) 不同店不同公司退款（应捕获商店ID） | J53: 同上 | K53: Lucky & Vetas | N53: 退款操作-单一支付方式 | O53: 1.输入退款原因（1） 2.自动退款调用+手动退款调用（2） 3.关联交易（1） 4.不同场景（1） 退款链路完善，只是对接情况（5） | P53: Front-End & Back-End | Q53: =BRD_EPIC2[[#This Row],[system type]]&BRD_EPIC2[[#This Row],[system type2]] -> Front-End & Back-End & QA & PM & DM & UI | R53: & QA & PM & DM & UI | U53: 15 | V53: =$U53*DE_Cost!$B$1*8 -> 144 | W53: =$U53*DE_Cost!$B$1 -> 18 | Z53: =LEN(Q53) - LEN(SUBSTITUTE(Q53, "&", "")) + 1 -> 6 | AA53: Y
A54: 1(Minimum scope) | B54: 2. Foundation operational functions 基础运营功能 | C54: 2.11 Finance Processing and Configuration 财务处理和配置 | D54: 2.11.1 Refund Finance Processing| Auto refund of combined payment 由退货触发自动退款（混合支付方式） | E54: 2.11.1.2 As Finance admin, I want to accept auto refund of products paid through combined payment so that I can select refund method to guest. | F54: 1. Preconditions as Merch/FnB operations requirements, need to input return reason 2. Cashier can select the refund payment from original combined payment methods. 3. If auto refund fails, should pop up system message to prompt manual refund. 4. Refund transaction should link back to original transaction. 5. Backend scenarios: 1) Same store refund, 2) Different store same company refund (store ID should be captured), 3) Different store different company refund (store ID should be captured) | G54: Finance | H54: 2.11.1.2 作为财务管理员，我希望接受通过组合支付方式购买的产品自动退款，以便我可以选择退款方式给客人。 | I54: 1. 作为Merch/FnB运营要求的前提条件，需要输入退货原因 2. 收银员可以从原始组合支付方式中选择退款支付。 3. 如果自动退款失败，应弹出系统消息提示手动退款。 4. 退款交易应链接回原始交易。 5. 后端场景：1) 同店退款，2) 不同店同公司退款（应捕获商店ID），3) 不同店不同公司退款（应捕获商店ID） | J54: POS发起自动退款，调Payment Service退款 Payment Service需要提供自动退款接口 | K54: Lucky & Vetas | N54: 退款操作-组合支付方式 | O54: 1.输入退款原因（1） 2.原始支付方式退款（2） 3.自动退款调用+手动退款调用（2+1） 4.链接回原始交易（1） 5.不同场景（1） 退款链路完善，仅对接情况（5） | P54: Front-End & Back-End | Q54: =BRD_EPIC2[[#This Row],[system type]]&BRD_EPIC2[[#This Row],[system type2]] -> Front-End & Back-End & QA & PM & DM & UI | R54: & QA & PM & DM & UI | U54: 15 | V54: =$U54*DE_Cost!$B$1*8 -> 144 | W54: =$U54*DE_Cost!$B$1 -> 18 | Z54: =LEN(Q54) - LEN(SUBSTITUTE(Q54, "&", "")) + 1 -> 6 | AA54: Y
A55: 1(Minimum scope) | B55: 2. Foundation operational functions 基础运营功能 | C55: 2.11 Finance Processing and Configuration 财务处理和配置 | D55: 2.11.1 Refund Finance Processing| Manual refund after auto refund failure 自动触发退款失败后手工发起退款 | E55: 2.11.1.3 As Finance admin, I want New POS to prompt alert with popup when payment refund is unsuccessful and provide selection of NonCash Code for manual refund methods, so that I can process guest refund accordingly. | G55: Finance | H55: 2.11.1.3 作为财务管理员，我希望新 POS 在支付退款失败时弹出提示警报，并提供非现金代码选项用于手动退款方法，以便我能够相应地为客人处理退款。 | J55: 同上 | K55: Lucky & Vetas | N55: 退款操作-失败报警-手动退款 | O55: 对接退款 （2） 手动退款方式（1） 退款链路完善，仅对接情况（5） | P55: Android & Back-End | Q55: =BRD_EPIC2[[#This Row],[system type]]&BRD_EPIC2[[#This Row],[system type2]] -> Android & Back-End & QA & PM & DM & UI | R55: & QA & PM & DM & UI | U55: 10 | V55: =$U55*DE_Cost!$B$1*8 -> 96 | W55: =$U55*DE_Cost!$B$1 -> 12 | Z55: =LEN(Q55) - LEN(SUBSTITUTE(Q55, "&", "")) + 1 -> 6 | AA55: Y
A56: 1(Minimum scope) | B56: 2. Foundation operational functions 基础运营功能 | C56: 2.11 Finance Processing and Configuration 财务处理和配置 | D56: 2.11.1 Refund Finance Processing| Manual refund 手工执行退款 | E56: 2.11.1.4 As Finance admin, I want to conduct manual refund for products so that I can successfully refund payment to guest. | F56: 1. Preconditions as Merch/FnB operations requirements. 2. Select refund method from available configured buttons. 3. Backend scenarios: 1) Same store refund, 2) Different store same company refund, 3) Different store different company refund | G56: Finance | H56: 2.11.1.4 作为财务管理员，我希望能够手动为产品退款，以便成功向客人退还付款。 | I56: 1. 作为Merch/FnB运营要求的前提条件。 2. 从可用的已配置按钮中选择退款方式。 3. 后端场景：1) 同店退款，2) 不同店同公司退款，3) 不同店不同公司退款 | J56: 同上 | K56: Lucky & Vetas | N56: 退款操作-手动退款 | O56: 从后台触发退款操作（5） 退款链路完善，仅对接情况（5） | P56: Front-End & Back-End | Q56: =BRD_EPIC2[[#This Row],[system type]]&BRD_EPIC2[[#This Row],[system type2]] -> Front-End & Back-End & QA & PM & DM & UI | R56: & QA & PM & DM & UI | U56: 10 | V56: =$U56*DE_Cost!$B$1*8 -> 96 | W56: =$U56*DE_Cost!$B$1 -> 12 | Z56: =LEN(Q56) - LEN(SUBSTITUTE(Q56, "&", "")) + 1 -> 6 | AA56: Y
A57: 1(Minimum scope) | B57: 2. Foundation operational functions 基础运营功能 | C57: 2.11 Finance Processing and Configuration 财务处理和配置 | D57: 2.11.1 Refund Finance Processing| NonCashCode manual refund 手工执行Noncash Code退款 | E57: 2.11.1.5 As Finance admin, I want to select NonCashCode as a refund method, so that I can refund order or products that were paid through NonCashCodes. | G57: Finance | H57: 2.11.1.5 作为财务管理员，我希望选择 NonCashCode 作为退款方式，以便能够退还通过 NonCashCode 支付的订单或产品。 | J57: 同上 | K57: Lucky & Vetas | N57: 退款操作-NonCashCode | O57: NonCashCode 方式退款（2） 退款链路完善，仅对接情况（5） | P57: Front-End & Back-End | Q57: =BRD_EPIC2[[#This Row],[system type]]&BRD_EPIC2[[#This Row],[system type2]] -> Front-End & Back-End & QA & PM & DM & UI | R57: & QA & PM & DM & UI | T57: 待确定 | U57: 10 | V57: =$U57*DE_Cost!$B$1*8 -> 96 | W57: =$U57*DE_Cost!$B$1 -> 12 | Z57: =LEN(Q57) - LEN(SUBSTITUTE(Q57, "&", "")) + 1 -> 6 | AA57: Y
A58: 1(Minimum scope) | B58: 2. Foundation operational functions 基础运营功能 | C58: 2.11 Finance Processing and Configuration 财务处理和配置 | D58: 2.11.2 Payment Finance Configuration| Enable rounding off/up 配置金额舍入规则 | E58: 2.11.2.1 As Finance admin, I need New POS will be able to configure rounding for each payment item by store and payment method | F58: 1) Rounding in cash as: Decimal places, Round up, Round down, Round off, Round before/after calculation. 2) Round by priority, and apply to check amount, refund amount, payment/refund method, discount/coupon/other benefit, services fee, item amount. | G58: Finance | H58: 2.11.2.1 作为财务管理员，我需要新 POS 能够按商店和支付方式为每个payment 项 配置舍入规则 | I58: 1) 现金舍入方式：小数位数、向上舍入、向下舍入、四舍五入、计算前/后舍入。 2) 按优先级舍入，并应用于检查金额、退款金额、支付/退款方式、折扣/优惠券/其他优惠、服务费、项目金额。 | J58: PIP上也需要配置，金额不一致？ | K58: Lucky | N58: 配置-payment item-配置舍入规则 | O58: admin配置规则，计算金额的舍入规则配置（2） 按照优先级舍入（1） 带上具体执行逻辑（7） | P58: Android & Front-End & Back-End | Q58: =BRD_EPIC2[[#This Row],[system type]]&BRD_EPIC2[[#This Row],[system type2]] -> Android & Front-End & Back-End & QA & PM & DM & UI | R58: & QA & PM & DM & UI | U58: 10 | V58: =$U58*DE_Cost!$B$1*8 -> 96 | W58: =$U58*DE_Cost!$B$1 -> 12 | Z58: =LEN(Q58) - LEN(SUBSTITUTE(Q58, "&", "")) + 1 -> 7 | AA58: Y
A59: 1(Minimum scope) | B59: 2. Foundation operational functions 基础运营功能 | C59: 2.11 Finance Processing and Configuration 财务处理和配置 | D59: 2.11.2 Payment Finance Configuration| Configuration of NonCash Codes 配置NonCash Code | E59: 2.11.2.2 As Finance admin, I want to configure NonCash Code payment methods from NewPOS backend, so that Ops Cashier can select appropriate NonCash Code payment method to process guest payment. | G59: Finance | H59: 2.11.2.2 作为财务管理员，我希望从 NewPOS 后端配置非现金代码支付方式，以便运营收银员能够选择合适的非现金代码支付方式来处理客人付款。 | J59: POS配置code，调Payment Service拿到支付方式配置的Mapping关系 | K59: Lucky & Vetas | N59: 配置-NonCashCode-付款 | O59: admin配置规则（1） 规则生效至PIS（1） | P59: Front-End & Back-End | Q59: =BRD_EPIC2[[#This Row],[system type]]&BRD_EPIC2[[#This Row],[system type2]] -> Front-End & Back-End & QA & PM & DM & UI | R59: & QA & PM & DM & UI | U59: 4 | V59: =$U59*DE_Cost!$B$1*8 -> 38.4 | W59: =$U59*DE_Cost!$B$1 -> 4.8 | Z59: =LEN(Q59) - LEN(SUBSTITUTE(Q59, "&", "")) + 1 -> 6 | AA59: Y | AD59: =U59 * Z59 -> 24
A60: 1(Minimum scope) | B60: 2. Foundation operational functions 基础运营功能 | C60: 2.11 Finance Processing and Configuration 财务处理和配置 | D60: 2.11.2 Payment Finance Configuration| NonCash Code payment 配置NonCash Code支付 | E60: 2.11.2.3 As Ops Cashier, I want New POS to support manual selection of Non CashCode as a payment method, so that I can complete payment process for guest | G60: Finance | H60: 2.11.2.3 作为收银员，我希望新 POS 系统能支持手动选择 Non CashCode 作为支付方式，以便我能为客人完成支付流程 | J60: 同上 | K60: Lucky & Vetas | N60: 配置-NonCashCode-付款 | O60: admin生效配置，（1） Android端去支持NonCashCode-付款（1） PIS调试（2） | P60: Android & Front-End & Back-End | Q60: =BRD_EPIC2[[#This Row],[system type]]&BRD_EPIC2[[#This Row],[system type2]] -> Android & Front-End & Back-End & QA & PM & DM & UI | R60: & QA & PM & DM & UI | U60: 4 | V60: =$U60*DE_Cost!$B$1*8 -> 38.4 | W60: =$U60*DE_Cost!$B$1 -> 4.8 | Z60: =LEN(Q60) - LEN(SUBSTITUTE(Q60, "&", "")) + 1 -> 7 | AA60: Y | AD60: =U60 * Z60 -> 28
A61: 1(Minimum scope) | B61: 2. Foundation operational functions 基础运营功能 | C61: 2.11 Finance Processing and Configuration 财务处理和配置 | D61: 2.11.2 Payment Finance Configuration| Enable promotion in payment method 支付渠道促销 | E61: 2.11.2.4 As Finance admin, I need New POS will be able to configure payment promotions as SHDR self-operated activities, 3rd payment codes and specific channel promotions | F61: Transactions revenue on payment promotions should have a spitted amount for Financial accounting. By order by using specific payment method or by products by using specific payment method. | G61: Finance | H61: 2.11.2.4 作为财务管理员，我需要新 POS 能够将支付促销配置为 SHDR 自营活动、第三方支付代码和特定渠道促销 | I61: 支付促销的交易收入应为财务会计分配金额。 通过使用特定支付方式的订单或通过使用特定支付方式的产品。 | J61: 这个配置应该在对应支付渠道里配置 | K61: Lucky & Vetas | N61: 配置-支付促销-配置特定支付方式或产品 | O61: admin配置工作（2） Android端 集成并生效（3） PIS对接（5） | P61: Android & Front-End & Back-End | Q61: =BRD_EPIC2[[#This Row],[system type]]&BRD_EPIC2[[#This Row],[system type2]] -> Android & Front-End & Back-End & QA & PM & DM & UI | R61: & QA & PM & DM & UI | U61: 10 | V61: =$U61*DE_Cost!$B$1*8 -> 96 | W61: =$U61*DE_Cost!$B$1 -> 12 | Z61: =LEN(Q61) - LEN(SUBSTITUTE(Q61, "&", "")) + 1 -> 7 | AA61: Y | AD61: =U61 * Z61 -> 70
A62: 1(Minimum scope) | B62: 2. Foundation operational functions 基础运营功能 | C62: 2.11 Finance Processing and Configuration 财务处理和配置 | D62: 2.11.3 Finance Posting| Financial Master Data configuration 配置财务主数据 | E62: 2.11.3.1 As Finance operator, I want to configure financial master data(e.g company code, GL account, CC, PC.ect) corresponding to Merch/FnB products, transactions, location/terminal, revenue type etc. by single-item or batch upload, so that NewPOS sale & payment data can be correctly posted to SAP. | F62: FS-4 产品、产品分类、支付方式、渠道、门店、收银终端、订单、促销活动等相关功能下可以灵活的配置一些财务需要的相关数据属性，比如公司代码、财务科目、利润中心、收入类型、税率、财务物料号码、财务支付方式、零售客户代码、零售业务模式、财务接口标识、Bank out标识等等 | G62: Finance | H62: 2.11.3.1 作为财务操作员，我希望通过单项或批量上传配置与商户/餐饮产品、交易、地点/终端、收入类型等对应的财务主数据（如公司代码、总账科目、成本中心、利润中心等），以便 NewPOS 销售和支付数据能够正确过账到 SAP。 | I62: FS-4 产品、产品分类、支付方式、渠道、门店、收银终端、订单、促销活动等相关功能下可以灵活的配置一些财务需要的相关数据属性，比如公司代码、财务科目、利润中心、收入类型、税率、财务物料号码、财务支付方式、零售客户代码、零售业务模式、财务接口标识、Bank out标识等等 | K62: Vetas | Q62: =BRD_EPIC2[[#This Row],[system type]]&BRD_EPIC2[[#This Row],[system type2]] -> & QA & PM & DM & UI | R62: & QA & PM & DM & UI | Z62: =LEN(Q62) - LEN(SUBSTITUTE(Q62, "&", "")) + 1 -> 5 | AA62: Y | AD62: =U62 * Z62 -> 0
A63: 1(Minimum scope) | B63: 2. Foundation operational functions 基础运营功能 | C63: 2.11 Finance Processing and Configuration 财务处理和配置 | D63: 2.11.3 Finance Posting| Financial Master Data attributes configuration 配置财务附加主数据 | E63: 2.11.3.2 As Finance Operator, I want to add, edit, or delete additional financial attributes to Merch and FnB product master data so that I can conduct Financial analysis and not affect operational processes. | F63: FS-4 TBC - 配置权限 | G63: Finance | H63: 2.11.3.2 作为财务操作员，我想添加、编辑或删除 Merch 和 FnB 产品主数据的额外财务属性，以便我可以进行财务分析，同时不影响运营流程。 | I63: FS-4 TBC - 配置权限 | J63: 财务主数据需要带到FMP | K63: Lucky & Vetas | N63: 配置- Merch 和 FnB 产品主数据的额外财务属性 | O63: admin配置工作 | P63: Front-End & Back-End | Q63: =BRD_EPIC2[[#This Row],[system type]]&BRD_EPIC2[[#This Row],[system type2]] -> Front-End & Back-End & QA & PM & DM & UI | R63: & QA & PM & DM & UI | U63: 5 | V63: =$U63*DE_Cost!$B$1*8 -> 48 | W63: =$U63*DE_Cost!$B$1 -> 6 | Z63: =LEN(Q63) - LEN(SUBSTITUTE(Q63, "&", "")) + 1 -> 6 | AA63: Y | AD63: =U63 * Z63 -> 30
A64: 1(Minimum scope) | B64: 2. Foundation operational functions 基础运营功能 | C64: 2.11 Finance Processing and Configuration 财务处理和配置 | D64: 2.11.4 Finance Reports and Logs| Search, View, and Download Financial Reports and logs 查询，查看和下载财务报表和日志 | E64: 2.11.4.1 As a Finance admin, I want to search, and filter Financial Reports and Logs via different criteria, and view and download these Reports and Logs from New POS, so that I can conduct Financial Reconciliation and Finance Posting | F64: FS-8 Search Criteria: Order info, Payment info, Location info, Transaction date, Coupon redemption, Payment Promotions, Inventory deduction, Payment methods, Product Type, etc Eg of Financial Reports: Payments reports, Sales reports, Store Open / Close reports PCM-6 SA-5 | G64: Finance & Report | H64: 2.11.4.1 作为财务管理员，我希望能够通过不同条件搜索和筛选财务报表与日志，并在新 POS 系统中查看和下载这些报表与日志，以便进行财务对账和财务过账。 | I64: FS-8 搜索条件：订单信息、支付信息、位置信息、交易日期、优惠券兑换、支付促销、库存扣除、支付方式、产品类型等 财务报告示例：支付报告、销售报告、商店开/关报告 PCM-6 SA-5 | J64: 需要大概多少张表？大概表的内容 | K64: Lucky | L64: 10/24 18:00之前可以确认 本周五再拉会过需求 | N64: 报表与日志 | O64: 搜索筛选，下载 | P64: Front-End & Back-End | Q64: =BRD_EPIC2[[#This Row],[system type]]&BRD_EPIC2[[#This Row],[system type2]] -> Front-End & Back-End & QA & PM & DM & UI | R64: & QA & PM & DM & UI | T64: 待确定 | U64: 10 | V64: =$U64*DE_Cost!$B$1*8 -> 96 | W64: =$U64*DE_Cost!$B$1 -> 12 | Z64: =LEN(Q64) - LEN(SUBSTITUTE(Q64, "&", "")) + 1 -> 6 | AA64: Y | AD64: =U64 * Z64 -> 60
A65: 1(Minimum scope) | B65: 2. Foundation operational functions 基础运营功能 | C65: 2.11 Finance Processing and Configuration 财务处理和配置 | D65: 2.11.4 Finance Reports and Logs| Create customized Financial Reports and Logs 创建财务报表和日志 | E65: 2.11.4.2 As a Finance Operator, I want to be able to create customized Financial Reports and Logs via different filtering criteria and download them from the NewPOS Backend system, so that I can conduct Financial Reconciliation and Finance Posting. | F65: FS-8 | G65: Finance & Report | H65: 2.11.4.2 作为财务操作员，我希望能够通过不同的筛选条件创建自定义财务报表和日志，并从 NewPOS 后端系统下载它们，以便进行财务对账和财务过账。 | I65: FS-8 | J65: 只是条件筛选，字段过滤，并非汇总型报表 | K65: Lucky | M65: 找供应商确认，提供哪些定制化的报表 | N65: 报表与日志 | O65: 搜索筛选，下载 | P65: Front-End & Back-End | Q65: =BRD_EPIC2[[#This Row],[system type]]&BRD_EPIC2[[#This Row],[system type2]] -> Front-End & Back-End & QA & PM & DM & UI | R65: & QA & PM & DM & UI | T65: 待确定 | U65: 10 | V65: =$U65*DE_Cost!$B$1*8 -> 96 | W65: =$U65*DE_Cost!$B$1 -> 12 | Z65: =LEN(Q65) - LEN(SUBSTITUTE(Q65, "&", "")) + 1 -> 6 | AA65: Y | AD65: =U65 * Z65 -> 60
A66: 1(Minimum scope) | B66: 2. Foundation operational functions 基础运营功能 | C66: 2.11 Finance Processing and Configuration 财务处理和配置 | D66: 2.11.4 Finance Reports and Logs| Finance Reports and Logs access permissions 配置财务报表和日志的权限 | E66: 2.11.4.3 As a Finance Operator, I want NewPOS system to support role and access permissions specific to Finance users, so that only Finance users can have access to Finance-related data and Finance-related reports. | F66: FS-10 | G66: Finance & Report | H66: 2.11.4.3 作为财务操作员，我希望 NewPOS 系统能支持财务用户特定的角色和访问权限，以便只有财务用户才能访问财务相关数据和财务相关报告。" | I66: FS-10 | K66: Lucky | N66: 支持财务用户特定的角色和访问权限 | O66: 用户展示特定功能数据 | P66: Front-End & Back-End | Q66: =BRD_EPIC2[[#This Row],[system type]]&BRD_EPIC2[[#This Row],[system type2]] -> Front-End & Back-End & QA & PM & DM & UI | R66: & QA & PM & DM & UI | T66: 待确定 | U66: 10 | V66: =$U66*DE_Cost!$B$1*8 -> 96 | W66: =$U66*DE_Cost!$B$1 -> 12 | Z66: =LEN(Q66) - LEN(SUBSTITUTE(Q66, "&", "")) + 1 -> 6 | AA66: Y | AD66: =U66 * Z66 -> 60
A67: 1(Minimum scope) | B67: 2. Foundation operational functions 基础运营功能 | C67: 2.11 Finance Processing and Configuration 财务处理和配置 | D67: 2.11.4 Finance Reports and Logs| Longview Integration 集成Longview | E67: 2.11.4.4 As a Finance operator, I want NewPOS transactions to be sent to Longview (financial forcast & planning) system according to longview interface specifications, so that I can conduct financial forcast & planning for Merch and Fnb. | G67: Finance | H67: 2.11.4.4 作为财务操作员，我希望根据 Longview 接口规范将 NewPOS 交易发送到 Longview（财务预测与规划）系统，以便我可以对商户和餐饮业务进行财务预测与规划。 | K67: Lucky & Vetas | N67: 发送交易数据到 Longview | O67: 后端对接联调 | P67: Back-End | Q67: =BRD_EPIC2[[#This Row],[system type]]&BRD_EPIC2[[#This Row],[system type2]] -> Back-End& QA & PM & DM | R67: & QA & PM & DM | U67: 10 | V67: =$U67*DE_Cost!$B$1*8 -> 96 | W67: =$U67*DE_Cost!$B$1 -> 12 | Z67: =LEN(Q67) - LEN(SUBSTITUTE(Q67, "&", "")) + 1 -> 4 | AA67: Y | AD67: =U67 * Z67 -> 40
A68: 1(Minimum scope) | B68: 2. Foundation operational functions 基础运营功能 | C68: 2.11 Finance Processing and Configuration 财务处理和配置 | D68: 2.11.4 Finance Reports and Logs| Store Inventory report 门店库存报表 | E68: 2.11.4.5 As a Finance operator, I want to have inventory information in NEW POS report, so that I can conduct Merch item revenue and cost. | G68: Finance & Report | H68: 2.11.4.5 作为财务操作员，我希望 NEW POS 报告中包含库存信息，以便我能进行商品项目的收入和成本核算。 | K68: Lucky | N68: 报表与日志-包含库存信息 | O68: 库存数据同步单独工时 | P68: Front-End & Back-End | Q68: =BRD_EPIC2[[#This Row],[system type]]&BRD_EPIC2[[#This Row],[system type2]] -> Front-End & Back-End & QA & PM & DM & UI | R68: & QA & PM & DM & UI | T68: 待确定 | U68: 10 | V68: =$U68*DE_Cost!$B$1*8 -> 96 | W68: =$U68*DE_Cost!$B$1 -> 12 | Z68: =LEN(Q68) - LEN(SUBSTITUTE(Q68, "&", "")) + 1 -> 6 | AA68: Y | AD68: =U68 * Z68 -> 60
A69: 1(Minimum scope) | B69: 2. Foundation operational functions 基础运营功能 | C69: 2.2 Non-coupon promotion and discount(POS promotion) (非优惠券类)促销与折扣 | D69: 2.2.1 Non-coupon promotion configuration|Setup POS promotion type 定义促销类型 | E69: 2.2.1.1 As Ops admin, I need New POS will be able to configure POS promotion type which available in the store, and publish promotion after approval, as to define promotion in ordering. | F69: 1. Include: GWP (Gift with Purchase), PWP (Purchase with Purchase), Bundle, Discount, Tier Discount, and coupon availability. Promotion from SIMBA include： A. Item Level Offers (PWP/Purchase with purchase, GWP/Gift with Purchase) Simple Discount - Get Y for Discount - 25% off all summer products Purchase with purchase - Buy X, Get Discount - Buy any 3 kids’ T-shirts, get CNY 10 off Purchase with purchase - Spend X, Get Discount - Spend CNY 50 in Toys, get CNY 5 off Purchase with purchase - Buy X, Get Y for Discount -Buy 2 T-shirts; get a toy for 50% off Purchase with purchase - Spend X, Get Y for Discount - Spend CNY 100 on jewelry, get 25% off any 2 toys Purchase with purchase - Buy X of Single Item for Discount -Buy 2 bags for CNY 50 Purchase with purchase - Buy X and Y, Get Discount -Buy a plush, keychain, and backpack for CNY 20.00 Purchase with purchase - Buy X and Y, Get Z for Discount - Buy a scarf and hat, get 50% off gloves Gift with Purchase - Buy X, Get Gift with Purchase -Buy any 2 Duffy items, get a free beach towel B. Transaction Level Offers Simple Discount - Get Discount -10% off your purchase today only Buy/Get -Buy X, Get Discount -Buy 3 t-shirts, get CNY 10 off on your purchase Buy/Get -Spend X, Get Discount - Spend CNY 100 on Toy’s sets, get 5% off your purchase C. Conflicts – Controlled via POS option Promotion on an item that is on clearance Overlapping promotions When there are overlapping promotions, POS dictates what takes priority. 2. Enable to define by batch upload/modify, administrator authorized approval. | G69: New Simba | H69: 2.2.1.1 作为运营管理员，我需要新的POS系统能够配置门店可用的促销类型，并在审批通过后发布促销活动，以便在订单处理过程中实现促销规则的定义。 | I69: 1. 包含以下类型：赠品促销、加价购、捆绑销售、折扣、阶梯折扣以及优惠券可用性。来自SIMBA系统的促销包括： A. 商品层级促销 ▪简单折扣 - 指定商品享受折扣 - 夏季商品全场25% off ▪购买条件折扣 - 买X，享折扣 - 任意购买3件儿童T恤，立减10元 ▪购买条件折扣 - 消费满X，享折扣 - 玩具类消费满50元，立减5元 ▪购买条件折扣 - 买X，Y商品享折扣 - 购买2件T恤，一件玩具享受5折 ▪购买条件折扣 - 消费满X，Y商品享折扣 - 珠宝消费满100元，任意2件玩具享受75折 ▪购买条件折扣 - 单商品买X件享折扣 - 2个包包售价50元 ▪购买条件折扣 - 买X和Y，享折扣 - 购买一个毛绒玩具、一个钥匙扣和一个背包，售价20元 ▪购买条件折扣 - 买X和Y，Z商品享折扣 - 购买一条围巾和一顶帽子，手套享受5折 ▪赠品促销 - 买X，获赠品 - 任意购买2件达菲商品，免费获赠一条沙滩毛巾 B. 交易层级促销 ▪简单折扣 - 享折扣 - 仅限今日，全场9折 ▪买/获 - 买X，享折扣 - 购买3件T恤，整单立减10元 ▪买/获 - 消费满X，享折扣 - 玩具套装消费满100元，整单享受95折 C. 冲突 – 通过POS选项控制 ▪清仓商品参与促销 ▪重叠促销 ▪当出现重叠促销时，由POS系统决定优先级。 2. 支持通过批量上传/修改进行定义，并需经管理员授权批准。 | J69: 从Simba同步门店促销类型 B里的折扣包含coupon和促销 | K69: F&B | M69: MO需要了解供应商关于促销的solution | N69: 配置-促销类型-配置商店中 | O69: 1.同步SIMBA的促销信息,并发布促销活动 A商品层级促销 B交易层级促销 C重叠的促销活动，POS决定优先级 D发布促销。 2能够通过批量上传/修改定义，管理员授权。 | P69: Android & Back-End | Q69: =BRD_EPIC2[[#This Row],[system type]]&BRD_EPIC2[[#This Row],[system type2]] -> Android & Back-End & QA & PM & DM & UI | R69: & QA & PM & DM & UI | U69: 30 | V69: =$U69*DE_Cost!$B$1*8 -> 288 | W69: =$U69*DE_Cost!$B$1 -> 36 | Z69: =LEN(Q69) - LEN(SUBSTITUTE(Q69, "&", "")) + 1 -> 6 | AA69: Y | AD69: =U69 * Z69 -> 180
A70: 1(Minimum scope) | B70: 2. Foundation operational functions 基础运营功能 | C70: 2.2 Non-coupon promotion and discount(POS promotion) (非优惠券类)促销与折扣 | D70: 2.2.1 Non-coupon promotion configuration|Configure POS promotion rules 配置促销规则 | E70: 2.2.1.2 As Ops admin, I need New POS will be able to configure POS promotion detail as effective/priority/repeat for each type, as to define promotion in ordering. | F70: A store will be able to support multiple promotions, and these promotions could be batch upload in file or sync from SIMBA. Include: 1)effective time/store/identity, 2) priority, overlay, exclusion rules | G70: New Simba | H70: 2.2.1.2 作为运维管理员，我需要新 POS 能够为每种类型配置 POS 促销详情，包括有效/优先级/重复设置，以便在订单中定义促销。 | I70: 一家商店将能够支持多个促销活动，并且这些促销活动可以通过文件批量上传或从SIMBA同步。 包括：1) 有效时间/商店/身份，2) 优先级、叠加、排除规则 | J70: 可从Simba同步门店促销规则 New POS设置好促销规则与Simba一一对应 促销的优级级冲突怎么配置--3.4.5.1 | N70: 配置-促销详情 | O70: 1配置+文件上传(2) | P70: Front-End & Back-End | Q70: =BRD_EPIC2[[#This Row],[system type]]&BRD_EPIC2[[#This Row],[system type2]] -> Front-End & Back-End & QA & PM & DM & UI | R70: & QA & PM & DM & UI | U70: 10 | V70: =$U70*DE_Cost!$B$1*8 -> 96 | W70: =$U70*DE_Cost!$B$1 -> 12 | Z70: =LEN(Q70) - LEN(SUBSTITUTE(Q70, "&", "")) + 1 -> 6 | AA70: Y | AD70: =U70 * Z70 -> 60
A71: 1(Minimum scope) | B71: 2. Foundation operational functions 基础运营功能 | C71: 2.2 Non-coupon promotion and discount(POS promotion) (非优惠券类)促销与折扣 | D71: 2.2.1 Non-coupon promotion configuration|Configure POS promotion available period 配置促销生效时间 | E71: 2.2.1.3 As Ops admin, I need New POS will be able to configure POS promotion available period, as to define promotion in ordering. | F71: The period can be define by start & end date timestamp with repeat cycle(monthly, weekly, daily), enable a reminder for ending/extension. | H71: 2.2.1.3 作为运维管理员，我需要新 POS 系统能够配置 POS 促销活动可用期限，以便在订单中定义促销。 | I71: 该期间可以通过开始和结束日期时间戳定义，并具有重复周期（每月、每周、每天），并为结束/延期启用提醒。 | N71: 配置-促销活动-可用期限 | O71: admin配置（2） | P71: Front-End & Back-End | Q71: =BRD_EPIC2[[#This Row],[system type]]&BRD_EPIC2[[#This Row],[system type2]] -> Front-End & Back-End & QA & PM & DM & UI | R71: & QA & PM & DM & UI | U71: 3 | V71: =$U71*DE_Cost!$B$1*8 -> 28.8 | W71: =$U71*DE_Cost!$B$1 -> 3.6 | Z71: =LEN(Q71) - LEN(SUBSTITUTE(Q71, "&", "")) + 1 -> 6 | AA71: Y | AD71: =U71 * Z71 -> 18
A72: 1(Minimum scope) | B72: 2. Foundation operational functions 基础运营功能 | C72: 2.2 Non-coupon promotion and discount(POS promotion) (非优惠券类)促销与折扣 | D72: 2.2.2 Non-coupon promotion execution|Auto-apply POS promotion 自动添加促销折扣 | E72: 2.2.2.1 As Ops cashier, I need New POS will be able to auto-apply available POS promotion when conditions are met in ordering in priority, as to process promotion benefit/discount in ordering. | F72: POS is not applicable to calculate the max discount as "best offer” in multiple promotions/discounts applied, but it can only calculate the amount by promotion/ discount pre-defined priority, no matter the sequence of these promotions applied. | H72: 2.2.2.1 作为收银员，我需要新 POS 系统能够在满足条件时按优先级自动应用可用的 POS 促销，以便在订单处理中应用促销优惠/折扣。 | I72: POS不适用于计算应用多个促销/折扣时的“最佳优惠”最大折扣，但它只能按促销/折扣预定义的优先级计算金额，无论这些促销的应用顺序如何。 | N72: 配置-促销活动-优先级设定 | O72: admin配置（2） | P72: Android & Back-End | Q72: =BRD_EPIC2[[#This Row],[system type]]&BRD_EPIC2[[#This Row],[system type2]] -> Android & Back-End & QA & PM & DM & UI | R72: & QA & PM & DM & UI | U72: 5 | V72: =$U72*DE_Cost!$B$1*8 -> 48 | W72: =$U72*DE_Cost!$B$1 -> 6 | Z72: =LEN(Q72) - LEN(SUBSTITUTE(Q72, "&", "")) + 1 -> 6 | AA72: Y | AD72: =U72 * Z72 -> 30
A73: 1(Minimum scope) | B73: 2. Foundation operational functions 基础运营功能 | C73: 2.2 Non-coupon promotion and discount(POS promotion) (非优惠券类)促销与折扣 | D73: 2.2.2 Non-coupon promotion execution|Manual apply POS promotion 手动添加促销 | E73: 2.2.2.2 As Ops cashier, I need New POS will be able to manual apply POS promotion by cast selection, as to process promotion benefit/discount in ordering. | F73: Show a list of available promotions in this store, then cashiers can select to apply | H73: 2.2.2.2 作为收银员，我需要新 POS 系统能够通过选择商品手动应用 POS 促销，以便在订单处理中应用促销优惠/折扣。 | I73: 显示此商店中可用促销活动的列表，然后收银员可以选择应用 | N73: 配置-促销活动-选择商品应用促销 | O73: 显示此商店中可用促销活动的列表，然后收银员可以选择应用 | P73: Android & Back-End | Q73: =BRD_EPIC2[[#This Row],[system type]]&BRD_EPIC2[[#This Row],[system type2]] -> Android & Back-End & QA & PM & DM & UI | R73: & QA & PM & DM & UI | U73: 3 | V73: =$U73*DE_Cost!$B$1*8 -> 28.8 | W73: =$U73*DE_Cost!$B$1 -> 3.6 | Z73: =LEN(Q73) - LEN(SUBSTITUTE(Q73, "&", "")) + 1 -> 6 | AA73: Y | AD73: =U73 * Z73 -> 18
A74: 1(Minimum scope) | B74: 2. Foundation operational functions 基础运营功能 | C74: 2.2 Non-coupon promotion and discount(POS promotion) (非优惠券类)促销与折扣 | D74: 2.2.2 Non-coupon promotion execution|Add remark on POS promotion 填写促销附加信息 | E74: 2.2.2.3 As Ops cashier, I need New POS will be able to input promotion information as additional fields by cashier as supporting. E.g. CEA discount, as to fulfill promotion benefit/discount info in ordering. | F74: Cashier may need to enter guest identity code(E.g. ETKT code for CEA discount) into additional fields by verify and scan guest identification document. | H74: 2.2.2.3 作为收银员，我需要新 POS 系统能够让收银员通过附加字段输入促销信息作为支持。例如 CEA 折扣，以便在订单中实现促销优惠/折扣信息。 | I74: 收银员可能需要通过验证和扫描客人身份证明文件，将客人身份代码（例如，CEA折扣的ETKT代码）输入到附加字段中。 | N74: 促销活动-收银员操作 | O74: POS Android端附加字段，能够实现订单优惠信息 | P74: Android & Back-End | Q74: =BRD_EPIC2[[#This Row],[system type]]&BRD_EPIC2[[#This Row],[system type2]] -> Android & Back-End & QA & PM & DM & UI | R74: & QA & PM & DM & UI | U74: 3 | V74: =$U74*DE_Cost!$B$1*8 -> 28.8 | W74: =$U74*DE_Cost!$B$1 -> 3.6 | Z74: =LEN(Q74) - LEN(SUBSTITUTE(Q74, "&", "")) + 1 -> 6 | AA74: Y | AD74: =U74 * Z74 -> 18
A75: 1(Minimum scope) | B75: 2. Foundation operational functions 基础运营功能 | C75: 2.2 Non-coupon promotion and discount(POS promotion) (非优惠券类)促销与折扣 | D75: 2.2.2 Non-coupon promotion execution|Cancel applied POS promotion 取消已添加的促销 | E75: 2.2.2.4 As Ops cashier, I need New POS will be able to remove a selected promotion when guest would like to pay without promotion, as to process promotion benefit/discount in ordering. | H75: 2.2.2.4 作为收银员，我需要新 POS 系统能够在客人选择不使用促销时移除所选促销，以便在点单过程中处理促销优惠/折扣。 | N75: 促销活动-移除促销 | O75: POS Android端 移除所选促销信息 | P75: Android & Back-End | Q75: =BRD_EPIC2[[#This Row],[system type]]&BRD_EPIC2[[#This Row],[system type2]] -> Android & Back-End & QA & PM & DM & UI | R75: & QA & PM & DM & UI | U75: 2 | V75: =$U75*DE_Cost!$B$1*8 -> 19.2 | W75: =$U75*DE_Cost!$B$1 -> 2.4 | Z75: =LEN(Q75) - LEN(SUBSTITUTE(Q75, "&", "")) + 1 -> 6 | AA75: Y | AD75: =U75 * Z75 -> 12
A76: 1(Minimum scope) | B76: 2. Foundation operational functions 基础运营功能 | C76: 2.3 Checkout and payment 支付与结账 | D76: 2.3.1 Payment method Configuration|Configure payment method 设置支付方式 | E76: 2.3.1.1 As Ops admin, I need New POS will be able to configure payment method in store/stores group level on payment screen, as to define payment in ordering. | F76: Include: payment method name, payment method ranking, enable/disable | H76: 2.3.1.1 作为运维管理员，我需要新 POS 能够在支付屏幕上配置门店/门店组级别的支付方式，以便在订单中定义支付方式。 | I76: 包括：支付方式名称、支付方式排名、启用/禁用 | N76: 配置-支付屏幕-配置门店级别支付方式 | O76: POS Android端 支付方式展示 （1） 后台 配置（1） | P76: Front-End & Back-End | Q76: =BRD_EPIC2[[#This Row],[system type]]&BRD_EPIC2[[#This Row],[system type2]] -> Front-End & Back-End & QA & PM & DM & UI | R76: & QA & PM & DM & UI | U76: 2 | V76: =$U76*DE_Cost!$B$1*8 -> 19.2 | W76: =$U76*DE_Cost!$B$1 -> 2.4 | Z76: =LEN(Q76) - LEN(SUBSTITUTE(Q76, "&", "")) + 1 -> 6 | AA76: Y | AD76: =U76 * Z76 -> 12
A77: 1(Minimum scope) | B77: 2. Foundation operational functions 基础运营功能 | C77: 2.3 Checkout and payment 支付与结账 | D77: 2.3.1 Payment method Configuration|Identify scan payment 配置扫码支付 | E77: 2.3.1.2 As Ops cashier, I need New POS will be able to identify scan payment channel by QR code, as to define payment in ordering. | F77: Include: 1)WeChat Pay, 2) Alipay, 3) Gift card-will be retired after 2026 Aug., 4) e - CNY, 5) Union Pay | H77: 2.3.1.2 作为运营管理员，我需要新的POS系统能够通过二维码识别扫码支付渠道，以便在订单处理中定义支付方式。 | I77: 支持的支付渠道包括： 1. 微信支付 2. 支付宝 3. 礼品卡（将于2026年8月后停用） 4. 数字人民币 5. 云闪付 | N77: POS Android 扫码识别支付方式 | O77: Android | P77: Android | Q77: =BRD_EPIC2[[#This Row],[system type]]&BRD_EPIC2[[#This Row],[system type2]] -> Android & QA & PM & DM & UI | R77: & QA & PM & DM & UI | S77: Ops Admin扫QR Code，再去定义支付方式，无法理解这个场景 扫码之后才能确认支付方式吗？ 不是OPS，是Cashier，扫多种码可以识别出微信或支付宝 | U77: 10 | V77: =$U77*DE_Cost!$B$1*8 -> 96 | W77: =$U77*DE_Cost!$B$1 -> 12 | Z77: =LEN(Q77) - LEN(SUBSTITUTE(Q77, "&", "")) + 1 -> 5 | AA77: Y | AC77: 1103 | AD77: =U77 * Z77 -> 50
A78: 1(Minimum scope) | B78: 2. Foundation operational functions 基础运营功能 | C78: 2.3 Checkout and payment 支付与结账 | D78: 2.3.1 Payment method Configuration|Configure cash payment and change 配置现金支付与找零 | E78: 2.3.1.3 As Ops admin, I need New POS will be able to configure RMB cash payment and change with cash drawer, as to define payment in ordering. | F78: 1. Set RMB cash payment as quick access button, and also able to manual input in 元角分(current practice will round down to 元, not need to input 角 and 分) 2. Link to drawer and calculate/prompt change, log all cash payment actions. | H78: 2.3.1.3 作为运维管理员，我需要新 POS 系统能够配置人民币现金支付和现金找零，以便在订单中定义支付方式。 | I78: 1. 将人民币现金支付设置为快速访问按钮，并能够以元角分手动输入（目前的做法将向下舍入到元，不需要输入角和分） 2. 连接到钱箱并计算/提示找零，记录所有现金支付操作。 | N78: 配置-现金/现金找零-付款方式 | O78: POS Android 支付方式展示 （1） 后台 配置（1） | P78: Android & Front-End & Back-End | Q78: =BRD_EPIC2[[#This Row],[system type]]&BRD_EPIC2[[#This Row],[system type2]] -> Android & Front-End & Back-End & QA & PM & DM & UI | R78: & QA & PM & DM & UI | U78: 2 | V78: =$U78*DE_Cost!$B$1*8 -> 19.2 | W78: =$U78*DE_Cost!$B$1 -> 2.4 | Z78: =LEN(Q78) - LEN(SUBSTITUTE(Q78, "&", "")) + 1 -> 7 | AA78: Y | AD78: =U78 * Z78 -> 14
A79: 1(Minimum scope) | B79: 2. Foundation operational functions 基础运营功能 | C79: 2.3 Checkout and payment 支付与结账 | D79: 2.3.1 Payment method Configuration|Configure bankcard payment 配置银行卡支付 | E79: 2.3.1.4 As Ops admin, I need New POS will be able to configure bankcard payment, as to define payment in ordering. | F79: Include: domestic bankcard and foreign bankcard on BOT | H79: 2.3.1.4 作为运维管理员，我需要新 POS 系统能够配置银行卡支付，以便在订单中定义支付方式。 | I79: 包括：BOT上的国内银行卡和国外银行卡 | N79: 配置-银行卡-付款方式 | O79: POS Android 支付方式展示 （1） 后台 配置（1） | P79: Android & Front-End & Back-End | Q79: =BRD_EPIC2[[#This Row],[system type]]&BRD_EPIC2[[#This Row],[system type2]] -> Android & Front-End & Back-End & QA & PM & DM & UI | R79: & QA & PM & DM & UI | U79: 2 | V79: =$U79*DE_Cost!$B$1*8 -> 19.2 | W79: =$U79*DE_Cost!$B$1 -> 2.4 | Z79: =LEN(Q79) - LEN(SUBSTITUTE(Q79, "&", "")) + 1 -> 7 | AA79: Y | AD79: =U79 * Z79 -> 14
A80: 1(Minimum scope) | B80: 2. Foundation operational functions 基础运营功能 | C80: 2.3 Checkout and payment 支付与结账 | D80: 2.3.1 Payment method Configuration|Configure voucher payment 配置兑换券支付 | E80: 2.3.1.5 As Ops admin, I need New POS will be able to configure voucher as a non-cash payment by pre-defined code, as to define payment in ordering. | F80: 1. Configure existing non-cash payment codes into buttons, like 181, 182, 183, 184, 1828, 1829, also able to customize non-cash code. 2. Configure non-cash voucher payment as create, edit, enable/disable. | H80: 2.3.1.5 作为运维管理员，我需要新 POS 系统能够通过预定义代码将优惠券配置为非现金支付方式，以便在订单中定义支付。 | I80: 1. 将现有的非现金支付代码配置为按钮，如181、182、183、184、1828、1829，也能够自定义非现金代码。 2. 将非现金代金券支付配置为创建、编辑、启用/禁用。 | N80: 配置-预定义代码-非现金支付方式 | O80: POS Android 支付方式展示 （1） 后台 配置（1） | P80: Android & Front-End & Back-End | Q80: =BRD_EPIC2[[#This Row],[system type]]&BRD_EPIC2[[#This Row],[system type2]] -> Android & Front-End & Back-End & QA & PM & DM & UI | R80: & QA & PM & DM & UI | U80: 2 | V80: =$U80*DE_Cost!$B$1*8 -> 19.2 | W80: =$U80*DE_Cost!$B$1 -> 2.4 | Z80: =LEN(Q80) - LEN(SUBSTITUTE(Q80, "&", "")) + 1 -> 7 | AA80: Y | AD80: =U80 * Z80 -> 14
A81: 1(Minimum scope) | B81: 2. Foundation operational functions 基础运营功能 | C81: 2.3 Checkout and payment 支付与结账 | D81: 2.3.2 Payment process Configuration|Process order payment 执行订单支付 | E81: 2.3.2.1 As Ops cashier, I need New POS will be able to process payment with multiple payment methods combination, and print receipt after payment is completed, as to process payment in ordering. | F81: Include: scan to pay, RMB Cash, bank card, non-cash(voucher), contingency payment, etc. | H81: 2.3.2.1 作为收银员，我需要新 POS 系统能够处理多种支付方式的组合支付，并在支付完成后打印收据，以便在点单过程中完成支付。 | I81: 包括：扫码支付、人民币现金、银行卡、非现金（代金券）、应急支付等。 | N81: 执行订单支付-多种组合支付方式 | O81: POS Android 组合支付调起（1） 服务端接收参数信息和PIS对接（2） | P81: Android & Back-End | Q81: =BRD_EPIC2[[#This Row],[system type]]&BRD_EPIC2[[#This Row],[system type2]] -> Android & Back-End & QA & PM & DM & UI | R81: & QA & PM & DM & UI | U81: 10 | V81: =$U81*DE_Cost!$B$1*8 -> 96 | W81: =$U81*DE_Cost!$B$1 -> 12 | Z81: =LEN(Q81) - LEN(SUBSTITUTE(Q81, "&", "")) + 1 -> 6 | AA81: Y | AD81: =U81 * Z81 -> 60
A82: 1(Minimum scope) | B82: 2. Foundation operational functions 基础运营功能 | C82: 2.3 Checkout and payment 支付与结账 | D82: 2.3.2 Payment process Configuration|Modify payment method in checkout 修改支付方式 | E82: 2.3.2.2 As Ops cashier, I need New POS will be able to modify the payment among configured methods, as to process payment in ordering. | F82: Payment method can be modified or cancelled before paid | H82: 2.3.2.2 作为运营收银员，我需要新 POS 系统能够在配置的支付方式之间修改支付，以便在订单处理过程中完成支付。 | I82: 支付方式可以在支付前修改或取消 | N82: 执行订单支付-切换支付方式 | O82: POS Android 切换支付方式 | P82: Android | Q82: =BRD_EPIC2[[#This Row],[system type]]&BRD_EPIC2[[#This Row],[system type2]] -> Android & QA & PM & DM & UI | R82: & QA & PM & DM & UI | U82: 2 | V82: =$U82*DE_Cost!$B$1*8 -> 19.2 | W82: =$U82*DE_Cost!$B$1 -> 2.4 | Z82: =LEN(Q82) - LEN(SUBSTITUTE(Q82, "&", "")) + 1 -> 5 | AA82: Y | AD82: =U82 * Z82 -> 10
A83: 1(Minimum scope) | B83: 2. Foundation operational functions 基础运营功能 | C83: 2.3 Checkout and payment 支付与结账 | D83: 2.3.2 Payment process Configuration|Enable combine payment 合并付款 | E83: 2.3.2.3 As Ops cashier, I need New POS will be able to process a payment with multiple products in a order, as to process payment in ordering. | H83: 2.3.2.3 作为收银员，我需要新 POS 系统能够处理订单中包含多个产品的支付，以便在订购过程中完成支付。 | N83: 执行订单支付-多商品支付 | O83: POS Android 多个商品结算支付 | P83: Android | Q83: =BRD_EPIC2[[#This Row],[system type]]&BRD_EPIC2[[#This Row],[system type2]] -> Android & QA & PM & DM & UI | R83: & QA & PM & DM & UI | U83: 2 | V83: =$U83*DE_Cost!$B$1*8 -> 19.2 | W83: =$U83*DE_Cost!$B$1 -> 2.4 | Z83: =LEN(Q83) - LEN(SUBSTITUTE(Q83, "&", "")) + 1 -> 5 | AA83: Y | AD83: =U83 * Z83 -> 10
A84: 1(Minimum scope) | B84: 2. Foundation operational functions 基础运营功能 | C84: 2.3 Checkout and payment 支付与结账 | D84: 2.3.2 Payment process Configuration|Charge to hotel room 挂房账支付 | E84: 2.3.2.4 As Ops cashier, I need New POS will be able to charge transaction to hotel room, as to fulfill guest payment request in hotel shopping or dinning. | F84: 1. The charging to room need to be checked-in and have enough deposit. 2. Store/Restaurant cast should be able to easily check if there is deposit or not via system. 3. Room charging is able to refund via guest original payment method in hotel payment. | G84: PMS-Opera | H84: 2.3.2.4 作为收银员，我需要新 POS 系统能够将交易费用计入酒店房间，以满足客人在酒店购物或用餐时的付款需求。 | I84: 1. 记入房费需要客人已办理入住且有足够的押金。 2. 商店/餐厅收银员应该能够通过系统轻松查看是否有押金。 3. 房费记账可以通过客人在酒店支付时使用的原始支付方式进行退款。 | J84: 同一个接口处理挂房帐付款和退款 | N84: 执行订单支付-挂房支付 | P84: Android & Back-End | Q84: =BRD_EPIC2[[#This Row],[system type]]&BRD_EPIC2[[#This Row],[system type2]] -> Android & Back-End & QA & PM & DM & UI | R84: & QA & PM & DM & UI | U84: 10 | V84: =$U84*DE_Cost!$B$1*8 -> 96 | W84: =$U84*DE_Cost!$B$1 -> 12 | Z84: =LEN(Q84) - LEN(SUBSTITUTE(Q84, "&", "")) + 1 -> 6 | AA84: Y | AD84: =U84 * Z84 -> 60
A85: 1(Minimum scope) | B85: 2. Foundation operational functions 基础运营功能 | C85: 2.3 Checkout and payment 支付与结账 | D85: 2.3.2 Payment process Configuration|Record tape number 输入防伪胶带数字 | E85: 2.3.2.5 As Merch cashier, I need New POS will be able to record tape number by transaction to verify if item are belong to given transaction in return, as to mitigate refund abuse. | F85: Tape number is max to 6 digits. May not needed after RFID launch. | H85: 2.3.2.5 作为收银员，我需要新 POS 系统能够按交易记录防伪胶带数字，以验证退货商品是否属于指定交易，从而减少退款滥用。 | I85: 磁条卡号最多6位数字。RFID启动后可能不需要。 | N85: 记录防伪胶带数字 | O85: POS 校验防伪胶带数字 | P85: Android & Back-End | Q85: =BRD_EPIC2[[#This Row],[system type]]&BRD_EPIC2[[#This Row],[system type2]] -> Android & Back-End & QA & PM & DM & UI | R85: & QA & PM & DM & UI | U85: 2 | V85: =$U85*DE_Cost!$B$1*8 -> 19.2 | W85: =$U85*DE_Cost!$B$1 -> 2.4 | Z85: =LEN(Q85) - LEN(SUBSTITUTE(Q85, "&", "")) + 1 -> 6 | AA85: Y | AD85: =U85 * Z85 -> 12
A86: 1(Minimum scope) | B86: 2. Foundation operational functions 基础运营功能 | C86: 2.3 Checkout and payment 支付与结账 | D86: 2.3.2 Payment process Configuration|Enable amount allocation(AA) after payment 支付分摊(AA) | E86: 2.3.2.6 As FnB cashier, I need New POS will be able to split check amount for AA payment, as to fulfill guest payment request in ordering. | F86: Enable to split check amount to AA by guest number | H86: 2.3.2.6 作为餐饮收银员，我需要新的POS系统能够按用餐人数均分账单金额，以满足顾客在点餐时提出的AA制支付需求 | I86: 功能要求： 支持按顾客人数自动均分账单金额，实现AA制支付。 | N86: 执行订单支付-账单金额拆分 | O86: 子账单支付，子账单各自状态（10） | P86: Android & Back-End | Q86: =BRD_EPIC2[[#This Row],[system type]]&BRD_EPIC2[[#This Row],[system type2]] -> Android & Back-End & QA & PM & DM & UI | R86: & QA & PM & DM & UI | S86: 1.需要确认1笔订单多个子订单情况，例如分摊规则需要提供。 2.子账单支付失败处理情况？ 要求确认主流程做法。 | T86: Align with finance tech | U86: 30 | V86: =$U86*DE_Cost!$B$1*8 -> 288 | W86: =$U86*DE_Cost!$B$1 -> 36 | Z86: =LEN(Q86) - LEN(SUBSTITUTE(Q86, "&", "")) + 1 -> 6 | AA86: Y | AD86: =U86 * Z86 -> 180
A87: 1(Minimum scope) | B87: 2. Foundation operational functions 基础运营功能 | C87: 2.3 Checkout and payment 支付与结账 | D87: 2.3.3 Pay by contingency code|Apply contingency payment 切换应急支付 | E87: 2.3.3.1 As Ops cashier, I need New POS will be able to use contingency payment on different payment method, as to process payment in contingency ordering. | F87: 1. Contingency payment is to cover all sales transaction scenarios. 2. Enable contingency code’s name configuration(e.g. Alipay non-cash payment). 3. Enable payment complete information as additional fields in contingency mode to record supporting information for accounting. | H87: 2.3.3.1 作为运营收银员，我需要新 POS 系统能够在不同支付方式上使用应急支付，以便处理应急订单的支付。 | I87: 1. 应急支付是为了覆盖所有销售交易场景。 2. 启用应急代码的名称配置（例如支付宝非现金支付）。 3. 启用支付完成信息作为应急模式下的附加字段，以记录支持会计核算的信息。 | N87: 执行订单支付-切换应急支付 | O87: 1.应急代码配置（4）覆盖所有销售交易场景（3） 2.支持核算信息（3） | P87: Android & Back-End | Q87: =BRD_EPIC2[[#This Row],[system type]]&BRD_EPIC2[[#This Row],[system type2]] -> Android & Back-End & QA & PM & DM & UI | R87: & QA & PM & DM & UI | U87: 10 | V87: =$U87*DE_Cost!$B$1*8 -> 96 | W87: =$U87*DE_Cost!$B$1 -> 12 | Z87: =LEN(Q87) - LEN(SUBSTITUTE(Q87, "&", "")) + 1 -> 6 | AA87: Y | AD87: =U87 * Z87 -> 60
A88: 1(Minimum scope) | B88: 2. Foundation operational functions 基础运营功能 | C88: 2.3 Checkout and payment 支付与结账 | D88: 2.3.3 Pay by contingency code|Authorize contingency payment 授权应急支付 | E88: 2.3.3.2 As Ops cashier, I need New POS will be able to have authorization code to switch to contingency payment, as to process payment in contingency ordering. | F88: Not needed special authorization as current practice, only code needed. | H88: 2.3.3.2 作为收银员，我需要新 POS 系统能够有授权代码切换到应急支付，以便处理应急订单的支付。 | I88: 不需要像目前做法那样的特殊授权，只需要代码。 | N88: 应急支付-移除原有的应急处理方式 | P88: Android & Back-End | Q88: =BRD_EPIC2[[#This Row],[system type]]&BRD_EPIC2[[#This Row],[system type2]] -> Android & Back-End & QA & PM & DM & UI | R88: & QA & PM & DM & UI | U88: 3 | V88: =$U88*DE_Cost!$B$1*8 -> 28.8 | W88: =$U88*DE_Cost!$B$1 -> 3.6 | Z88: =LEN(Q88) - LEN(SUBSTITUTE(Q88, "&", "")) + 1 -> 6 | AA88: Y | AD88: =U88 * Z88 -> 18
A89: 1(Minimum scope) | B89: 2. Foundation operational functions 基础运营功能 | C89: 2.3 Checkout and payment 支付与结账 | D89: 2.3.3 Pay by contingency code|Process contingency payment 操作应急支付 | E89: 2.3.3.3 As Ops cashier, I need New POS will be able to tap button or input contingency code to switch to contingency payment mode manually, as to process payment in contingency ordering. | F89: Frequent used contingency payment by quick access button. | H89: 2.3.3.3 作为收银员，我需要新 POS 系统能够通过点击按钮或输入应急代码手动切换到应急支付模式，以便处理应急订单的支付。 | I89: 通过快速访问按钮频繁使用的应急支付。 | N89: 应急支付-输入授权码，切换对应应急支付 | O89: POS Android 输入授权code | P89: Android & Back-End | Q89: =BRD_EPIC2[[#This Row],[system type]]&BRD_EPIC2[[#This Row],[system type2]] -> Android & Back-End & QA & PM & DM & UI | R89: & QA & PM & DM & UI | U89: 2 | V89: =$U89*DE_Cost!$B$1*8 -> 19.2 | W89: =$U89*DE_Cost!$B$1 -> 2.4 | Z89: =LEN(Q89) - LEN(SUBSTITUTE(Q89, "&", "")) + 1 -> 6 | AA89: Y | AD89: =U89 * Z89 -> 12
A90: 1(Minimum scope) | B90: 2. Foundation operational functions 基础运营功能 | C90: 2.3 Checkout and payment 支付与结账 | D90: 2.3.3 Pay by contingency code|Contingency code payment situation 配置应急支付场景 | E90: 2.3.3.4 As Ops cashier, I need New POS will be able to auto-trigger switch to contingency payment/refund when POS is offline or payment function broken, as to process payment in contingency ordering. | F90: Contingency mode triggers BOT network mode switch from leased line to 5G mode. | H90: 2.3.3.4 作为收银员，我需要新 POS 系统能够在 POS 离线或支付功能故障时自动触发切换到应急支付/退款模式，以便在应急订单处理中完成支付。 | I90: 应急模式触发BOT网络模式从专线切换到5G模式。 | N90: 应急支付-故障自动触发应急支付 | O90: POS Android 触发专线切换（网络）判断场景的不确定性 | P90: Android | Q90: =BRD_EPIC2[[#This Row],[system type]]&BRD_EPIC2[[#This Row],[system type2]] -> Android & QA & PM & DM & UI | R90: & QA & PM & DM & UI | U90: 10 | V90: =$U90*DE_Cost!$B$1*8 -> 96 | W90: =$U90*DE_Cost!$B$1 -> 12 | Z90: =LEN(Q90) - LEN(SUBSTITUTE(Q90, "&", "")) + 1 -> 5 | AA90: N | AB90: 这里建议10人天， 自动切换是如何判断，如何保证准确性需要不断优化 | AD90: =U90 * Z90 -> 50
A91: 1(Minimum scope) | B91: 2. Foundation operational functions 基础运营功能 | C91: 2.3 Checkout and payment 支付与结账 | D91: 2.3.4 [FnB] Service fee|Calculate service fee 计算服务费 | E91: 2.3.4.1 As FnB cashier, I need New POS will be able to calculate service fee by order/product level, as to process service fee payment in dinning. | F91: 1. Service fee is calculated upon product original price (w/o discount). 2. Service charge do not participate in any discounts. | H91: 2.3.4.1 作为餐饮收银员，我需要新 POS 系统能够按订单/产品级别计算服务费，以便在用餐过程中处理服务费支付。 | I91: 1. 服务费按产品原价（不含折扣）计算。 2. 服务费不参与任何折扣。 | N91: 服务费-订单/产品 | O91: 考虑商品/订单上独立计算，最终需要 加在总账单上结算 | P91: Android & Back-End | Q91: =BRD_EPIC2[[#This Row],[system type]]&BRD_EPIC2[[#This Row],[system type2]] -> Android & Back-End & QA & PM & DM & UI | R91: & QA & PM & DM & UI | U91: 5 | V91: =$U91*DE_Cost!$B$1*8 -> 48 | W91: =$U91*DE_Cost!$B$1 -> 6 | Z91: =LEN(Q91) - LEN(SUBSTITUTE(Q91, "&", "")) + 1 -> 6 | AA91: Y | AD91: =U91 * Z91 -> 30
A92: 1(Minimum scope) | B92: 2. Foundation operational functions 基础运营功能 | C92: 2.3 Checkout and payment 支付与结账 | D92: 2.3.4 [FnB] Service fee|Modify service fee 调整服务费 | E92: 2.3.4.2 As FnB cashier, I need New POS will be able to modify service fee with specific permission, as to process service fee payment in dinning. | F92: Adjust/exempt service fee by GSM/Lead authorized for exceptional cases, GSM/Lead authorized needed. | H92: 2.3.4.2 作为餐饮收银员，我需要新 POS 系统能够在特定权限下修改服务费，以便处理餐饮中的服务费支付。 | I92: 由GSM/主管授权调整/免除特殊情况下的服务费，需要GSM/主管授权。 | N92: 服务费-授权服务费修改 | O92: 1.服务费修改（3）联动金额计算 2.授权操作（1） | P92: Android & Back-End | Q92: =BRD_EPIC2[[#This Row],[system type]]&BRD_EPIC2[[#This Row],[system type2]] -> Android & Back-End & QA & PM & DM & UI | R92: & QA & PM & DM & UI | U92: 4 | V92: =$U92*DE_Cost!$B$1*8 -> 38.4 | W92: =$U92*DE_Cost!$B$1 -> 4.8 | Z92: =LEN(Q92) - LEN(SUBSTITUTE(Q92, "&", "")) + 1 -> 6 | AA92: Y | AD92: =U92 * Z92 -> 24
A93: 1(Minimum scope) | B93: 2. Foundation operational functions 基础运营功能 | C93: 2.3 Checkout and payment 支付与结账 | D93: 2.3.4 [FnB] Service fee|Configure service fee 配置服务费 | E93: 2.3.4.3 As FnB admin, I need New POS will be able to configure service fee onto order/product level with fix amount or percentage, as to process service fee payment in dinning. | F93: Store service fee can be configured at menu level or configured at product level | H93: 2.3.4.3 作为餐饮管理员，我需要新 POS 系统能够在订单/产品级别配置服务费，支持固定金额或百分比形式，以便在用餐过程中处理服务费支付。 | I93: 商店服务费可以在菜单级别配置，也可以在产品级别配置 | N93: 服务费-菜单层级/产品层级 | O93: 服务配参与配置菜单级别和产品级别 | P93: Front-End & Back-End | Q93: =BRD_EPIC2[[#This Row],[system type]]&BRD_EPIC2[[#This Row],[system type2]] -> Front-End & Back-End & QA & PM & DM & UI | R93: & QA & PM & DM & UI | U93: 5 | V93: =$U93*DE_Cost!$B$1*8 -> 48 | W93: =$U93*DE_Cost!$B$1 -> 6 | Z93: =LEN(Q93) - LEN(SUBSTITUTE(Q93, "&", "")) + 1 -> 6 | AA93: Y | AD93: =U93 * Z93 -> 30
A94: 1(Minimum scope) | B94: 2. Foundation operational functions 基础运营功能 | C94: 2.4 Order & transaction 交易订单 | D94: 2.4.1 Order foundation|Record sales order as SOR (System of Record) 记录订单-Sales SOR | E94: 2.4.1.1 As Ops admin, I need New POS will be able to record sales order as SOR which align to existing Merch and FnB transaction fields and logic, as to record all settled order as sales SOR. | F94: 1. Record the transaction data by business, store and channel -- include online (e.g. Tmall) and offline FnB & Merch stores. 2. Follow existing POS logic to upload transaction data (1, 12, 95 etc.) on T+1 and synchronize to SAP as sales SOR. Upload transaction data method define in Finance part. | H94: 2.4.1.1 作为运营管理员，我需要新的POS系统能够按照与现有商场及餐饮业务交易字段和逻辑一致的方式，将销售订单记录为销售订单凭证（SOR），以便将所有已结算的订单记录为销售SOR | I94: 按业务、门店和渠道记录交易数据——包括线上（如天猫）和线下的餐饮与商场门店。 遵循现有POS逻辑，在T+1日上传交易数据（如1、12、95等类型），并同步至SAP系统作为销售SOR。交易数据上传方法在财务部分定义。 | N94: 交易订单- 记录销售订单凭证（SOR） | O94: 1.销售订单记录为销售订单凭证（3） 2渠道上传交易数据（5） 3.同步交易数据到FM（5） | P94: Front-End & Back-End | Q94: =BRD_EPIC2[[#This Row],[system type]]&BRD_EPIC2[[#This Row],[system type2]] -> Front-End & Back-End & QA & PM & DM & UI | R94: & QA & PM & DM & UI | U94: 13 | V94: =$U94*DE_Cost!$B$1*8 -> 124.8 | W94: =$U94*DE_Cost!$B$1 -> 15.6 | Z94: =LEN(Q94) - LEN(SUBSTITUTE(Q94, "&", "")) + 1 -> 6 | AA94: Y | AD94: =U94 * Z94 -> 78
A95: 1(Minimum scope) | B95: 2. Foundation operational functions 基础运营功能 | C95: 2.4 Order & transaction 交易订单 | D95: 2.4.1 Order foundation|Record order detail in an unified format 维护统一的订单明细 | E95: 2.4.1.2 As Ops admin, I need New POS will be able to record order detail with a unified order information structure, as to record unified settled order detail as sales SOR. | F95: Includes: 1. business date and timestamp, store ID, POS ID, order transaction number, order status, product SKU, quantity, unit price, total price, payment method and type, cashier ID, associated order(order correction or refund), discount, and revenue type, etc. 2. Business customized fields like guest type: Walkin/hotel guest; Reservation type. 3. Discounts from POS, coupon and channel(e.g. coupon VID, coupon redemption status, redemption cancellation, coupon redeemed product information) and its promotion/discount codes. | H95: 2.4.1.2 作为运营管理员，我需要新的POS系统能够采用统一的订单信息结构来记录订单详情，以便将统一格式的已结算订单详细信息记录为销售凭证。 | I95: 1.业务日期与时间戳、门店ID、POS终端ID、订单交易编号、订单状态、商品SKU、数量、单价、总价、支付方式与类型、收银员ID、关联订单（订单更正或退款）、折扣信息及收入类型等。 2.业务定制字段，如宾客类型：散客/酒店住客；预订类型。 3.来自POS系统、优惠券及渠道的折扣信息（例如：优惠券虚拟ID、优惠券核销状态、核销取消、优惠券对应商品信息）及其促销/折扣代码。 | N95: 交易订单- 维护统一的订单明细 | O95: 订单的业务字段数据格式定义 | P95: Back-End | Q95: =BRD_EPIC2[[#This Row],[system type]]&BRD_EPIC2[[#This Row],[system type2]] -> Back-End& QA & PM & DM | R95: & QA & PM & DM | U95: 3 | V95: =$U95*DE_Cost!$B$1*8 -> 28.8 | W95: =$U95*DE_Cost!$B$1 -> 3.6 | Z95: =LEN(Q95) - LEN(SUBSTITUTE(Q95, "&", "")) + 1 -> 4 | AA95: Y | AD95: =U95 * Z95 -> 12
A96: 1(Minimum scope) | B96: 2. Foundation operational functions 基础运营功能 | C96: 2.4 Order & transaction 交易订单 | D96: 2.4.1 Order foundation|View/search order 查看/查询订单 | E96: 2.4.1.3 As Ops admin & cashier, I need New POS will be able to search order and its detail by specify field in order/receipt level, as to execute order audit and customer service after order settled. | F96: 1. Enable search by order fields as condition by criteria or range, and export search result to excel or PDF file. 2. All order fields can be configured as searching condition. | H96: 2.4.1.3 作为运营管理员和收银员，我需要新 POS 系统能够通过指定订单/收据级别的字段来搜索订单及其详情，以便在订单结算后执行订单审核和客户服务。 | I96: 1. 支持按订单字段作为条件按条件或范围进行搜索，并将搜索结果导出到Excel或PDF文件。 2. 所有订单字段都可以配置为搜索条件。 | N96: 交易订单-筛选订单及详情 | O96: 1.搜索功能界面，导出Excel/PDF。(5) 2.所有订单字段配置为搜索条件。(2) | P96: Android & Front-End & Back-End | Q96: =BRD_EPIC2[[#This Row],[system type]]&BRD_EPIC2[[#This Row],[system type2]] -> Android & Front-End & Back-End & QA & PM & DM & UI | R96: & QA & PM & DM & UI | U96: 30 | V96: =$U96*DE_Cost!$B$1*8 -> 288 | W96: =$U96*DE_Cost!$B$1 -> 36 | Z96: =LEN(Q96) - LEN(SUBSTITUTE(Q96, "&", "")) + 1 -> 7 | AA96: Y | AD96: =U96 * Z96 -> 210
A97: 1(Minimum scope) | B97: 2. Foundation operational functions 基础运营功能 | C97: 2.4 Order & transaction 交易订单 | D97: 2.4.1 Order foundation|Modify/cancel order 修改/取消订单 | E97: 2.4.1.4 As Ops admin & cashier, I need New POS will be able to modify settled orders for return & refund, exchange item, or apply discount, as to audit and customer service after order settled. | F97: 1. Return & refund on order or item level, and change refund method for guest recovery cases who may leave park 2. Apply discount by coupon or promotion | H97: 2.4.1.4 作为运营管理员及收银员，我需要新的POS系统能够在订单结算后，支持对已结算订单进行退货退款、商品换货或折扣补录等操作，以满足审计及客户服务需求。 | I97: 1.支持按订单或商品层级办理退货退款，并可根据客户关怀需要（如游客可能已离园）调整退款方式 2.支持通过优惠券或促销活动补录折扣 | N97: 交易订单-修改已结算的订单 | O97: 1.订单或商品级别进行退货和退款，退款调用（2） 2.通过优惠券或促销活动补录折扣，订单重新计算优惠（5） | P97: Android & Front-End & Back-End | Q97: =BRD_EPIC2[[#This Row],[system type]]&BRD_EPIC2[[#This Row],[system type2]] -> Android & Front-End & Back-End & QA & PM & DM & UI | R97: & QA & PM & DM & UI | U97: 30 | V97: =$U97*DE_Cost!$B$1*8 -> 288 | W97: =$U97*DE_Cost!$B$1 -> 36 | Z97: =LEN(Q97) - LEN(SUBSTITUTE(Q97, "&", "")) + 1 -> 7 | AA97: Y | AD97: =U97 * Z97 -> 210
A98: 1(Minimum scope) | B98: 2. Foundation operational functions 基础运营功能 | C98: 2.4 Order & transaction 交易订单 | D98: 2.4.1 Order foundation|Void FnB order 作废餐饮订单 | E98: 2.4.1.5 As FnB admin & cashier, I need New POS will be able to void orders without inventory depletion, as to execute customer service after order settled. | F98: F&B voided transactions do not deduct supply chain inventory | H98: 2.4.1.5 作为餐饮部管理员和收银员，我需要新 POS 系统能够在不减少库存的情况下取消订单，以便在订单结算后执行客户服务。 | I98: 餐饮作废交易不扣除供应链库存 | N98: 交易订单-取消订单 | O98: 餐饮作废交易不扣除供应链库存（3） PIS联调（2） | P98: Android & Front-End & Back-End | Q98: =BRD_EPIC2[[#This Row],[system type]]&BRD_EPIC2[[#This Row],[system type2]] -> Android & Front-End & Back-End & QA & PM & DM & UI | R98: & QA & PM & DM & UI | U98: 5 | V98: =$U98*DE_Cost!$B$1*8 -> 48 | W98: =$U98*DE_Cost!$B$1 -> 6 | Z98: =LEN(Q98) - LEN(SUBSTITUTE(Q98, "&", "")) + 1 -> 7 | AA98: Y | AD98: =U98 * Z98 -> 35
A99: 1(Minimum scope) | B99: 2. Foundation operational functions 基础运营功能 | C99: 2.4 Order & transaction 交易订单 | D99: 2.4.2 [Merch] Exchange|Configure exchange rules 配置换货规则 | E99: 2.4.2.1 As Merch admin, I need New POS will be able to configure exchange rules, as to execute customer service after order settled. | F99: 1. Configure cross store exchange policy by original store ID and SKU 2. Configure exchange limitation on one transaction 3. AP holder/CM identification not needed for exchange. | H99: 2.4.2.1 作为商场管理员，我需要新的POS系统能够配置换货规则，以便在订单结算后执行客户服务。 | I99: 1.支持根据原始门店ID和SKU配置跨店换货政策 2.支持配置单次交易的换货数量限制 3.换货操作无需验证年票持有者/员工身份信息 | N99: 交易订单-商场管理员-配置换货规则 | O99: 1.门店ID和SKU配置跨店换货政策（5） 2.单次交易的换货数量（3） 3.换货操作不验证部分（1） | P99: Front-End & Back-End | Q99: =BRD_EPIC2[[#This Row],[system type]]&BRD_EPIC2[[#This Row],[system type2]] -> Front-End & Back-End & QA & PM & DM & UI | R99: & QA & PM & DM & UI | T99: sku配置自己的换货规则，这个2天？我该为5 | U99: 5 | V99: =$U99*DE_Cost!$B$1*8 -> 48 | W99: =$U99*DE_Cost!$B$1 -> 6 | Z99: =LEN(Q99) - LEN(SUBSTITUTE(Q99, "&", "")) + 1 -> 6 | AA99: N | AB99: 这里的人天过多，建议为2人天，这里是换货配置，不是换货功能 | AD99: =U99 * Z99 -> 30
A100: 1(Minimum scope) | B100: 2. Foundation operational functions 基础运营功能 | C100: 2.4 Order & transaction 交易订单 | D100: 2.4.2 [Merch] Exchange|Exchange with payment 换货与补差价 | E100: 2.4.2.2 As Merch cashier, I need New POS will be able to exchange Merch product in item level with partial refund/additional payment, as to execute customer service after order settled. | F100: 1. Scan original receipt to identify original order 2. Print exchange receipt when finished 3. May need GSM/Lead authorized for exceed-limit exchanges or no receipt - GSM/Lead authorized needed | H100: 2.4.2.2 作为 Merch 收银员，我需要新 POS 系统能够在商品级别进行 Merch 产品兑换，并支持部分退款/额外支付，以便在订单完成后执行客户服务。 | I100: 1. 扫描原始收据以识别原始订单 2. 完成后打印换货收据 3. 超出限制或没有收据可能需要GSM/主管授权 - 需要GSM/主管授权 | N100: 执行-Merch 产品兑换 | O100: 1. 扫描原始收据以识别原始订单（2） 2. 打印换货收据（2） 3. 授权（1） | P100: Android & Back-End | Q100: =BRD_EPIC2[[#This Row],[system type]]&BRD_EPIC2[[#This Row],[system type2]] -> Android & Back-End & QA & PM & DM & UI | R100: & QA & PM & DM & UI | U100: 25 | V100: =$U100*DE_Cost!$B$1*8 -> 240 | W100: =$U100*DE_Cost!$B$1 -> 30 | Z100: =LEN(Q100) - LEN(SUBSTITUTE(Q100, "&", "")) + 1 -> 6 | AA100: N | AB100: 建议25人天，这里是换货的具体实施 | AD100: =U100 * Z100 -> 150
A101: 1(Minimum scope) | B101: 2. Foundation operational functions 基础运营功能 | C101: 2.4 Order & transaction 交易订单 | D101: 2.4.3 Return and refund|Configure return and refund rules 配置退货规则和残次状态/原因 | E101: 2.4.3.1 As Ops admin, I need New POS will be able to configure return/refund rules and defective status/return reason selection , as to execute customer service after order settled. | F101: 1. Configure cross store return policy by original company code, LoB, store ID and SKU 2. Configure defective status/return reason in order and in item level 3. Define amount threshold for GSM/Lead authorized by Merch and FnB location | H101: 2.4.3.1 作为运营管理员，我需要新的POS系统能够配置退货/退款规则及瑕疵状态/退货原因选项，以便在订单结算后执行客户服务。 | I101: 1. 按原始公司代码、LoB、商店ID和SKU配置跨店退货策略 2. 在订单和项目级别配置缺陷状态/退货原因 3. 定义商品和餐饮场所GSM/主管授权的金额阈值 | N101: 配置退货/退款规则及 瑕疵状态/退货原因选项 | O101: 1. 配置跨店退货策略(5) 2. 在订单和项目级别配置缺陷状态/退货原因(4) 3.1定义金额阈值(2) 3.2授权功能(1) | P101: Front-End & Back-End | Q101: =BRD_EPIC2[[#This Row],[system type]]&BRD_EPIC2[[#This Row],[system type2]] -> Front-End & Back-End & QA & PM & DM & UI | R101: & QA & PM & DM & UI | U101: 5 | V101: =$U101*DE_Cost!$B$1*8 -> 48 | W101: =$U101*DE_Cost!$B$1 -> 6 | Z101: =LEN(Q101) - LEN(SUBSTITUTE(Q101, "&", "")) + 1 -> 6 | AA101: N | AB101: 这里建议5人天，仅规则配置及原因录入 | AD101: =U101 * Z101 -> 30
...

Sheet 1_Standard Part
A1: No. 序号 | B1: Quotation Item 报价项 | C1: Description 内容说明 | D1: Unit 计费单位 | E1: Quantity 数量 | F1: Unit Price(VAT Inc) 含税单价 | G1: Total Price(VAT Inc) 含税总价 | H1: Tax Rate 税率 | I1: Filling Instructions 填写说明
A2: =ROW()-1 -> 1 | B2: Standard Software 标品软件 | C2: 1. Deploy the standard software server and client in Party A’s own environment. 2. Provide a complete user manual. 3. Provide functional specification documentation for the standard software. 4. Deliver the full source code, including source code files, architecture description, deployment documents, test cases, training materials, and all other deliverables covering the software development lifecycle. 1. 在甲方自有环境部署标品软件服务端和客户端 2. 提供软件完整操作手册 3. 提供标品软件功能说明文档 4. 提供完整源码交付：含源码、架构说明、部署文档、测试用例、培训材料等软件生命周期的所有交付材料 Comments: The acquisition of the source code is solely intended for internal use and dedicated to expanding functionalities through development. We assure that it will not be utilized for any commercial purposes. 注：源码的购买仅用于内部功能扩展开发使用，承诺不用于任何商业用途。 | D2: 套 | E2: 1 | F2: 4420000 | G2: =E2*F2 -> 4420000 | H2: 0.06 | I2: Please fill in the quantity, unit price (tax included), and tax rate. The total price (tax included) will be auto-calculated; no need to fill it in. For non-standard software, please enter 0 for the quantity. 请填写数量，含税单价，税率 含税总价不需要填写，自动生成 无标品软件提供的，数量填0 有标品软件，请填写单位(如套)
A3: 标品软件包含RFP功能列表
A4: No. 序号 | B4: RFP Section RFP章节 | C4: Function Module 功能模块 | D4: Function Name 功能名称 | E4: Filling Instructions 填写说明 | F4: EPIC | G4: Time spent by EPIC | H4: price | I4: 公式例子
A5: =ROW()-4 -> 1 | B5: 3.2.1.1 3.2.2.1 3.2.4.1 3.2.5.1 3.2.6.1 | C5: Account Log-in 账号 | D5: Log-in/Log out Change Password修改密码 Lock Account | E5: 刷卡登录功能需要定制化 | F5: 2.8.3.1 2.8.3.2 2.8.3.3 2.8.3.4 | I5: count day总和 985 价格公式例子 91/所有的总和*4420000 注意此处EPIC的编号重复，内容不一样
A6: =ROW()-4 -> 2 | B6: 3.2.1.2 3.2.2.2 3.2.4.2 3.2.5.2 3.2.6.2 | C6: Store Open/Closed 开关店 | D6: Store Open开店 Store Close 关店 | F6: 2.6.1.1 2.6.1.2 2.6.1.7 2.6.2.1 | I6: 3.2.2.2 中应急支付
A7: =ROW()-4 -> 3 | B7: 3.2.1.3 3.2.4.3 3.2.5.3 3.2.6.3 | C7: Product Item Management 商品项管理 | D7: Menu Management菜单管理 Search 餐品查询 Product Modify商品编辑 | F7: 2.7.1.3
A8: =ROW()-4 -> 4 | B8: 3.2.6.4 | C8: Table Management 桌台管理 | D8: Table Management桌台管理 Open Table开桌台 | F8: 2.6.1.6 2.1.3.1 2.1.3.2 2.1.3.6 2.3.2.4
A9: =ROW()-4 -> 5 | B9: 3.2.1.5 3.2.2.5 3.2.4.5 3.2.5.5 3.2.6.6 | C9: Order 订单操作 | D9: Create Order创建订单 Settlement结算 Order Landing落单 Store Pickup门店自提 | F9: 2.1.1.1 2.1.1.2 2.1.1.3 2.1.1.4 2.1.2.1 2.1.2.2 2.1.2.3 2.1.2.4 2.1.2.5 2.2.2.1 2.2.2.2 2.2.2.4 2.3.1.1 2.3.1.2 2.3.1.3 2.3.1.4 2.3.1.5 2.3.2.1 2.3.2.2 2.3.2.3 2.3.2.4
A10: =ROW()-4 -> 6 | B10: 3.2.1.6 3.2.2.6 3.2.3.3 3.2.4.6 3.2.5.6 3.2.6.7 3.2.7.3 | C10: Order Management 订单管理 | D10: Return退货 Exchange换货 Suspend Order挂单 Search 查询 | F10: 2.4.3.2 2.4.3.3 2.4.2.1 2.4.2.2
A11: =ROW()-4 -> 7 | B11: 3.2.3.1 3.2.7.1 3.2.3.4 | C11: Online Order Creation 线上订单创建 Exception handling on order integration 异常处理 | D11: Master data sychonization and validation餐品主档同步和餐品校验 Previlege Validation权益校验 Order Payment订单支付 Exception handling on order integration 异常处理 | F11: 2.4.1.1 2.4.1.2 2.4.1.3 2.4.1.4 2.4.1.5 3.6.4.1 3.6.5.1
A12: =ROW()-4 -> 8 | B12: 3.2.8 | C12: Merch and F&B Cross-sell Stores 商品&餐饮综合门店 | D12: 功能等同于以下两个功能模块 3.2.1 Merchandise Store零售门店 3.2.4 F&B Quick Service Resturant 餐饮快餐 | G12: 已标注等同位置
A13: =ROW()-4 -> 9 | B13: 3.2.9.1 3.2.9.3 3.2.9.4 | C13: Inventory Management 库存管理 | D13: Inventory Synchronization库存同步 Inventory Search库存查询 Inventory Monitor & Alert库存监控机制 | F13: 3.6.3.1 3.6.3.2 3.6.3.3
A14: =ROW()-4 -> 10 | B14: 3.2.10.1 3.2.10.2 3.2.10.3 3.2.10.4 | C14: Product Management 商品管理 | D14: Product Creation商品创建 Master Data Management 商品主档信息管理 Product Search & Product List商品查询&商品列表 Monitoring and Alert监控和预警 | F14: 2.7.1.1 2.7.1.2 2.7.1.4 2.7.1.5 | G14: Customize Part 中重复
A15: =ROW()-4 -> 11 | B15: 3.2.11.1 3.2.11.2 3.2.11.3 3.2.11.4 3.2.11.5 | C15: Promotion Management 促销管理 | D15: Promotion Creation创建促销 Promotion Types 促销类型 Promotion List促销列表 Promotion Quota Control促销额度管理 Promotion Rules Setting促销规则管理 | F15: 2.2.1.1 2.2.1.2 2.2.1.3
A16: =ROW()-4 -> 12 | B16: 3.2.13 | C16: System Admin 系统管理 | D16: 3.2.13.1 ~ 3.2.13.9的功能 | F16: 2.8.2.1 2.8.2.2 2.8.2.3 2.8.3.1 2.8.3.4 2.9.2.3 2.9.2.4 2.5.1.1 2.6.3.1 2.6.3.2 2.6.3.3 3.4.1.1 3.4.1.2 3.4.1.4 3.4.2.1 3.4.2.2 3.4.3.1 3.4.3.2 3.4.4.1 3.4.5.1 3.5.2.1 3.5.2.2 5.1.2.1 | I16: 2.8.3.1 2.8.3.2 2.8.3.3 2.8.3.4 在EPIC中重复号，需要看内容才能理解

Sheet 2_Customize Part
A1: Additional Notes： 补充说明： | B1: The custom development section includes function adaptation, custom feature development, and integration with SHDR’s internal systems. 定制开发部分包含功能适配、功能开发、SHDR内部系统对接等。
A2: No. 序号 | B2: RFP Section RFP章节 | C2: Function Module 功能模块 | D2: Function Name 功能名称 | E2: Workload (Man-Days) 工作量（人天） | F2: Unit Price(VAT Inc) 含税单价 | G2: Total Price(VAT Inc) 含税总价 | H2: Tax Rate 税率 | I2: Filling Instructions 填写说明 | J2: EIPC | K2: day
A3: =ROW()-2 -> 1 | B3: 3.2.1.1 3.2.4.1 3.2.5.1 3.2.6.1 | C3: User Account 账号 | D3: Slash card 刷卡登录 | E3: 30 | F3: 2611 | G3: =E3*F3 -> 78330 | H3: 0.06 | J3: 2.8.3.2
A4: =ROW()-2 -> 2 | B4: 3.2.1.2 3.2.4.2 3.2.5.2 3.2.6.2 | C4: Store Open/Closed 开关店 | D4: POS Support offline mode POS支持离线交易 查看钱箱报表 | E4: 30 | F4: 2611 | G4: =E4*F4 -> 78330 | H4: 0.06 | J4: 2.6.2.3 2.3.3.4
A5: =ROW()-2 -> 3 | B5: 3.2.1.3 3.2.4.3 3.2.5.3 3.2.6.3 | C5: Product Items Management 商品项管理 | D5: Search Functions 搜索功能 Store inventory view and editing require authurization 门店库存的查看和编辑需要授权 | E5: 25 | F5: 2611 | G5: =E5*F5 -> 65275 | H5: 0.06 | J5: 3.5.1.1 2.6.1.7
A6: =ROW()-2 -> 4 | B6: 3.2.6.4.1 | C6: Table Management 桌台管理 | D6: Reservation 预定信息 | E6: 25 | F6: 2611 | G6: =E6*F6 -> 65275 | H6: 0.06 | J6: 3.1.2.4
A7: =ROW()-2 -> 5 | B7: 3.2.1.4 3.2.4.4 3.2.5.4 3.2.6.5 | C7: Guest Profile 游客身份识别 | D7: Log in登录 Profile Display显示游客身份信息 Previlege Recommendation权益推荐 Black List黑名单 | E7: 30 | F7: 2611 | G7: =E7*F7 -> 78330 | H7: 0.06
A8: =ROW()-2 -> 6 | B8: 3.2.2.5.1 | C8: Order Operation 订单操作 | D8: RFID Add product RFID添加商品 Modify Price 修改价格 Modify Inventory 修改库存 | E8: 55 | F8: 2611 | G8: =E8*F8 -> 143605 | H8: 0.06 | J8: 3.6.6.2
A9: =ROW()-2 -> 7 | B9: 3.2.1.6.5 3.2.3.4 3.2.4.6.4 3.2.5.6.4 3.2.6.7.4 3.2.6.7.5 3.2.7.4 | C9: Order Management 订单管理 | D9: Order Transmit 订单下发 Check & Order Modify 订单&账单编辑 | E9: 30 | F9: 2611 | G9: =E9*F9 -> 78330 | H9: 0.06 | J9: 2.4.1.1 2.4.1.2 2.4.1.3 2.4.1.4
A10: =ROW()-2 -> 8 | B10: 3.2.3.2 3.2.7.2 | C10: Order Landing 落单 | D10: Order Landing 落单 | E10: 25 | F10: 2611 | G10: =E10*F10 -> 65275 | H10: 0.06 | J10: 3.6.2.1 3.6.2.2 3.6.2.3
A11: =ROW()-2 -> 9 | B11: 3.2.1.7 3.2.4.7 3.2.5.7 3.2.6.8 | C11: Hardware Peripherals 硬件外设 | D11: Hardware Peripherals 硬件外设 | E11: 85 | F11: 2611 | G11: =E11*F11 -> 221935 | H11: 0.06 | J11: 2.9.1.3
A12: =ROW()-2 -> 10 | B12: 3.2.9.2 | C12: Inventory Management 库存管理 | D12: Store Repleishment 店间补货 Warehouse Repleishment 仓库补货 (产品安全溯源系统) | E12: 30 | F12: 2611 | G12: =E12*F12 -> 78330 | H12: 0.06 | J12: 3.6.3.1 3.5.2.2
A13: =ROW()-2 -> 11 | B13: 3.2.10.5 | C13: Product Management 商品管理 | D13: Configuration 功能配置 | H13: 0.06 | J13: 2.7.1.3
A14: =ROW()-2 -> 12 | B14: 3.2.10.1 3.2.10.2 3.2.10.3 3.2.10.4 | C14: Promotion Management 促销管理 | D14: Product Creation商品创建 Master Data Management 商品主档信息管理 Product Search & Product List商品查询&商品列表 Monitoring and Alert监控和预警 | H14: 0.06 | J14: 2.7.1.1 2.7.1.2 2.7.1.4 2.7.1.5
A15: =ROW()-2 -> 13 | B15: 3.2 | C15: Store Management 门店管理 | D15: Store Information Management 门店基础信息管理 | H15: 0.06 | J15: 2.6.1.5
A16: =ROW()-2 -> 14 | B16: 3.2 | C16: Workstation Management 工作终端管理 | D16: POS Workstation Management POS终端管理 | E16: 30 | F16: 2611 | G16: =E16*F16 -> 78330 | H16: 0.06 | J16: 2.9.1.1 2.9.1.3
A17: =ROW()-2 -> 15 | B17: 3.2 | D17: Printer Setting 打印机设置 | H17: 0.06 | J17: 2.9.2.1 2.9.2.2
A18: =ROW()-2 -> 16 | B18: 3.2.12.1 | C18: POS Report POS 报表 | D18: Report Creation 创建报表 | H18: 0.06 | J18: 2.10.1.1 2.10.1.2 2.10.1.3
A19: =ROW()-2 -> 17 | B19: 3.2.12.2 | D19: Self-defined Report 自定义报表功能 | H19: 0.06 | J19: 2.11.4.1 2.11.4.2 2.11.4.3 2.11.4.5
A20: =ROW()-2 -> 18 | B20: 3.2.13.1 | C20: System Admin 系统管理 | D20: Role management 角色管理 | E20: 30 | F20: 2611 | G20: =E20*F20 -> 78330 | H20: 0.06 | J20: 2.8.3.1 2.8.2.4
A21: =ROW()-2 -> 19 | B21: 3.2.13.2 | D21: Account management 账号管理 | H21: 0.06 | J21: 2.8.3.2 2.8.3.3
A22: =ROW()-2 -> 20 | B22: 3.2.13.3 | D22: User Journal 操作日志管理 | H22: 0.06 | J22: 2.8.3.4
A23: =ROW()-2 -> 21 | B23: 3.3.5 | C23: System Integration Requirements 系统集成需求 | D23: Receive SIMBA pushes Product Data interface 接收SIMBA推送的 商品信息接口 | H23: 0.06 | J23: 3.6.1.1 3.6.1.2
A24: =ROW()-2 -> 22 | B24: 3.3.5 | C24: System Integration Requirements 系统集成需求 | D24: Inventory Query Interface 库存查询接口（Merch） | E24: 0 | G24: 0 | H24: 0.06 | J24: 3.6.1.3
A25: =ROW()-2 -> 23 | B25: 3.3.5 | C25: System Integration Requirements 系统集成需求 | D25: Create Order Interface 创建订单接口 | E25: 25 | F25: 2611 | G25: =E25*F25 -> 65275 | H25: 0.06
A26: =ROW()-2 -> 24 | B26: 3.3.5 | C26: System Integration Requirements 系统集成需求 | D26: Commodity Trading Push Interface 商品交易推送接口 | H26: 0.06
A27: =ROW()-2 -> 25 | B27: 3.3.5 | C27: System Integration Requirements 系统集成需求 | D27: POS Docking CCTV POS对接CCTV | E27: 130 | F27: 2611 | G27: =E27*F27 -> 339430 | H27: 0.06 | J27: 3.7.7.10
A28: =ROW()-2 -> 26 | B28: 3.3.5 | C28: System Integration Requirements 系统集成需求 | D28: Coupon Query Interface 券查询口 | H28: 0.06 | J28: 3.6.6.1
A29: =ROW()-2 -> 27 | B29: 3.3.5 | C29: System Integration Requirements 系统集成需求 | D29: Coupon Verification Interface 券核销接口 | E29: 25 | F29: 2611 | G29: =E29*F29 -> 65275 | H29: 0.06 | J29: 3.4.1.3
A30: =ROW()-2 -> 28 | B30: 3.3.5 | C30: System Integration Requirements 系统集成需求 | D30: Inventory Updates Interface 库存更新接口(F&B) | H30: 0.06 | J30: 3.5.1.1
A31: =ROW()-2 -> 29 | B31: 3.3.5 | C31: System Integration Requirements 系统集成需求 | D31: Invoicing Synchronous Interface 同步开票信息接口 | H31: 0.06 | J31: 3.7.5.1
A32: =ROW()-2 -> 30 | B32: 3.3.5 | C32: System Integration Requirements 系统集成需求 | D32: Store CostCenter Pushes the UDS Interface 门店成本中心推送UDS接口 | H32: 0.06
A33: =ROW()-2 -> 31 | B33: 3.3.5 | C33: System Integration Requirements 系统集成需求 | D33: 推送销售数据到UDS（SAP） | E33: 50 | F33: 2611 | G33: =E33*F33 -> 130550 | H33: 0.06
A34: =ROW()-2 -> 32 | B34: 3.3.5 | C34: System Integration Requirements 系统集成需求 | D34: 推送销售数据到UDS（LongView） | E34: 10 | F34: 2611 | G34: =E34*F34 -> 26110 | H34: 0.06
A35: =ROW()-2 -> 33 | B35: 3.3.5 | C35: System Integration Requirements 系统集成需求 | D35: 推送销售数据到UDS（Kornos） | E35: 28 | F35: 2611 | G35: =E35*F35 -> 73108 | H35: 0.06
A36: =ROW()-2 -> 34 | B36: 3.3.5 | C36: System Integration Requirements 系统集成需求 | D36: Employee Discount Information Push Interface 员工折扣信息推送接口 | E36: 45 | F36: 2611 | G36: =E36*F36 -> 117495 | H36: 0.06
A37: =ROW()-2 -> 35 | B37: 3.3.5 | C37: System Integration Requirements 系统集成需求 | D37: Inquire%Verify Member Information 查询验证会员信息 | E37: 15 | F37: 2611 | G37: =E37*F37 -> 39165 | H37: 0.06
A38: =ROW()-2 -> 36 | B38: 3.3.5 | C38: System Integration Requirements 系统集成需求 | D38: Inventory Updates Interface 库存更新接口(Merch) | E38: 10 | F38: 2611 | G38: =E38*F38 -> 26110 | H38: 0.06
A39: =ROW()-2 -> 37 | B39: 3.3.5 | C39: System Integration Requirements 系统集成需求 | D39: Order Placement Interface 订单落单接口 | E39: 10 | F39: 2611 | G39: =E39*F39 -> 26110 | H39: 0.06
A40: =ROW()-2 -> 38 | B40: 3.3.5 | C40: System Integration Requirements 系统集成需求 | D40: Order Query Interface 订单查询接口 | E40: 8 | F40: 2611 | G40: =E40*F40 -> 20888 | H40: 0.06
A41: =ROW()-2 -> 39 | B41: 3.3.5 | C41: System Integration Requirements 系统集成需求 | D41: Return Request Interface 退货申请接口 | E41: 15 | F41: 2611 | G41: =E41*F41 -> 39165 | H41: 0.06
A42: =ROW()-2 -> 40 | B42: 3.3.5 | C42: System Integration Requirements 系统集成需求 | D42: Product Query Interface 商品查询接口 | E42: 5 | F42: 2611 | G42: =E42*F42 -> 13055 | H42: 0.06
A43: =ROW()-2 -> 41 | B43: 3.3.5 | C43: System Integration Requirements 系统集成需求 | D43: POS推送订单信息Coupon接口 | E43: 10 | F43: 2611 | G43: =E43*F43 -> 26110 | H43: 0.06
A44: =ROW()-2 -> 42 | B44: 3.3.5 | C44: System Integration Requirements 系统集成需求 | D44: Product Information Synchronous Interface 商品信息同步接口 | E44: 10 | F44: 2611 | G44: =E44*F44 -> 26110 | H44: 0.06
... A48: =ROW()-2 -> 46 | B48: 3.3.5 | C48: System Integration Requirements 系统集成需求 | D48: Push the account Information to Hotel Systm 推送房账信息给Hotel System | E48: 25 | F48: 2611 | G48: =E48*F48 -> 65275 | H48: 0.06
A49: =ROW()-2 -> 47 | B49: 3.3.5 | C49: System Integration Requirements 系统集成需求 | D49: Transaction Payment Interface 交易支付接口 | E49: 30 | F49: 2611 | G49: =E49*F49 -> 78330 | H49: 0.06 | J49: 3.7.7.7
A50: =ROW()-2 -> 48 | B50: 3.3.5 | C50: System Integration Requirements 系统集成需求 | D50: Payment Status Query Interface 支付状态查询接口 | E50: 25 | F50: 2611 | G50: =E50*F50 -> 65275 | H50: 0.06
A51: =ROW()-2 -> 49 | B51: 3.3.5 | C51: System Integration Requirements 系统集成需求 | D51: Refund Interface 退款接口 | E51: 10 | F51: 2611 | G51: =E51*F51 -> 26110 | H51: 0.06
A52: =ROW()-2 -> 50 | B52: 3.3.5 | C52: System Integration Requirements 系统集成需求 | D52: Push F&B Information to the F&B POS system 推送餐饮信息给 F&B POS系统 | E52: 5 | F52: 2611 | G52: =E52*F52 -> 13055 | H52: 0.06
A53: =ROW()-2 -> 51 | B53: 3.3.5 | C53: System Integration Requirements 系统集成需求 | D53: 判断coupon有效性 | E53: 5 | F53: 2611 | G53: =E53*F53 -> 13055 | H53: 0.06
A54: =ROW()-2 -> 52 | B54: 3.3.5 | C54: System Integration Requirements 系统集成需求 | D54: Push the sales data of the airport store to the system Interface of the airport tenant 推送机场店销售数据给机场租户系统接口 | E54: 3 | F54: 2611 | G54: =E54*F54 -> 7833 | H54: 0.06 | J54: 3.7.7.9
A55: RFP 更新（需求新增及删除部分）10.17
A56: 53 | B56: 3.2.1.2.1 3.2.2.2.1 3.2.4.2.1 3.2.5.2.1 3.2.6.2.1 | C56: Store Open开店 | D56: Remove the startup receipt printing function 去掉打印开机小票功能 | E56: -10 | F56: 2611 | G56: =E56*F56 -> -26110 | H56: 0.06 | K56: 去除
A57: 54 | B57: 3.2.1.2.1 3.2.2.2.1 3.2.4.2.1 3.2.5.2.1 3.2.6.2.1 | C57: Store Open开店 | D57: Add emergency payment function 新增应急支付功能 | E57: 10 | F57: 2611 | G57: =E57*F57 -> 26110 | H57: 0.06 | I57: 5种场景 | J57: 2.3.3.1 2.3.3.2 2.3.3.3
A58: 55 | B58: 3.2.1.2.2 3.2.2.2.2 3.2.4.2.2 3.2.5.2.2 3.2.6.2.2 | C58: Store Close 关店 | D58: 1. Daily settlement每日结算 2. Upload daily settlement 上传检查日结信息 3. Drop pending order in draft box关闭暂存订单 | E58: 10 | F58: 2611 | G58: =E58*F58 -> 26110 | H58: 0.06 | I58: 5种场景 | J58: 2.6.1.3 2.6.1.4 2.6.2.4
A59: 56 | B59: 3.2.1.4.1 3.2.2.4.1 3.2.4.4.1 3.2.5.4.1 3.2.6.5.1 | C59: Guest log in游客登录 | D59: 1. Add multiple identity recognition types: Annual Pass, SMED, HEP, Employee, and C33 Member 添加几种身份识别：年卡、SMED、HEP、员工、C33会员 2. Display guest greeting messages by group 分组展示游客问候信息 | E59: 15 | F59: 2611 | G59: =E59*F59 -> 39165 | H59: 0.06 | J59: 3.3.1.1 3.3.1.2 3.3.1.3 3.3.1.4 6.1.1.2
A60: 57 | B60: 3.2.1.4.3 3.2.2.4.3 3.2.4.4.3 3.2.5.4.3 3.2.6.5.3 | C60: Previlege Recommendation权益推荐 | D60: Recommend add-on purchases to enjoy more discounts 推荐加购凑单以享受更多折扣 | E60: 20 | F60: 2611 | G60: =E60*F60 -> 52220 | H60: 0.06 | I60: 促销中心 | J60: 6.1.2.2
A61: 58 | B61: 3.2.1.5.1 3.2.2.5.1 | C61: Create Order创建订单 | D61: 1. Check product sales status 检查商品售卖状态 2. Enter promotional additional information 填写促销附加信息 | E61: 8 | F61: 2611 | G61: =E61*F61 -> 20888 | H61: 0.06 | J61: 2.1.1.5 2.2.2.3
A62: 59 | B62: 3.2.1.5.2 3.2.2.5.2 3.2.4.5.2 3.2.5.5.2 3.2.6.6.2 | C62: Settlement结算 | D62: Remove facial payment function 去掉人脸支付功能 | E62: -20 | F62: 2611 | G62: =E62*F62 -> -52220 | H62: 0.06 | K62: 去除
A63: 60 | B63: 3.2.1.5.2 3.2.2.5.2 3.2.4.5.2 | C63: Settlement结算 | D63: 1. Support room charge payment for hotel guests 酒店客户支持挂房账支付 2. Anti-counterfeit tape code verification during return 退货时防伪胶带数字验证 | E63: 10 | F63: 2611 | G63: =E63*F63 -> 26110 | H63: 0.06 | I63: 对接酒店支付系统，查询押金 | J63: 2.3.2.4 2.3.2.5
A64: 61 | B64: 3.2.1.5.4 | C64: Store Pickup门店自提 | D64: Remove store pickup function 删除门店自提功能 | E64: -30 | F64: 2611 | G64: =E64*F64 -> -78330 | H64: 0.06
A65: 62 | B65: 3.2.1.6 3.2.2.6 3.2.4.6 3.2.5.6 3.2.6.7 | C65: Order Management 订单管理 | D65: 1. Enhance return and refund functions 退换货退款功能增强 2. Record and synchronize sales orders to SAP 销售订单记录并同步至SAP | E65: 30 | F65: 2611 | G65: =E65*F65 -> 78330 | H65: 0.06 | J65: 2.4.3.1 2.4.3.6 2.4.3.4 2.4.3.5 2.4.3.7
A66: 63 | B66: 3.2.2.5.5 | C66: Exchange game prizes游戏兑奖 | D66: Exchange game prizes游戏兑奖 | E66: 10 | F66: 2611 | G66: =E66*F66 -> 26110 | H66: 0.06 | J66: 3.1.2.2
A67: 64 | B67: 3.2.2.5.5 | C67: Deposit for stroller童车押金 | D67: Deposit for stroller童车押金 | E67: 10 | F67: 2611 | G67: =E67*F67 -> 26110 | H67: 0.06 | J67: 3.1.2.3
A68: 65 | B68: 3.2.3.4 | C68: Order Transmit订单下发 | D68: Online order integration exception handling, reporting, and logging 线上订单集成异常处理、报表、日志 | E68: 10 | F68: 2611 | G68: =E68*F68 -> 26110 | H68: 0.06 | J68: 3.6.2.4
A69: 66 | B69: 3.2.4.5.1 3.2.5.5.1 3.2.6.6.1 | C69: F&B create Order餐饮创建订单 | D69: 1. service fee function 服务费功能 2. Inventory alert库存预警 | E69: 10 | F69: 2611 | G69: =E69*F69 -> 26110 | H69: 0.06 | J69: 2.3.4.1 2.3.4.2 2.3.4.3
A70: 67 | B70: 3.2.4.5.2 3.2.5.5.2 3.2.6.6.2 | C70: F&B cettlement 餐饮结算 | D70: Kitchen receipt餐饮厨房小票 | E70: 8 | F70: 2611 | G70: =E70*F70 -> 20888 | H70: 0.06 | J70: 2.5.3.1 2.5.3.2 2.5.3.3
A71: 68 | B71: 3.2.4.6.4 3.2.5.6.4 3.2.6.7.5 | C71: F&B order transmit餐饮订单下发 | D71: Sync order information to KDS screen同步订单信息至厨房屏幕 | E71: 5 | F71: 2611 | G71: =E71*F71 -> 13055 | H71: 0.06 | J71: 3.6.3.3
A72: 69 | B72: 3.2.5.5.2 3.2.6.6.2 | C72: F&B Settlement餐饮结算 | D72: 1. Support room charge payment for hotel guests 酒店客户支持挂房账支付 2. Enable amount allocation(AA) after payment 支付分摊(AA) | E72: 8 | F72: 2611 | G72: =E72*F72 -> 20888 | H72: 0.06 | J72: 2.1.3.5 2.3.2.6
A73: 70 | B73: 3.2.6.4 | C73: Table Management 桌台管理 | D73: 1. Integrate with TableCheck reservation management system 集成预定管理系统Table Check 2. Add support for buffet ordering 新增支持自助餐点单 3.Add support for banquet ordering 新增宴会点单 4. Support room charge支持挂房账 | E73: 20 | F73: 2611 | G73: =E73*F73 -> 52220 | H73: 0.06 | J73: 5.1.1.1 2.1.3.2 2.1.3.4
A74: 71 | B74: 3.2.7.2 | C74: Order Landing 落单 | D74: Integrate with MO to synchronize available inventory and invoice status 与MO集成，同步可售库存及发票状态 | E74: 8 | F74: 2611 | G74: =E74*F74 -> 20888 | H74: 0.06 | J74: 5.2.1.4
A75: 72 | B75: 3.2.8 | C75: Merch and F&B Cross-sell Stores 商品&餐饮综合门店 | D75: Joint sales financial - revenue and accounting 融合财务-收入分割与核算 | E75: 20 | F75: 2611 | G75: =E75*F75 -> 52220 | H75: 0.06 | J75: 4.2.1.1
A76: 73 | B76: 3.2.10.2 | C76: Master Data Management 商品主档信息管理 | D76: Add purchase limit function 新增限购功能 | E76: 5 | F76: 2611 | G76: =E76*F76 -> 13055 | H76: 0.06 | J76: 3.2.1.1 3.2.1.2 3.2.1.3 3.2.1.4
A77: 74 | B77: 3.2.10.6 | C77: Merch supply chain integration - SIMBA 商品供应链-SIMBA | D77: Integrate with retail supply chain system 对接零售供应链系统 | E77: 3 | F77: 2611 | G77: =E77*F77 -> 7833 | H77: 0.06 | K77: 和系统数据同步21行 雷同
A78: 75 | B78: 3.2.13.1 | C78: Role Management 角色管理 | D78: Audit privilege on permission isolation权限隔离和审计 | E78: 8 | F78: 2611 | G78: =E78*F78 -> 20888 | H78: 0.06
A79: 76 | B79: 3.2.13.10 | C79: Financial foundation data management 财务主数据管理 | D79: Financial foundation data management财务主数据管理 | E79: 5 | F79: 2611 | G79: =E79*F79 -> 13055 | H79: 0.06 | J79: 2.11.3.1 2.11.3.2 2.11.4.1 2.11.4.2 2.11.4.3 2.11.4.4 2.11.4.5
A80: 77 | B80: 3.2.13.11 | C80: Enhanced in finance operations & control 财务运营和控制增强 | D80: Enhanced in finance operations & control财务运营和控制增强 | E80: 10 | F80: 2611 | G80: =E80*F80 -> 26110 | H80: 0.06 | J80: 3.7.2.3 3.7.3.1 3.7.3.10 3.7.3.11 3.7.3.12 3.7.3.2 3.7.3.3 3.7.3.9 3.7.5.1 3.7.5.2 3.7.5.3 3.7.5.4 3.7.6.1 3.7.7.10 3.7.7.11 3.7.7.3 3.7.7.7 3.7.7.9
A81: 78 | B81: 3.2.14 | C81: Terminals and peripherals 终端与外设 | D81: Terminals and peripherals management终端与外设管理 | E81: 20 | F81: 2611 | G81: =E81*F81 -> 52220 | H81: 0.06 | J81: 2.9.1.4 2.9.2.1 2.9.2.4 5.1.2.2
A82: 79 | B82: 3.2.15 | C82: Members and Consumer Activation 会员和消费者互动 | D82: Members and Consumer Activation会员和消费者互动 | E82: 10 | F82: 2611 | G82: =E82*F82 -> 26110 | H82: 0.06 | J82: 6.1.1.1 6.1.1.3 6.1.2.1 6.1.2.2 6.1.2.3 6.1.3.1 6.1.3.2 6.2.1.1 6.2.1.2 6.2.1.3 6.2.2.1
A83: 80 | B83: 3.3.1 3.3.5 | C83: Overall Infrastructure Requirements 总体架构需 System Integration Requirements 系统集成需求 | D83: 1. Remove OMS (Online Order System) integration requirement 删除OMS OMS 系统（线上订单系统）集成需求 2. Remove Parking System integration requirement 删除Parking 停车收费系统 集成需求 | E83: -30 | F83: 2611 | G83: =E83*F83 -> -78330 | H83: 0.06
A84: 81 | B84: 3.3.1 3.3.5 | C84: Overall Infrastructure Requirements 总体架构需 System Integration Requirements 系统集成需求 | D84: PMS – Opera Hotel Property Management System (Room Charge)+D33 PMS – Opera 酒店资产管理系统（挂房账） | E84: 0 | F84: 2611 | G84: =E84*F84 -> 0 | H84: 0.06 | I84: 上述工作量评估中已包含
A85: Total合计： | E85: =SUM(E3:E84) -> 1133 | G85: =SUM(G3:G84) -> 2958263

Sheet BRD & EPIC
A1: EPIC - Project Name | F1: 点击返回说明页 Back to Instructions | X1: 0 | AC1: 总金额 | AD1: 有效条数 | AE1: 总人天
A2: LOB VP Signature | C2: Tony Castillo/Steve Sulaski | D2: Date | AC2: 7378263 | AD2: =SUBTOTAL(103, P:P) - 1 -> 241 | AE2: =SUM(Y:Y) -> 20181
A3: PM Diretctor Level Sigature | C3: Jimmy Lee | D3: Date
A4: DM Diretctor Level Sigature | C4: Peter Zhang | D4: Date
A6: BRD Priority | B6: 0. BRD Overview | C6: 0.0 BRD Detailed Requirement | D6: 0.0.0 EPIC Title | E6: 0.0.0.0 EPIC Story | F6: Description | G6: Dependencies | H6: EPIC Story(CN) | I6: Description(CN) | J6: Comment | K6: Follow-up Group | L6: Follow-up | M6: Follow-up with vendor | N6: Task Title | O6: Task Description | P6: system type | Q6: follw up PM | R6: follow up | S6: Develop Labor(man/day) | T6: Real Develop Labor(Man/Hour) | U6: Real Develop Labor(Man/Day) | V6: 表设计 | W6: 表个数 | X6: task count | Y6: task sum count | Z6: Review Pass | AA6: Lucky Comment | AB6: check content change | AD6: Asset Function | AE6: 分摊到1条的钱数
A7: 0 | B7: 0. Project Foundation | C7: 0.1 SE|Hosting | D7: 0.1.1 SE|System deployment in Cloud | E7: 0.1.1.1 Services/systems set up in cloud, Create new cloud accounts, New vendor system support in Cloud | G7: SE | H7: 0.1.1.1 在云中设置的服务/系统，创建新的云账户，在云中支持新的供应商系统 | T7: =$S7*DE_Cost!$B$1*8 -> 0 | U7: =$S7*DE_Cost!$B$1 -> 0 | X7: =IF(TRIM(P7)="", 0, LEN(P7) - LEN(SUBSTITUTE(P7, "&", "")) + 1) -> 0 | Y7: =S7 * X7 -> 0 | Z7: Y | AE7: =(Y7 / $AE$2) * $AC$2 -> 0
D8: 0.1.2 SE|System deployment on-premise | E8: 0.1.2.1 Services/systems deployment/configurition/automation for new servers in on-premise datacenter | G8: SE | H8: 0.1.2.1 本地数据中心新服务器部署/配置/自动化服务/系统 | T8: =$S8*DE_Cost!$B$1*8 -> 0 | U8: =$S8*DE_Cost!$B$1 -> 0 | X8: =IF(TRIM(P8)="", 0, LEN(P8) - LEN(SUBSTITUTE(P8, "&", "")) + 1) -> 0 | Y8: =S8 * X8 -> 0 | Z8: Y | AE8: =(Y8 / $AE$2) * $AC$2 -> 0
D9: 0.1.3 SE|Database deployment in Cloud | E9: 0.1.3.1 Database set up in cloud, dashboard requirements, database schema changes, data migration | G9: SE | H9: 0.1.3.1 云端数据库设置，仪表板需求，数据库架构变更，数据迁移 | T9: =$S9*DE_Cost!$B$1*8 -> 0 | U9: =$S9*DE_Cost!$B$1 -> 0 | X9: =IF(TRIM(P9)="", 0, LEN(P9) - LEN(SUBSTITUTE(P9, "&", "")) + 1) -> 0 | Y9: =S9 * X9 -> 0 | Z9: Y | AE9: =(Y9 / $AE$2) * $AC$2 -> 0
D10: 0.1.4 SE|Cloud Hosting | E10: 0.1.4.1 Hosting fee in AliCloud, AWS | G10: SE | H10: 0.1.4.1 阿里云、AWS 托管费用 | T10: =$S10*DE_Cost!$B$1*8 -> 0 | U10: =$S10*DE_Cost!$B$1 -> 0 | X10: =IF(TRIM(P10)="", 0, LEN(P10) - LEN(SUBSTITUTE(P10, "&", "")) + 1) -> 0 | Y10: =S10 * X10 -> 0 | Z10: Y | AE10: =(Y10 / $AE$2) * $AC$2 -> 0
D11: 0.1.5 SE|Hardware purchase | E11: 0.1.5.1 New servers/storage/devices in on-premise datacenter | G11: SE | H11: 0.1.5.1 本地数据中心中的新服务器/存储设备 | T11: =$S11*DE_Cost!$B$1*8 -> 0 | U11: =$S11*DE_Cost!$B$1 -> 0 | X11: =IF(TRIM(P11)="", 0, LEN(P11) - LEN(SUBSTITUTE(P11, "&", "")) + 1) -> 0 | Y11: =S11 * X11 -> 0 | Z11: Y | AE11: =(Y11 / $AE$2) * $AC$2 -> 0
D12: 0.1.6 SE|Vendor Service | E12: 0.1.6.1 3rd party vendor services | G12: SE | H12: 0.1.6.1 第三方供应商服务 | T12: =$S12*DE_Cost!$B$1*8 -> 0 | U12: =$S12*DE_Cost!$B$1 -> 0 | X12: =IF(TRIM(P12)="", 0, LEN(P12) - LEN(SUBSTITUTE(P12, "&", "")) + 1) -> 0 | Y12: =S12 * X12 -> 0 | Z12: Y | AE12: =(Y12 / $AE$2) * $AC$2 -> 0
D13: 0.1.7 SE|License|Software | E13: 0.1.7.1 License cost for hardware/software | G13: SE | H13: 0.1.7.1 硬件/软件的许可费用 | T13: =$S13*DE_Cost!$B$1*8 -> 0 | U13: =$S13*DE_Cost!$B$1 -> 0 | X13: =IF(TRIM(P13)="", 0, LEN(P13) - LEN(SUBSTITUTE(P13, "&", "")) + 1) -> 0 | Y13: =S13 * X13 -> 0 | Z13: Y | AE13: =(Y13 / $AE$2) * $AC$2 -> 0
C14: 0.2 QO|GQE | D14: 0.2.1 GQE |Manual Testing | E14: 0.2.1.1 Design test cases, execute test cases, analyze defects, write test reports for Manual Testing. | G14: QO | H14: 0.2.1.1 设计测试用例，执行测试用例，分析缺陷，编写手动测试报告。 | K14: QO | T14: =$S14*DE_Cost!$B$1*8 -> 0 | U14: =$S14*DE_Cost!$B$1 -> 0 | X14: =IF(TRIM(P14)="", 0, LEN(P14) - LEN(SUBSTITUTE(P14, "&", "")) + 1) -> 0 | Y14: =S14 * X14 -> 0 | Z14: Y | AE14: =(Y14 / $AE$2) * $AC$2 -> 0
D15: 0.2.2 GQE |Automation Testing | E15: 0.2.2.1 Design test cases, encode test cases, execute automation scripts, analyze defects, write test reports for Automation Testing. | G15: QO | H15: 0.2.2.1 设计测试用例，编码测试用例，执行自动化脚本，分析缺陷，编写自动化测试报告。 | K15: QO | T15: =$S15*DE_Cost!$B$1*8 -> 0 | U15: =$S15*DE_Cost!$B$1 -> 0 | X15: =IF(TRIM(P15)="", 0, LEN(P15) - LEN(SUBSTITUTE(P15, "&", "")) + 1) -> 0 | Y15: =S15 * X15 -> 0 | Z15: Y | AE15: =(Y15 / $AE$2) * $AC$2 -> 0
D16: 0.2.3 GQE |Performance Testing | E16: 0.2.3.1 Design test cases, encode test cases, execute performance test cases, analyze defects, write test reports for Performance Testing. | G16: QO | H16: 0.2.3.1 设计测试用例，编码测试用例，执行性能测试用例，分析缺陷，编写性能测试报告。 | K16: QO | T16: =$S16*DE_Cost!$B$1*8 -> 0 | U16: =$S16*DE_Cost!$B$1 -> 0 | X16: =IF(TRIM(P16)="", 0, LEN(P16) - LEN(SUBSTITUTE(P16, "&", "")) + 1) -> 0 | Y16: =S16 * X16 -> 0 | Z16: Y | AE16: =(Y16 / $AE$2) * $AC$2 -> 0
D17: 0.2.4 GQE |Command Center Support | E17: 0.2.4.1 Support command centers during launch and hypercare period. | G17: QO | H17: 0.2.4.1 在发布和超保支持期间支持指挥中心。 | K17: QO | T17: =$S17*DE_Cost!$B$1*8 -> 0 | U17: =$S17*DE_Cost!$B$1 -> 0 | X17: =IF(TRIM(P17)="", 0, LEN(P17) - LEN(SUBSTITUTE(P17, "&", "")) + 1) -> 0 | Y17: =S17 * X17 -> 0 | Z17: Y | AE17: =(Y17 / $AE$2) * $AC$2 -> 0
C18: 0.3 QO|Release Management | D18: 0.3.1 RM |Change and Release Support | E18: 0.3.1.1 Plan, design, schedule, validate, deploy and control system changes and releases to support system launches. | G18: QO | H18: 0.3.1.1 计划、设计、安排、验证、部署和控制系统变更与发布，以支持系统上线。 | K18: QO | T18: =$S18*DE_Cost!$B$1*8 -> 0 | U18: =$S18*DE_Cost!$B$1 -> 0 | X18: =IF(TRIM(P18)="", 0, LEN(P18) - LEN(SUBSTITUTE(P18, "&", "")) + 1) -> 0 | Y18: =S18 * X18 -> 0 | Z18: Y | AE18: =(Y18 / $AE$2) * $AC$2 -> 0
D19: 0.3.2 RM |Command Center Support | E19: 0.3.2.1 Support command centers during hypercare period. | G19: QO | H19: 0.3.2.1 在超保期间支持指挥中心。 | K19: QO | T19: =$S19*DE_Cost!$B$1*8 -> 0 | U19: =$S19*DE_Cost!$B$1 -> 0 | X19: =IF(TRIM(P19)="", 0, LEN(P19) - LEN(SUBSTITUTE(P19, "&", "")) + 1) -> 0 | Y19: =S19 * X19 -> 0 | Z19: Y | AE19: =(Y19 / $AE$2) * $AC$2 -> 0
C20: 0.4 QO|Incident Management | D20: 0.4.1 L2 |Configuration Management | E20: 0.4.1.1 Perform configuration changes on TYK, ACP, UAP, VDM. | G20: QO | H20: 0.4.1.1 在 TYK、ACP、UAP、VDM 上执行配置更改。 | J20: 确认Onsite时间， L2需要规划成员支持 7天，7:~23 | K20: QO | T20: =$S20*DE_Cost!$B$1*8 -> 0 | U20: =$S20*DE_Cost!$B$1 -> 0 | X20: =IF(TRIM(P20)="", 0, LEN(P20) - LEN(SUBSTITUTE(P20, "&", "")) + 1) -> 0 | Y20: =S20 * X20 -> 0 | Z20: Y | AE20: =(Y20 / $AE$2) * $AC$2 -> 0
D21: 0.4.2 L2 |Command Center Coordination and Support | E21: 0.4.2.1 Plan and implement command centers to support launches. | G21: QO | H21: 0.4.2.1 规划并实施支持发射的指挥中心。 | J21: 确认try run时间，住酒店40人/1000 | K21: QO | T21: =$S21*DE_Cost!$B$1*8 -> 0 | U21: =$S21*DE_Cost!$B$1 -> 0 | X21: =IF(TRIM(P21)="", 0, LEN(P21) - LEN(SUBSTITUTE(P21, "&", "")) + 1) -> 0 | Y21: =S21 * X21 -> 0 | Z21: Y | AE21: =(Y21 / $AE$2) * $AC$2 -> 0
C22: 0.5 QO|Problem Management | D22: 0.5.1 Problem Management |Proactive Problem Management | E22: 0.5.1.1 Follow all opened defects that will move to production with the launch and drive the resolution of defects before they turn into incidents. | G22: QO | H22: 0.5.1.1 跟踪所有将随发布移至生产环境的缺陷，并在其演变为事件前推动解决这些缺陷。 | J22: 需要确认我们自己是否介入测试 | K22: QO | T22: =$S22*DE_Cost!$B$1*8 -> 0 | U22: =$S22*DE_Cost!$B$1 -> 0 | X22: =IF(TRIM(P22)="", 0, LEN(P22) - LEN(SUBSTITUTE(P22, "&", "")) + 1) -> 0 | Y22: =S22 * X22 -> 0 | Z22: Y | AE22: =(Y22 / $AE$2) * $AC$2 -> 0
C23: 0.6 InfoSec|Information Security | D23: 0.6.1 InfoSec|Security Terms Review in the Contract | E23: 0.6.1.1 Whenever the 3rd party provider would like to change the default information security terms and schedules, the project team needs to contact InfoSec for change review. | G23: Security | H23: 0.6.1.1 当第三方提供商希望更改默认信息安全条款和时间表时，项目团队需要联系信息安全部门进行变更审核。 | T23: =$S23*DE_Cost!$B$1*8 -> 0 | U23: =$S23*DE_Cost!$B$1 -> 0 | X23: =IF(TRIM(P23)="", 0, LEN(P23) - LEN(SUBSTITUTE(P23, "&", "")) + 1) -> 0 | Y23: =S23 * X23 -> 0 | Z23: Y | AE23: =(Y23 / $AE$2) * $AC$2 -> 0
D24: 0.6.2 InfoSec|Information Security Assessment (ISA) | E24: 0.6.2.1 All the new applications and significant change to the existing applications need to complete the information security assessment. | G24: Security | H24: 0.6.2.1 所有新应用及对现有应用的重大变更均需完成信息安全评估。 | T24: =$S24*DE_Cost!$B$1*8 -> 0 | U24: =$S24*DE_Cost!$B$1 -> 0 | X24: =IF(TRIM(P24)="", 0, LEN(P24) - LEN(SUBSTITUTE(P24, "&", "")) + 1) -> 0 | Y24: =S24 * X24 -> 0 | Z24: Y | AE24: =(Y24 / $AE$2) * $AC$2 -> 0
D25: 0.6.3 InfoSec|RFP Security Questionnaire and/or Third Party Assessment (TPA) | E25: 0.6.3.1 If a 3rd party provider is involved, RFP security questionnaire is mandatory to be filled, and if necessary the Third Party Assessment should be conducted. | G25: Security | H25: 0.6.3.1 如果涉及第三方供应商，则必须填写 RFP 安全问卷，并在必要时进行第三方评估。 | T25: =$S25*DE_Cost!$B$1*8 -> 0 | U25: =$S25*DE_Cost!$B$1 -> 0 | X25: =IF(TRIM(P25)="", 0, LEN(P25) - LEN(SUBSTITUTE(P25, "&", "")) + 1) -> 0 | Y25: =S25 * X25 -> 0 | Z25: Y | AE25: =(Y25 / $AE$2) * $AC$2 -> 0
D26: 0.6.4 InfoSec|Application Security Enrollment and Testing | E26: 0.6.4.1 This includes the applicable enrollment and testing, such as SAST, DAST, Pen-Test, Privacy Scan, Mobile Shield and etc. | G26: Security | H26: 0.6.4.1 这包括适用的注册和测试，例如 SAST、DAST、渗透测试、隐私扫描、移动防护等。 | T26: =$S26*DE_Cost!$B$1*8 -> 0 | U26: =$S26*DE_Cost!$B$1 -> 0 | X26: =IF(TRIM(P26)="", 0, LEN(P26) - LEN(SUBSTITUTE(P26, "&", "")) + 1) -> 0 | Y26: =S26 * X26 -> 0 | Z26: Y | AE26: =(Y26 / $AE$2) * $AC$2 -> 0
D27: 0.6.5 InfoSec|Security Operation Monitoring and Verificiation | E27: 0.6.5.1 This includes: Network Connection Review (Firewall); Endpoint Security Verification and Testing; Scripting for MyJira Sync; Review Application Hosting and Cloud Infrastructure SCS; Vulnerability Scanning. | G27: Security | H27: 0.6.5.1 这包括：网络连接审查（防火墙）；终端安全验证和测试；MyJira Sync 的脚本编写；审查应用程序托管和云基础设施 SCS；漏洞扫描。 | T27: =$S27*DE_Cost!$B$1*8 -> 0 | U27: =$S27*DE_Cost!$B$1 -> 0 | X27: =IF(TRIM(P27)="", 0, LEN(P27) - LEN(SUBSTITUTE(P27, "&", "")) + 1) -> 0 | Y27: =S27 * X27 -> 0 | Z27: Y | AE27: =(Y27 / $AE$2) * $AC$2 -> 0
D28: 0.6.6 InfoSec|Identity and Access Management | E28: 0.6.6.1 Integration with central authentication and authorization platforms. | G28: Security | H28: 0.6.6.1 与中央身份验证和授权平台的集成。 | T28: =$S28*DE_Cost!$B$1*8 -> 0 | U28: =$S28*DE_Cost!$B$1 -> 0 | X28: =IF(TRIM(P28)="", 0, LEN(P28) - LEN(SUBSTITUTE(P28, "&", "")) + 1) -> 0 | Y28: =S28 * X28 -> 0 | Z28: Y | AE28: =(Y28 / $AE$2) * $AC$2 -> 0
D29: 0.6.7 InfoSec|Online Fraud Detection | E29: 0.6.7.1 Online fraud rules review and integration with AOFD platform | G29: Security | H29: 0.6.7.1 在线欺诈规则审查并与 AOFD 平台集成 | T29: =$S29*DE_Cost!$B$1*8 -> 0 | U29: =$S29*DE_Cost!$B$1 -> 0 | X29: =IF(TRIM(P29)="", 0, LEN(P29) - LEN(SUBSTITUTE(P29, "&", "")) + 1) -> 0 | Y29: =S29 * X29 -> 0 | Z29: Y | AE29: =(Y29 / $AE$2) * $AC$2 -> 0
D30: 0.6.8 InfoSec|Disaster Recovery and Business Continuity Management | E30: 0.6.8.1 Conduct a Business Impact Analysis (BIA) to identify critical IT services and determine the IT service continuity strategy. Develop and test comprehensive IT Service Continuity Plans to maintain business operations in the event of security incidents or system downtime | G30: Security | H30: 0.6.8.1 进行业务影响分析（BIA）以识别关键 IT 服务并确定 IT 服务连续性策略。制定并测试全面的 IT 服务连续性计划，以在发生安全事件或系统停机时维持业务运营。 | T30: =$S30*DE_Cost!$B$1*8 -> 0 | U30: =$S30*DE_Cost!$B$1 -> 0 | X30: =IF(TRIM(P30)="", 0, LEN(P30) - LEN(SUBSTITUTE(P30, "&", "")) + 1) -> 0 | Y30: =S30 * X30 -> 0 | Z30: Y | AE30: =(Y30 / $AE$2) * $AC$2 -> 0
C31: 0.7 EA|Enterprise Architecture | D31: 0.7.1 EA|Solution Architecture Review | E31: 0.7.1.1 Collaborative work for appropriate design of availability, resilience, integrations and ensure all EA standards are aligned and complied | G31: EA | H31: 0.7.1.1 协同工作，确保可用性、弹性、集成设计的合理性，并确保所有企业架构标准保持一致并得到遵守 | T31: =$S31*DE_Cost!$B$1*8 -> 0 | U31: =$S31*DE_Cost!$B$1 -> 0 | X31: =IF(TRIM(P31)="", 0, LEN(P31) - LEN(SUBSTITUTE(P31, "&", "")) + 1) -> 0 | Y31: =S31 * X31 -> 0 | Z31: Y | AE31: =(Y31 / $AE$2) * $AC$2 -> 0
C32: 0.8 F&IT|Data Technology | D32: 0.8.1 Data|Database deployment on-premises | E32: 0.8.1.1 Database deploy on-premises, database schema changes, data migration and database optimization | G32: FIT | H32: 0.8.1.1 本地数据库部署、数据库架构变更、数据迁移和数据库优化 | T32: =$S32*DE_Cost!$B$1*8 -> 0 | U32: =$S32*DE_Cost!$B$1 -> 0 | X32: =IF(TRIM(P32)="", 0, LEN(P32) - LEN(SUBSTITUTE(P32, "&", "")) + 1) -> 0 | Y32: =S32 * X32 -> 0 | Z32: Y | AE32: =(Y32 / $AE$2) * $AC$2 -> 0
D33: 0.8.2 Data|Database deployment in cloud | E33: 0.8.2.1 Database deploy in cloud database schema changes, data migration and database optimization | G33: FIT | H33: 0.8.2.1 数据库部署在云数据库模式变更、数据迁移和数据库优化 | T33: =$S33*DE_Cost!$B$1*8 -> 0 | U33: =$S33*DE_Cost!$B$1 -> 0 | X33: =IF(TRIM(P33)="", 0, LEN(P33) - LEN(SUBSTITUTE(P33, "&", "")) + 1) -> 0 | Y33: =S33 * X33 -> 0 | Z33: Y | AE33: =(Y33 / $AE$2) * $AC$2 -> 0
D34: 0.8.3 Data|Data migration & synchronization | E34: 0.8.3.1 During the transition between the old POS and the new POS, the old POS data needs to be migrated to the New POS. Historical data from the past six months will be migrated in one batch. Incremental data will be synchronized in near real-time (within 15 minutes). Currently, there are three proposed solutions (choose one): Directly connect to the old POS database in the cloud or migrate the old POS sales data tables as-is into the New POS database, with the New POS handling the old tables’ data for interface display. Based on option 1, transform the data into the New POS format and write it into the New POS sales tables. Directly use Javis APIs to query old POS sales data to support order data inquiries, refunds, and exchange/return operations. 0.8.3.1 新老POS切换期间，需要将老POS数据迁移至New POS里，历史近半年数据一次性迁移，增量数据近实时同步（15分钟内）。目前有三种方案（选其一）： 1. 云上直连老POS数据库或将老POS的销售数据表原样迁移至New POS的库中，由New POS处理老表数据用于界面展示 2. 在1的基础上，将数据转换成New POS的数据，写入到New POS的销售表里 3. 直接使用Javis的接口查询老POS销售数据，完成订单数据查询、退款、退换货操作 | G34: Data & Jarvis | H34: 0.8.3.1 在旧 POS 系统和新 POS 系统过渡期间，旧 POS 数据需要迁移到新 POS 系统。 过去六个月的历史数据将一次性迁移。 增量数据将进行近实时同步（15 分钟内）。 目前，提出了三种解决方案（选择其一）： 直接连接到云端的旧 POS 数据库，或将旧 POS 销售数据表原样迁移到新 POS 数据库中，由新 POS 处理这些旧表的数据以进行界面显示。 根据选项 1，将数据转换为新的 POS 格式并写入新的 POS 销售表中。 直接使用 Javis API 查询旧的 POS 销售数据，以支持订单数据查询、退款以及换货/退货操作。 | K34: Jarvis | T34: =$S34*DE_Cost!$B$1*8 -> 0 | U34: =$S34*DE_Cost!$B$1 -> 0 | X34: =IF(TRIM(P34)="", 0, LEN(P34) - LEN(SUBSTITUTE(P34, "&", "")) + 1) -> 0 | Y34: =S34 * X34 -> 0 | Z34: Y | AE34: =(Y34 / $AE$2) * $AC$2 -> 0
A35: 1(Minimum scope) | B35: 2. Foundation operational functions 基础运营功能 | C35: 2.1 Merch & FnB product ordering 商品&餐饮点单 | D35: 2.1.1 [Merch] Add/delete product|Add product to shopping list 添加商品 | E35: 2.1.1.1 As Merch cashier, I need New POS will be able to add product to shopping list by barcode scanning or tap button, as to process shopping in store ordering. | F35: Items in one transaction may more than one thousand lines. | H35: 2.1.1.1 作为收银员，我需要新 POS 系统能够通过条形码扫描或点击按钮将商品添加到购物清单，以便处理店内购物订单。 | I35: 一个交易中的商品可能超过一千行。 | N35: 购物清单-添加+清单联动 | O35: 不包含优惠券等促销计算逻辑（需其他EPIC计算工时间） | P35: Android Developer & Front-end Developer & Product Designer & Quality Assurance & Product Manager & Delivery Manager | S35: 5 | T35: =$S35*DE_Cost!$B$1*8 -> 48 | U35: =$S35*DE_Cost!$B$1 -> 6 | V35: 0 | W35: 0 | X35: =IF(TRIM(P35)="", 0, LEN(P35) - LEN(SUBSTITUTE(P35, "&", "")) + 1) -> 6 | Y35: =S35 * X35 -> 30 | Z35: N | AA35: 建议5人天，估的工时过少可能，点击按钮添加购物清单如何实现，这里需要找到商品这一步 | AE35: =(Y35 / $AE$2) * $AC$2 -> 10968.133
A36: 1(Minimum scope) | B36: 2. Foundation operational functions 基础运营功能 | C36: 2.1 Merch & FnB product ordering 商品&餐饮点单 | D36: 2.1.1 [Merch] Add/delete product|Delete product in shopping list 删除商品 | E36: 2.1.1.2 As Merch cashier, I need New POS will be able to delete product in shopping list by slide w/ tap button, as to process shopping in store ordering. | H36: 2.1.1.2 作为收银员，我需要新 POS 系统能够通过滑动并点击按钮来删除购物清单中的商品，以便处理店内订单购物。 | N36: 购物清单-删除 | O36: (删除（0.5天） | P36: Android Developer & Front-end Developer & Product Designer & Quality Assurance & Product Manager & Delivery Manager | S36: 2 | T36: =$S36*DE_Cost!$B$1*8 -> 19.2 | U36: =$S36*DE_Cost!$B$1 -> 2.4 | V36: 0 | W36: 0 | X36: =IF(TRIM(P36)="", 0, LEN(P36) - LEN(SUBSTITUTE(P36, "&", "")) + 1) -> 6 | Y36: =S36 * X36 -> 12 | Z36: Y | AE36: =(Y36 / $AE$2) * $AC$2 -> 4387.2532
A37: 1(Minimum scope) | B37: 2. Foundation operational functions 基础运营功能 | C37: 2.1 Merch & FnB product ordering 商品&餐饮点单 | D37: 2.1.1 [Merch] Add/delete product|Modify product quantity/price in shopping list 修改商品数量或价格 | E37: 2.1.1.3 As Merch cashier, I need New POS will be able to modify product quantity/price in shopping list by tap button , as to process shopping in store ordering. | F37: 1. Press “+, -” or entering number to adjust item quantity 2. Repeated scanning same item or continuous scanning in X seconds will accumulate quantity(X is configurable) 3. Pricing change can only be process by GSM/Lead authorized, and not impact its price in foundation data. GSM/Lead authorized needed. | H37: 2.1.1.3 作为收银员，我需要新 POS 系统能够通过点击按钮修改购物清单中的产品数量/价格，以便处理店内订单购物。 | I37: 1. 按“+、-”或输入数字调整商品数量 2. 在X秒内重复扫描同一商品或连续扫描将累积数量（X可配置） 3. 价格更改只能由GSM/主管授权处理，且不影响基础数据中的价格。需要GSM/主管授权。 | N37: 购物清单-修改-产品数量/价格 | O37: 1.权限校验 2.修改发起授权（弹窗输入主管工号/密码？这个功能应该是有单独工时跟进） | P37: Android Developer & Front-end Developer & Product Designer & Back-end Developer & Quality Assurance & Product Manager & Delivery Manager | S37: 2 | T37: =$S37*DE_Cost!$B$1*8 -> 19.2 | U37: =$S37*DE_Cost!$B$1 -> 2.4 | V37: 0 | W37: 0 | X37: =IF(TRIM(P37)="", 0, LEN(P37) - LEN(SUBSTITUTE(P37, "&", "")) + 1) -> 7 | Y37: =S37 * X37 -> 14 | Z37: Y | AE37: =(Y37 / $AE$2) * $AC$2 -> 5118.462
A38: 1(Minimum scope) | B38: 2. Foundation operational functions 基础运营功能 | C38: 2.1 Merch & FnB product ordering 商品&餐饮点单 | D38: 2.1.1 [Merch] Add/delete product|Save/get product in shopping list 暂存与提取购物清单 | E38: 2.1.1.4 As Merch cashier, I need New POS will be able to save/get product list as draft when guest would like to order pending, as to process shopping in store ordering. | F38: 1. Modify draft shopping list: item/discount/coupon, and search 2. Delete shopping list | H38: 2.1.1.4 作为收银员，我需要新 POS 系统能够在客人想要暂存订单时保存/获取产品清单草稿，以便处理店内购物订单。 | I38: 1. 修改草稿购物车：商品/折扣/优惠券，以及搜索 2. 删除购物车 | N38: 购物清单-修改 | O38: 1.Android Developer本地修改 2.销售信息联动，存在系统对接。实时试算。主要耗时在联调上(2)。 | P38: Android Developer & Front-end Developer & Product Designer & Back-end Developer & Quality Assurance & Product Manager & Delivery Manager | S38: 5 | T38: =$S38*DE_Cost!$B$1*8 -> 48 | U38: =$S38*DE_Cost!$B$1 -> 6 | V38: 0 | W38: 0 | X38: =IF(TRIM(P38)="", 0, LEN(P38) - LEN(SUBSTITUTE(P38, "&", "")) + 1) -> 7 | Y38: =S38 * X38 -> 35 | Z38: Y | AE38: =(Y38 / $AE$2) * $AC$2 -> 12796.155
A39: 1(Minimum scope) | B39: 2. Foundation operational functions 基础运营功能 | C39: 2.1 Merch & FnB product ordering 商品&餐饮点单 | D39: 2.1.1 [Merch] Add/delete product|Check product saleable in shopping list 检查商品售卖状态 | E39: 2.1.1.5 As Merch cashier, I need New POS will be able to check product saleable when add into shopping list, display message when its unsaleable , as to make sure non-saleable product in shopping list. | F39: Finance | H39: 2.1.1.5 作为收银员，我需要新 POS 系统能够在商品添加到购物清单时检查其是否可销售，并在不可销售时显示提示信息，以确保购物清单中不会包含不可销售的商品。 | I39: 财务 | N39: 购物清单-添加时校验商品可用状态 | O39: 商品售卖状态在初始化时售卖状态应该拿到，直接校验（0.5） | P39: Android Developer & Front-end Developer & Product Designer & Quality Assurance & Product Manager & Delivery Manager | S39: 2 | T39: =$S39*DE_Cost!$B$1*8 -> 19.2 | U39: =$S39*DE_Cost!$B$1 -> 2.4 | V39: 0 | W39: 0 | X39: =IF(TRIM(P39)="", 0, LEN(P39) - LEN(SUBSTITUTE(P39, "&", "")) + 1) -> 6 | Y39: =S39 * X39 -> 12 | Z39: Y | AE39: =(Y39 / $AE$2) * $AC$2 -> 4387.2532
A40: 1(Minimum scope) | B40: 2. Foundation operational functions 基础运营功能 | C40: 2.1 Merch & FnB product ordering 商品&餐饮点单 | D40: 2.1.2 [FnB] QSR ordering|Ordering with add/delete meal on QSR 开单与添加删除商品 | E40: 2.1.2.1 As FnB cashier, I need New POS will be able to add/delete meal to shopping list by barcode scanning or tap button, as to process shopping in restaurant ordering. | F40: 1. Add single item/meal/service to list. 2. Delete product in shopping list. | H40: 2.1.2.1 作为餐饮收银员，我需要新 POS 系统能够通过条形码扫描或点击按钮来添加/删除购物清单中的餐品，以便处理餐厅订单。 | I40: 1. 将单个商品/餐点/服务添加到列表。 2. 删除购物车中的产品。 | N40: 购物清单-添加+清单联动 | O40: 扫码触发逻辑、增删查同步、本地缓存 不包含硬件集成 | P40: Android Developer & Front-end Developer & Product Designer & Quality Assurance & Product Manager & Delivery Manager | S40: 5 | T40: =$S40*DE_Cost!$B$1*8 -> 48 | U40: =$S40*DE_Cost!$B$1 -> 6 | V40: 0 | W40: 0 | X40: =IF(TRIM(P40)="", 0, LEN(P40) - LEN(SUBSTITUTE(P40, "&", "")) + 1) -> 6 | Y40: =S40 * X40 -> 30 | Z40: N | AA40: 推荐5人天, 见2.1.1.1 | AE40: =(Y40 / $AE$2) * $AC$2 -> 10968.133
A41: 1(Minimum scope) | B41: 2. Foundation operational functions 基础运营功能 | C41: 2.1 Merch & FnB product ordering 商品&餐饮点单 | D41: 2.1.2 [FnB] QSR ordering|Modify meal/set/Condiments configuration 调整单品、套餐与调料 | E41: 2.1.2.2 As FnB cashier, I need New POS will be able to modify meal/set/condiments configuration in shopping list, as to process shopping in restaurant ordering. | F41: Sync to kitchen printer for order detail. Condiments may deduct inventory or not deduct(depending on the case) | H41: 2.1.2.2 作为餐饮收银员，我需要新 POS 系统能够在购物清单中修改餐食/套餐/调味品配置，以便处理餐厅订单的购物流程。 | I41: 同步到厨房打印机以获取订单详情。 调味品可能会扣除库存，也可能不扣除（视情况而定） | N41: 购物清单-获取厨房订单信息 | O41: 配置的增删改查开发（2） 可视库存检查（1） 【无库存概念，部分餐饮有可售库存（不在这里估），打印同步不在这里估】 | P41: Android Developer & Front-end Developer & Product Designer & Back-end Developer & Quality Assurance & Product Manager & Delivery Manager | S41: 3 | T41: =$S41*DE_Cost!$B$1*8 -> 28.8 | U41: =$S41*DE_Cost!$B$1 -> 3.6 | V41: 0 | W41: 0 | X41: =IF(TRIM(P41)="", 0, LEN(P41) - LEN(SUBSTITUTE(P41, "&", "")) + 1) -> 7 | Y41: =S41 * X41 -> 21 | Z41: Y | AE41: =(Y41 / $AE$2) * $AC$2 -> 7677.693
A42: 1(Minimum scope) | B42: 2. Foundation operational functions 基础运营功能 | C42: 2.1 Merch & FnB product ordering 商品&餐饮点单 | D42: 2.1.2 [FnB] QSR ordering|Add remark for kitchen 增加厨房备注 | E42: 2.1.2.3 As FnB cashier, I need New POS will be able to add kitchen remark or special information on order/items level, as to process shopping in restaurant ordering. | F42: Sync to kitchen printer for order detail | H42: 2.1.2.3 作为餐饮收银员，我需要新 POS 系统能够在订单/项目级别添加厨房备注或特殊信息，以便处理餐厅购物订单。 | I42: 同步到厨房打印机以获取订单详情 | N42: 订单中菜品的备注信息 | O42: 厨房备注修改 | P42: Android Developer & Front-end Developer & Product Designer & Quality Assurance & Product Manager & Delivery Manager | S42: 2 | T42: =$S42*DE_Cost!$B$1*8 -> 19.2 | U42: =$S42*DE_Cost!$B$1 -> 2.4 | V42: 0 | W42: 0 | X42: =IF(TRIM(P42)="", 0, LEN(P42) - LEN(SUBSTITUTE(P42, "&", "")) + 1) -> 6 | Y42: =S42 * X42 -> 12 | Z42: Y | AE42: =(Y42 / $AE$2) * $AC$2 -> 4387.2532
A43: 1(Minimum scope) | B43: 2. Foundation operational functions 基础运营功能 | C43: 2.1 Merch & FnB product ordering 商品&餐饮点单 | D43: 2.1.2 [FnB] QSR ordering|Modify meal quantity/price in shopping list 调整数量与复制，修改价格 | E43: 2.1.2.4 As FnB cashier, I need New POS will be able to modify meal quantity or price in shopping list, as to process shopping in restaurant ordering. | F43: 1. Press “+, -” or entering number to adjust item qty 2. Able to duplicate added product 3. Pricing change can only be process by GSM/Lead authorized, and not impact its price in foundation data. GSM/Lead authorized needed. | H43: 2.1.2.4 作为餐饮收银员，我需要新 POS 系统能够修改购物清单中的餐品数量或价格，以便处理餐厅订单的购物流程。 | I43: 1. 按“+、-”或输入数字调整商品数量 2. 能够复制添加的产品 3. 价格更改只能由GSM/主管授权处理，且不影响基础数据中的价格。需要GSM/主管授权。 | N43: 购物清单-餐厅订单 | O43: 1.调整数量，2.复制商品（1） 3.权限校验（弹窗输入主管工号/密码？这个功能应该是有单独工时跟进）（1） | P43: Android Developer & Front-end Developer & Product Designer & Back-end Developer & Quality Assurance & Product Manager & Delivery Manager | S43: 2 | T43: =$S43*DE_Cost!$B$1*8 -> 19.2 | U43: =$S43*DE_Cost!$B$1 -> 2.4 | V43: 0 | W43: 0 | X43: =IF(TRIM(P43)="", 0, LEN(P43) - LEN(SUBSTITUTE(P43, "&", "")) + 1) -> 7 | Y43: =S43 * X43 -> 14 | Z43: Y | AE43: =(Y43 / $AE$2) * $AC$2 -> 5118.462
A44: 1(Minimum scope) | B44: 2. Foundation operational functions 基础运营功能 | C44: 2.1 Merch & FnB product ordering 商品&餐饮点单 | D44: 2.1.2 [FnB] QSR ordering|Display inventory and prompt sold out 显示库存并提示即将售罄 | E44: 2.1.2.5 As FnB cashier, I need New POS will be able to display inventory and prompt sell out when remaining qty is below a certain threshold by meal, as to prevent over sales in restaurant ordering. | F44: Inventory prompt threshold is configurable. | H44: 2.1.2.5 作为餐饮收银员，我需要新 POS 系统能够按餐次显示库存并在剩余数量低于特定阈值时提示售罄，以防止餐厅订单中的超量销售。 | I44: 库存提示阈值可配置。 | N44: 购物清单-库存 | O44: 1.Android Developer购物清单需要校验提示售罄 2.服务端取库存信息，正常来说是个查询 | P44: Android Developer & Front-end Developer & Product Designer & Back-end Developer & Quality Assurance & Product Manager & Delivery Manager | S44: 2 | T44: =$S44*DE_Cost!$B$1*8 -> 19.2 | U44: =$S44*DE_Cost!$B$1 -> 2.4 | V44: 0 | W44: 0 | X44: =IF(TRIM(P44)="", 0, LEN(P44) - LEN(SUBSTITUTE(P44, "&", "")) + 1) -> 7 | Y44: =S44 * X44 -> 14 | Z44: Y | AE44: =(Y44 / $AE$2) * $AC$2 -> 5118.462
A45: 1(Minimum scope) | B45: 2. Foundation operational functions 基础运营功能 | C45: 2.1 Merch & FnB product ordering 商品&餐饮点单 | D45: 2.1.3 [FnB] TSR ordering|Add/delete meal to table order w/service fee on TSR TSR桌台点单（部分点位含服务费） | E45: 2.1.3.1 As FnB cashier, I need New POS will be able to add/delete meal/set/service (w/ service fee) to order after open table, as to process shopping in dinning . | F45: 1. Input number of guests to open table, and guest type is optional(walk-in/hotel/reserved) 2. Enable to add/delete meal, seat, change quantity/service fee, change table, merge tables, pending to draft/get from draft, re-purchase 3.Condiments may deduct inventory or not deduct(depending on the case) 4. Customize product and kitchen remark to item/order level 5. Inventory deduction or not when editing saved check | H45: 2.1.3.1 作为餐饮收银员，我需要新 POS 系统能够在开台后向订单中添加/删除餐品/套餐/服务（含服务费），以便处理餐饮消费。 | I45: 1. 输入客人人数以打开餐桌，客人类型可选（散客/酒店/预订） 2. 能够添加/删除餐点、座位，更改数量/服务费，更改餐桌，合并餐桌，挂起到草稿/从草稿中获取，重新购买 3. 调味品可能会扣除库存，也可能不扣除（视情况而定） 4. 自定义产品和厨房备注到商品/订单级别 5. 编辑已保存的账单时是否扣除库存 | N45: 开台-订单 | O45: TSR业务 1.客数修改，类型调整（1） 2.（3） 3.（1） 4.（1） 5.（1） | P45: Android Developer & Front-end Developer & Product Designer & Back-end Developer & Quality Assurance & Product Manager & Delivery Manager | Q45: 按商品属性去控制是否扣库存 有库存管理的就扣 | S45: 15 | T45: =$S45*DE_Cost!$B$1*8 -> 144 | U45: =$S45*DE_Cost!$B$1 -> 18 | V45: 0 | W45: 0 | X45: =IF(TRIM(P45)="", 0, LEN(P45) - LEN(SUBSTITUTE(P45, "&", "")) + 1) -> 7 | Y45: =S45 * X45 -> 105 | Z45: Y | AE45: =(Y45 / $AE$2) * $AC$2 -> 38388.465
A46: 1(Minimum scope) | B46: 2. Foundation operational functions 基础运营功能 | C46: 2.1 Merch & FnB product ordering 商品&餐饮点单 | D46: 2.1.3 [FnB] TSR ordering|Buffet order(Cast-serve and guest-self service) 自助餐点单(CM上菜/客人自助) | E46: 2.1.3.2 As FnB cashier, I need New POS will be able to add/delete buffet order after open table by cast, as to process shopping in dinning. | F46: 1. Enable to order buffet products and items 2. Enable to order a-la-carte item | H46: 2.1.3.2 作为餐饮收银员，我需要新 POS 系统能够按班次在开台后添加/删除自助餐订单，以便处理餐饮消费。 | I46: 1. 能够订购自助餐产品和商品 2. 能够点菜 | N46: 开台-订单-添加商品 | O46: TSR业务 继续增加在原有订单上（2） | P46: Android Developer & Front-end Developer & Product Designer & Back-end Developer & Quality Assurance & Product Manager & Delivery Manager | S46: 3 | T46: =$S46*DE_Cost!$B$1*8 -> 28.8 | U46: =$S46*DE_Cost!$B$1 -> 3.6 | V46: 0 | W46: 0 | X46: =IF(TRIM(P46)="", 0, LEN(P46) - LEN(SUBSTITUTE(P46, "&", "")) + 1) -> 7 | Y46: =S46 * X46 -> 21 | Z46: Y | AE46: =(Y46 / $AE$2) * $AC$2 -> 7677.693
A47: 1(Minimum scope) | B47: 2. Foundation operational functions 基础运营功能 | C47: 2.1 Merch & FnB product ordering 商品&餐饮点单 | D47: 2.1.3 [FnB] TSR ordering|Banquet order 宴会点单 | E47: 2.1.3.4 As FnB cashier, I need New POS will be able to add/delete banquet order to after open tables, as to process shopping in dinning. | F47: 1. Input number of tables, guest count, order comments to open tables 2. Enable to add sales package/F&B/Misc/Merc/Ticketing /Rental to order | H47: 2.1.3.4 作为餐饮收银员，我需要新 POS 系统能够在开台后添加/删除宴会订单，以便处理餐饮消费。 | I47: 1. 输入餐桌数量、客人人数、订单备注以打开餐桌 2. 能够将销售套餐/餐饮/杂项/商品/票务/租赁添加到订单 | N47: 开台-订单-宴会订单 | O47: 宴会订单 1.（1） 2.将各类信息添加到订单中（2）（这些信息来源需要工时单独计算） | P47: Android Developer & Front-end Developer & Product Designer & Back-end Developer & Quality Assurance & Product Manager & Delivery Manager | S47: 3 | T47: =$S47*DE_Cost!$B$1*8 -> 28.8 | U47: =$S47*DE_Cost!$B$1 -> 3.6 | V47: 0 | W47: 0 | X47: =IF(TRIM(P47)="", 0, LEN(P47) - LEN(SUBSTITUTE(P47, "&", "")) + 1) -> 7 | Y47: =S47 * X47 -> 21 | Z47: Y | AE47: =(Y47 / $AE$2) * $AC$2 -> 7677.693
A48: 1(Minimum scope) | B48: 2. Foundation operational functions 基础运营功能 | C48: 2.1 Merch & FnB product ordering 商品&餐饮点单 | D48: 2.1.3 [FnB] TSR ordering|Hotel room order(charge to room) 酒店客房点餐(挂房账) | E48: 2.1.3.5 As FnB cashier, I need New POS will be able to add/delete hotel order to room service, as to process shopping in hotel room dinning. | F48: [Similar as TSR ordering] 1. Number of guests needed to open table 2. Enable to add/delete meal, change quantity/service fee, pending to draft/get from draft, re-purchase 3. Customize product and kitchen remark to item/order level 4. Display the room charges status if refunded or not | G48: PMS-Opera | H48: 2.1.3.5 作为餐饮收银员，我需要新 POS 系统能够添加/删除酒店订单到客房服务，以便处理酒店客房内的餐饮消费。 | I48: 【类似于TSR订购】 1. 打开餐桌所需的客人人数 2. 能够添加/删除餐点，更改数量/服务费，挂起到草稿/从草稿中获取，重新购买 3. 自定义产品和厨房备注到商品/订单级别 4. 如果已退款，则显示房间费用状态 | N48: 酒店订单到客房服务 | O48: 1.落座人数update（0.5） 2.（1） 3.（1） 4.（0.5） | P48: Android Developer & Front-end Developer & Product Designer & Back-end Developer & Quality Assurance & Product Manager & Delivery Manager | S48: 3 | T48: =$S48*DE_Cost!$B$1*8 -> 28.8 | U48: =$S48*DE_Cost!$B$1 -> 3.6 | V48: 0 | W48: 0 | X48: =IF(TRIM(P48)="", 0, LEN(P48) - LEN(SUBSTITUTE(P48, "&", "")) + 1) -> 7 | Y48: =S48 * X48 -> 21 | Z48: Y | AE48: =(Y48 / $AE$2) * $AC$2 -> 7677.693
A49: 1(Minimum scope) | B49: 2. Foundation operational functions 基础运营功能 | C49: 2.1 Merch & FnB product ordering 商品&餐饮点单 | D49: 2.1.3 [FnB] TSR ordering|Change/cancel table order on TSR 合并桌台/变更桌台/取消桌台 | E49: 2.1.3.6 As FnB cashier, I need New POS will be able to change table or cancel meal/set/service to order after open table, as to fulfill guest request in dinning. | H49: 2.1.3.6 作为餐饮收银员，我需要新 POS 系统能够在开台后更改餐桌或取消餐点/套餐/服务，以满足客人在用餐过程中的需求。 | N49: TSR 合并桌台/变更桌台/取消桌台 | O49: 餐桌状态流转，伴随着订单状态流转 | P49: Android Developer & Front-end Developer & Product Designer & Back-end Developer & Quality Assurance & Product Manager & Delivery Manager | S49: 4 | T49: =$S49*DE_Cost!$B$1*8 -> 38.4 | U49: =$S49*DE_Cost!$B$1 -> 4.8 | V49: 0 | W49: 0 | X49: =IF(TRIM(P49)="", 0, LEN(P49) - LEN(SUBSTITUTE(P49, "&", "")) + 1) -> 7 | Y49: =S49 * X49 -> 28 | Z49: Y | AE49: =(Y49 / $AE$2) * $AC$2 -> 10236.924
A50: 1(Minimum scope) | B50: 2. Foundation operational functions 基础运营功能 | C50: 2.10 Operational reports 运营报表 | D50: 2.10.1 Sales report|Location sales report 门店销售报表 | E50: 2.10.1.1 As Ops admin & cashier, I need New POS will be able to customized reports output format and result fields, as to fulfill operations reporting requirements. | F50: Including custom report formats, custom data sources and fields, binding fields to the compound, designing report styles, adding custom events and publishing reports. | G50: report | H50: 2.10.1.1 作为运营管理员和收银员，我需要新 POS 系统能够自定义报表输出格式和结果字段，以满足运营报告需求。 | I50: 包括自定义报表格式、自定义数据源和字段、将字段绑定到复合项、设计报表样式、添加自定义事件和发布报表。 | N50: 在POS后台展示报表需求 | O50: 报表筛选，数据准确性 | P50: Front-end Developer & Product Designer & Back-end Developer & Quality Assurance & Product Manager & Delivery Manager | R50: 待确定 | S50: 10 | T50: =$S50*DE_Cost!$B$1*8 -> 96 | U50: =$S50*DE_Cost!$B$1 -> 12 | X50: =IF(TRIM(P50)="", 0, LEN(P50) - LEN(SUBSTITUTE(P50, "&", "")) + 1) -> 6 | Y50: =S50 * X50 -> 60 | Z50: N | AA50: PM: 涉及系统端有争议，报表理论无收银员无关 | AE50: =(Y50 / $AE$2) * $AC$2 -> 21936.266
A51: 1(Minimum scope) | B51: 2. Foundation operational functions 基础运营功能 | C51: 2.10 Operational reports 运营报表 | D51: 2.10.1 Sales report|Merch sales/management reports 商品销售报表 | E51: 2.10.1.2 As Merch admin & cashier, I need New POS will be able to summary sales record as Merch current operations report with 9 categories (40 reports), as to fulfill operations reporting requirements. | F51: 包含9类共40张报表 1. Account info include: PERNER, name, phone, email, store, business type, joining time, title, button group, is ND. 2. Each account has a identifier field(e.g. PERNER/Email address) for identity. 3. Account creation require corresponding Line Manager approval. GSM/Lead/Administrator authorized needed | G51: report | H51: 2.10.1.2 作为商户管理员和收银员，我需要新 POS 系统能够将销售记录汇总为商户当前运营报告，包含 9 个类别（40 份报告），以满足运营报告需求。 | I51: 包含9类共40张报表 1. 帐户信息包括：PERNER、姓名、电话、电子邮件、商店、业务类型、加入时间、职称、按钮组、是否为ND。 2. 每个帐户都有一个标识符字段（例如PERNER/电子邮件地址）用于身份验证。 3. 帐户创建需要相应的直线经理批准。需要GSM/主管/管理员授权 | N51: 按照不同类型划分过滤出不同的结果集合，才生40份reports | O51: 1. UI（1） + 数据组合（1） 3.授权（1） | P51: Front-end Developer & Product Designer & Back-end Developer & Quality Assurance & Product Manager & Delivery Manager | R51: 待确定 | S51: 100 | T51: =$S51*DE_Cost!$B$1*8 -> 960 | U51: =$S51*DE_Cost!$B$1 -> 120 | X51: =IF(TRIM(P51)="", 0, LEN(P51) - LEN(SUBSTITUTE(P51, "&", "")) + 1) -> 6 | Y51: =S51 * X51 -> 600 | Z51: N | AA51: PM: 涉及系统端有争议，报表理论无收银员无关 | AE51: =(Y51 / $AE$2) * $AC$2 -> 219362.66
A52: 1(Minimum scope) | B52: 2. Foundation operational functions 基础运营功能 | C52: 2.10 Operational reports 运营报表 | D52: 2.10.1 Sales report|FnB location sales report 餐饮销售报表 | E52: 2.10.1.3 As FnB admin & cashier, I need New POS will be able to summary sales record as FnB current operations report for location closed, as to fulfill operations reporting requirements. | F52: 1. Field including: sales report/transaction report(by payment method)/cash drawer report/coupon and discount report, and actual receipt statements for payment methods, and the accounts receivable statements for sales categories. 2. Display daily report, but POS frontend stores 3 days of report data) | G52: report | H52: 2.10.1.3 作为餐饮部管理员和收银员，我需要新 POS 系统能够为已关闭的门店汇总销售记录作为餐饮部当前运营报告，以满足运营报告要求。 | I52: 1. 字段包括：销售报告/交易报告（按支付方式）/收银机报告/优惠券和折扣报告，以及支付方式的实际收据报表，以及销售类别的应收账款报表。 2. 显示每日报告，但POS前端存储3天的报告数据） | N52: 基础报表+POS端报告数据 | O52: 1.基础报表 2.Android Developer本地缓存数据 | P52: Android Developer & Front-end Developer & Back-end Developer & Quality Assurance & Product Manager & Delivery Manager | S52: 15 | T52: =$S52*DE_Cost!$B$1*8 -> 144 | U52: =$S52*DE_Cost!$B$1 -> 18 | X52: =IF(TRIM(P52)="", 0, LEN(P52) - LEN(SUBSTITUTE(P52, "&", "")) + 1) -> 6 | Y52: =S52 * X52 -> 90 | Z52: N | AA52: PM: 这报表也涉及收银端么？ | AE52: =(Y52 / $AE$2) * $AC$2 -> 32904.399
A53: 1(Minimum scope) | B53: 2. Foundation operational functions 基础运营功能 | C53: 2.11 Finance Processing and Configuration 财务处理和配置 | D53: 2.11.1 Refund Finance Processing| Auto refund of single payment 由退货触发自动退款（单一支付方式） | E53: 2.11.1.1 As Finance admin, I want to accept auto refund of products paid through single payment method so that I can refund through original payment method. | F53: 1. Preconditions as Merch/FnB operations requirements, need to input return reason 2. If auto refund fails, should pop up system message to prompt manual refund, 3. Refund transaction should link back to original transaction. 4. Backend scenarios include: 1) Same store refund, 2) Different store same company refund (store ID should be captured), 3) Different store different company refund (store ID should be captured) | G53: Finance | H53: 2.11.1.1 作为财务管理员，我希望接受通过单一支付方式支付的产品自动退款，以便能够通过原始支付方式进行退款。 | I53: 1. 作为Merch/FnB运营要求的前提条件，需要输入退货原因 2. 如果自动退款失败，应弹出系统消息提示手动退款， 3. 退款交易应链接回原始交易。 4. 后端场景包括：1) 同店退款，2) 不同店同公司退款（应捕获商店ID），3) 不同店不同公司退款（应捕获商店ID） | J53: 同上 | K53: Lucky & Vetas | N53: 退款操作-单一支付方式 | O53: 1.输入退款原因（1） 2.自动退款调用+手动退款调用（2） 3.关联交易（1） 4.不同场景（1） 退款链路完善，只是对接情况（5） | P53: Front-end Developer & Product Designer & Back-end Developer & Quality Assurance & Product Manager & Delivery Manager | S53: 15 | T53: =$S53*DE_Cost!$B$1*8 -> 144 | U53: =$S53*DE_Cost!$B$1 -> 18 | X53: =IF(TRIM(P53)="", 0, LEN(P53) - LEN(SUBSTITUTE(P53, "&", "")) + 1) -> 6 | Y53: =S53 * X53 -> 90 | Z53: Y | AE53: =(Y53 / $AE$2) * $AC$2 -> 32904.399
A54: 1(Minimum scope) | B54: 2. Foundation operational functions 基础运营功能 | C54: 2.11 Finance Processing and Configuration 财务处理和配置 | D54: 2.11.1 Refund Finance Processing| Auto refund of combined payment 由退货触发自动退款（混合支付方式） | E54: 2.11.1.2 As Finance admin, I want to accept auto refund of products paid through combined payment so that I can select refund method to guest. | F54: 1. Preconditions as Merch/FnB operations requirements, need to input return reason 2. Cashier can select the refund payment from original combined payment methods. 3. If auto refund fails, should pop up system message to prompt manual refund. 4. Refund transaction should link back to original transaction. 5. Backend scenarios: 1) Same store refund, 2) Different store same company refund (store ID should be captured), 3) Different store different company refund (store ID should be captured) | G54: Finance | H54: 2.11.1.2 作为财务管理员，我希望接受通过组合支付方式购买的产品自动退款，以便我可以选择退款方式给客人。 | I54: 1. 作为Merch/FnB运营要求的前提条件，需要输入退货原因 2. 收银员可以从原始组合支付方式中选择退款支付。 3. 如果自动退款失败，应弹出系统消息提示手动退款。 4. 退款交易应链接回原始交易。 5. 后端场景：1) 同店退款，2) 不同店同公司退款（应捕获商店ID），3) 不同店不同公司退款（应捕获商店ID） | J54: POS发起自动退款，调Payment Service退款 Payment Service需要提供自动退款接口 | K54: Lucky & Vetas | N54: 退款操作-组合支付方式 | O54: 1.输入退款原因（1） 2.原始支付方式退款（2） 3.自动退款调用+手动退款调用（2+1） 4.链接回原始交易（1） 5.不同场景（1） 退款链路完善，仅对接情况（5） | P54: Front-end Developer & Product Designer & Back-end Developer & Quality Assurance & Product Manager & Delivery Manager | S54: 15 | T54: =$S54*DE_Cost!$B$1*8 -> 144 | U54: =$S54*DE_Cost!$B$1 -> 18 | X54: =IF(TRIM(P54)="", 0, LEN(P54) - LEN(SUBSTITUTE(P54, "&", "")) + 1) -> 6 | Y54: =S54 * X54 -> 90 | Z54: Y | AE54: =(Y54 / $AE$2) * $AC$2 -> 32904.399
A55: 1(Minimum scope) | B55: 2. Foundation operational functions 基础运营功能 | C55: 2.11 Finance Processing and Configuration 财务处理和配置 | D55: 2.11.1 Refund Finance Processing| Manual refund after auto refund failure 自动触发退款失败后手工发起退款 | E55: 2.11.1.3 As Finance admin, I want New POS to prompt alert with popup when payment refund is unsuccessful and provide selection of NonCash Code for manual refund methods, so that I can process guest refund accordingly. | G55: Finance | H55: 2.11.1.3 作为财务管理员，我希望新 POS 在支付退款失败时弹出提示警报，并提供非现金代码选项用于手动退款方法，以便我能够相应地为客人处理退款。 | J55: 同上 | K55: Lucky & Vetas | N55: 退款操作-失败报警-手动退款 | O55: 对接退款 （2） 手动退款方式（1） 退款链路完善，仅对接情况（5） | P55: Android Developer & Front-end Developer & Product Designer & Back-end Developer & Quality Assurance & Product Manager & Delivery Manager | S55: 10 | T55: =$S55*DE_Cost!$B$1*8 -> 96 | U55: =$S55*DE_Cost!$B$1 -> 12 | X55: =IF(TRIM(P55)="", 0, LEN(P55) - LEN(SUBSTITUTE(P55, "&", "")) + 1) -> 7 | Y55: =S55 * X55 -> 70 | Z55: Y | AE55: =(Y55 / $AE$2) * $AC$2 -> 25592.31
A56: 1(Minimum scope) | B56: 2. Foundation operational functions 基础运营功能 | C56: 2.11 Finance Processing and Configuration 财务处理和配置 | D56: 2.11.1 Refund Finance Processing| Manual refund 手工执行退款 | E56: 2.11.1.4 As Finance admin, I want to conduct manual refund for products so that I can successfully refund payment to guest. | F56: 1. Preconditions as Merch/FnB operations requirements. 2. Select refund method from available configured buttons. 3. Backend scenarios: 1) Same store refund, 2) Different store same company refund, 3) Different store different company refund | G56: Finance | H56: 2.11.1.4 作为财务管理员，我希望能够手动为产品退款，以便成功向客人退还付款。 | I56: 1. 作为Merch/FnB运营要求的前提条件。 2. 从可用的已配置按钮中选择退款方式。 3. 后端场景：1) 同店退款，2) 不同店同公司退款，3) 不同店不同公司退款 | J56: 同上 | K56: Lucky & Vetas | N56: 退款操作-手动退款 | O56: 从后台触发退款操作（5） 退款链路完善，仅对接情况（5） | P56: Front-end Developer & Product Designer & Back-end Developer & Quality Assurance & Product Manager & Delivery Manager | S56: 10 | T56: =$S56*DE_Cost!$B$1*8 -> 96 | U56: =$S56*DE_Cost!$B$1 -> 12 | X56: =IF(TRIM(P56)="", 0, LEN(P56) - LEN(SUBSTITUTE(P56, "&", "")) + 1) -> 6 | Y56: =S56 * X56 -> 60 | Z56: Y | AE56: =(Y56 / $AE$2) * $AC$2 -> 21936.266
A57: 1(Minimum scope) | B57: 2. Foundation operational functions 基础运营功能 | C57: 2.11 Finance Processing and Configuration 财务处理和配置 | D57: 2.11.1 Refund Finance Processing| NonCashCode manual refund 手工执行Noncash Code退款 | E57: 2.11.1.5 As Finance admin, I want to select NonCashCode as a refund method, so that I can refund order or products that were paid through NonCashCodes. | G57: Finance | H57: 2.11.1.5 作为财务管理员，我希望选择 NonCashCode 作为退款方式，以便能够退还通过 NonCashCode 支付的订单或产品。 | J57: 同上 | K57: Lucky & Vetas | N57: 退款操作-NonCashCode | O57: NonCashCode 方式退款（2） 退款链路完善，仅对接情况（5） | P57: Front-end Developer & Product Designer & Back-end Developer & Quality Assurance & Product Manager & Delivery Manager | R57: 待确定 | S57: 10 | T57: =$S57*DE_Cost!$B$1*8 -> 96 | U57: =$S57*DE_Cost!$B$1 -> 12 | X57: =IF(TRIM(P57)="", 0, LEN(P57) - LEN(SUBSTITUTE(P57, "&", "")) + 1) -> 6 | Y57: =S57 * X57 -> 60 | Z57: Y | AE57: =(Y57 / $AE$2) * $AC$2 -> 21936.266
A58: 1(Minimum scope) | B58: 2. Foundation operational functions 基础运营功能 | C58: 2.11 Finance Processing and Configuration 财务处理和配置 | D58: 2.11.2 Payment Finance Configuration| Enable rounding off/up 配置金额舍入规则 | E58: 2.11.2.1 As Finance admin, I need New POS will be able to configure rounding for each payment item by store and payment method | F58: 1) Rounding in cash as: Decimal places, Round up, Round down, Round off, Round before/after calculation. 2) Round by priority, and apply to check amount, refund amount, payment/refund method, discount/coupon/other benefit, services fee, item amount. | G58: Finance | H58: 2.11.2.1 作为财务管理员，我需要新 POS 能够按商店和支付方式为每个payment 项 配置舍入规则 | I58: 1) 现金舍入方式：小数位数、向上舍入、向下舍入、四舍五入、计算前/后舍入。 2) 按优先级舍入，并应用于检查金额、退款金额、支付/退款方式、折扣/优惠券/其他优惠、服务费、项目金额。 | J58: PIP上也需要配置，金额不一致？ | K58: Lucky | N58: 配置-payment item-配置舍入规则 | O58: admin配置规则，计算金额的舍入规则配置（2） 按照优先级舍入（1） 带上具体执行逻辑（7） | P58: Android Developer & Front-end Developer & Back-end Developer & Quality Assurance & Product Manager & Delivery Manager | S58: 10 | T58: =$S58*DE_Cost!$B$1*8 -> 96 | U58: =$S58*DE_Cost!$B$1 -> 12 | X58: =IF(TRIM(P58)="", 0, LEN(P58) - LEN(SUBSTITUTE(P58, "&", "")) + 1) -> 6 | Y58: =S58 * X58 -> 60 | Z58: Y | AE58: =(Y58 / $AE$2) * $AC$2 -> 21936.266
A59: 1(Minimum scope) | B59: 2. Foundation operational functions 基础运营功能 | C59: 2.11 Finance Processing and Configuration 财务处理和配置 | D59: 2.11.2 Payment Finance Configuration| Configuration of NonCash Codes 配置NonCash Code | E59: 2.11.2.2 As Finance admin, I want to configure NonCash Code payment methods from NewPOS backend, so that Ops Cashier can select appropriate NonCash Code payment method to process guest payment. | G59: Finance | H59: 2.11.2.2 作为财务管理员，我希望从 NewPOS 后端配置非现金代码支付方式，以便运营收银员能够选择合适的非现金代码支付方式来处理客人付款。 | J59: POS配置code，调Payment Service拿到支付方式配置的Mapping关系 | K59: Lucky & Vetas | N59: 配置-NonCashCode-付款 | O59: admin配置规则（1） 规则生效至PIS（1） | P59: Front-end Developer & Product Designer & Back-end Developer & Quality Assurance & Product Manager & Delivery Manager | S59: 4 | T59: =$S59*DE_Cost!$B$1*8 -> 38.4 | U59: =$S59*DE_Cost!$B$1 -> 4.8 | X59: =IF(TRIM(P59)="", 0, LEN(P59) - LEN(SUBSTITUTE(P59, "&", "")) + 1) -> 6 | Y59: =S59 * X59 -> 24 | Z59: Y | AE59: =(Y59 / $AE$2) * $AC$2 -> 8774.5063
A60: 1(Minimum scope) | B60: 2. Foundation operational functions 基础运营功能 | C60: 2.11 Finance Processing and Configuration 财务处理和配置 | D60: 2.11.2 Payment Finance Configuration| NonCash Code payment 配置NonCash Code支付 | E60: 2.11.2.3 As Ops Cashier, I want New POS to support manual selection of Non CashCode as a payment method, so that I can complete payment process for guest | G60: Finance | H60: 2.11.2.3 作为收银员，我希望新 POS 系统能支持手动选择 Non CashCode 作为支付方式，以便我能为客人完成支付流程 | J60: 同上 | K60: Lucky & Vetas | N60: 配置-NonCashCode-付款 | O60: admin生效配置，（1） Android Developer端去支持NonCashCode-付款（1） PIS调试（2） | P60: Android Developer & Front-end Developer & Back-end Developer & Quality Assurance & Product Manager & Delivery Manager | S60: 4 | T60: =$S60*DE_Cost!$B$1*8 -> 38.4 | U60: =$S60*DE_Cost!$B$1 -> 4.8 | X60: =IF(TRIM(P60)="", 0, LEN(P60) - LEN(SUBSTITUTE(P60, "&", "")) + 1) -> 6 | Y60: =S60 * X60 -> 24 | Z60: Y | AE60: =(Y60 / $AE$2) * $AC$2 -> 8774.5063
A61: 1(Minimum scope) | B61: 2. Foundation operational functions 基础运营功能 | C61: 2.11 Finance Processing and Configuration 财务处理和配置 | D61: 2.11.2 Payment Finance Configuration| Enable promotion in payment method 支付渠道促销 | E61: 2.11.2.4 As Finance admin, I need New POS will be able to configure payment promotions as SHDR self-operated activities, 3rd payment codes and specific channel promotions | F61: Transactions revenue on payment promotions should have a spitted amount for Financial accounting. By order by using specific payment method or by products by using specific payment method. | G61: Finance | H61: 2.11.2.4 作为财务管理员，我需要新 POS 能够将支付促销配置为 SHDR 自营活动、第三方支付代码和特定渠道促销 | I61: 支付促销的交易收入应为财务会计分配金额。 通过使用特定支付方式的订单或通过使用特定支付方式的产品。 | J61: 这个配置应该在对应支付渠道里配置 | K61: Lucky & Vetas | N61: 配置-支付促销-配置特定支付方式或产品 | O61: admin配置工作（2） Android Developer端 集成并生效（3） PIS对接（5） | P61: Android Developer & Front-end Developer & Back-end Developer & Quality Assurance & Product Manager & Delivery Manager | S61: 10 | T61: =$S61*DE_Cost!$B$1*8 -> 96 | U61: =$S61*DE_Cost!$B$1 -> 12 | X61: =IF(TRIM(P61)="", 0, LEN(P61) - LEN(SUBSTITUTE(P61, "&", "")) + 1) -> 6 | Y61: =S61 * X61 -> 60 | Z61: Y | AE61: =(Y61 / $AE$2) * $AC$2 -> 21936.266
A62: 1(Minimum scope) | B62: 2. Foundation operational functions 基础运营功能 | C62: 2.11 Finance Processing and Configuration 财务处理和配置 | D62: 2.11.3 Finance Posting| Financial Master Data configuration 配置财务主数据 | E62: 2.11.3.1 As Finance operator, I want to configure financial master data(e.g company code, GL account, CC, PC.ect) corresponding to Merch/FnB products, transactions, location/terminal, revenue type etc. by single-item or batch upload, so that NewPOS sale & payment data can be correctly posted to SAP. | F62: FS-4 产品、产品分类、支付方式、渠道、门店、收银终端、订单、促销活动等相关功能下可以灵活的配置一些财务需要的相关数据属性，比如公司代码、财务科目、利润中心、收入类型、税率、财务物料号码、财务支付方式、零售客户代码、零售业务模式、财务接口标识、Bank out标识等等 | G62: Finance | H62: 2.11.3.1 作为财务操作员，我希望通过单项或批量上传配置与商户/餐饮产品、交易、地点/终端、收入类型等对应的财务主数据（如公司代码、总账科目、成本中心、利润中心等），以便 NewPOS 销售和支付数据能够正确过账到 SAP。 | I62: FS-4 产品、产品分类、支付方式、渠道、门店、收银终端、订单、促销活动等相关功能下可以灵活的配置一些财务需要的相关数据属性，比如公司代码、财务科目、利润中心、收入类型、税率、财务物料号码、财务支付方式、零售客户代码、零售业务模式、财务接口标识、Bank out标识等等 | K62: Vetas | N62: 配置-灵活配置属性 | O62: admin相关功能下配置字段（5） | X62: =IF(TRIM(P62)="", 0, LEN(P62) - LEN(SUBSTITUTE(P62, "&", "")) + 1) -> 0 | Y62: =S62 * X62 -> 0 | Z62: Y | AE62: =(Y62 / $AE$2) * $AC$2 -> 0
A63: 1(Minimum scope) | B63: 2. Foundation operational functions 基础运营功能 | C63: 2.11 Finance Processing and Configuration 财务处理和配置 | D63: 2.11.3 Finance Posting| Financial Master Data attributes configuration 配置财务附加主数据 | E63: 2.11.3.2 As Finance Operator, I want to add, edit, or delete additional financial attributes to Merch and FnB product master data so that I can conduct Financial analysis and not affect operational processes. | F63: FS-4 TBC - 配置权限 | G63: Finance | H63: 2.11.3.2 作为财务操作员，我想添加、编辑或删除 Merch 和 FnB 产品主数据的额外财务属性，以便我可以进行财务分析，同时不影响运营流程。 | I63: FS-4 TBC - 配置权限 | J63: 财务主数据需要带到FMP | K63: Lucky & Vetas | N63: 配置- Merch 和 FnB 产品主数据的额外财务属性 | O63: admin配置工作 | P63: Front-end Developer & Product Designer & Back-end Developer & Quality Assurance & Product Manager & Delivery Manager | S63: 5 | T63: =$S63*DE_Cost!$B$1*8 -> 48 | U63: =$S63*DE_Cost!$B$1 -> 6 | X63: =IF(TRIM(P63)="", 0, LEN(P63) - LEN(SUBSTITUTE(P63, "&", "")) + 1) -> 6 | Y63: =S63 * X63 -> 30 | Z63: Y | AE63: =(Y63 / $AE$2) * $AC$2 -> 10968.133
A64: 1(Minimum scope) | B64: 2. Foundation operational functions 基础运营功能 | C64: 2.11 Finance Processing and Configuration 财务处理和配置 | D64: 2.11.4 Finance Reports and Logs| Search, View, and Download Financial Reports and logs 查询，查看和下载财务报表和日志 | E64: 2.11.4.1 As a Finance admin, I want to search, and filter Financial Reports and Logs via different criteria, and view and download these Reports and Logs from New POS, so that I can conduct Financial Reconciliation and Finance Posting | F64: FS-8 Search Criteria: Order info, Payment info, Location info, Transaction date, Coupon redemption, Payment Promotions, Inventory deduction, Payment methods, Product Type, etc Eg of Financial Reports: Payments reports, Sales reports, Store Open / Close reports PCM-6 SA-5 | G64: Finance & Report | H64: 2.11.4.1 作为财务管理员，我希望能够通过不同条件搜索和筛选财务报表与日志，并在新 POS 系统中查看和下载这些报表与日志，以便进行财务对账和财务过账。 | I64: FS-8 搜索条件：订单信息、支付信息、位置信息、交易日期、优惠券兑换、支付促销、库存扣除、支付方式、产品类型等 财务报告示例：支付报告、销售报告、商店开/关报告 PCM-6 SA-5 | J64: 需要大概多少张表？大概表的内容 | K64: Lucky | L64: 10/24 18:00之前可以确认 本周五再拉会过需求 | N64: 报表与日志 | O64: 搜索筛选，下载 | P64: Front-end Developer & Product Designer & Back-end Developer & Quality Assurance & Product Manager & Delivery Manager | R64: 待确定 | S64: 10 | T64: =$S64*DE_Cost!$B$1*8 -> 96 | U64: =$S64*DE_Cost!$B$1 -> 12 | X64: =IF(TRIM(P64)="", 0, LEN(P64) - LEN(SUBSTITUTE(P64, "&", "")) + 1) -> 6 | Y64: =S64 * X64 -> 60 | Z64: Y | AE64: =(Y64 / $AE$2) * $AC$2 -> 21936.266
A65: 1(Minimum scope) | B65: 2. Foundation operational functions 基础运营功能 | C65: 2.11 Finance Processing and Configuration 财务处理和配置 | D65: 2.11.4 Finance Reports and Logs| Create customized Financial Reports and Logs 创建财务报表和日志 | E65: 2.11.4.2 As a Finance Operator, I want to be able to create customized Financial Reports and Logs via different filtering criteria and download them from the NewPOS Backend system, so that I can conduct Financial Reconciliation and Finance Posting. | F65: FS-8 | G65: Finance & Report | H65: 2.11.4.2 作为财务操作员，我希望能够通过不同的筛选条件创建自定义财务报表和日志，并从 NewPOS 后端系统下载它们，以便进行财务对账和财务过账。 | I65: FS-8 | J65: 只是条件筛选，字段过滤，并非汇总型报表 | K65: Lucky | M65: 找供应商确认，提供哪些定制化的报表 | N65: 报表与日志 | O65: 搜索筛选，下载 | P65: Front-end Developer & Product Designer & Back-end Developer & Quality Assurance & Product Manager & Delivery Manager | R65: 待确定 | S65: 10 | T65: =$S65*DE_Cost!$B$1*8 -> 96 | U65: =$S65*DE_Cost!$B$1 -> 12 | X65: =IF(TRIM(P65)="", 0, LEN(P65) - LEN(SUBSTITUTE(P65, "&", "")) + 1) -> 6 | Y65: =S65 * X65 -> 60 | Z65: Y | AE65: =(Y65 / $AE$2) * $AC$2 -> 21936.266
A66: 1(Minimum scope) | B66: 2. Foundation operational functions 基础运营功能 | C66: 2.11 Finance Processing and Configuration 财务处理和配置 | D66: 2.11.4 Finance Reports and Logs| Finance Reports and Logs access permissions 配置财务报表和日志的权限 | E66: 2.11.4.3 As a Finance Operator, I want NewPOS system to support role and access permissions specific to Finance users, so that only Finance users can have access to Finance-related data and Finance-related reports. | F66: FS-10 | G66: Finance & Report | H66: 2.11.4.3 作为财务操作员，我希望 NewPOS 系统能支持财务用户特定的角色和访问权限，以便只有财务用户才能访问财务相关数据和财务相关报告。" | I66: FS-10 | K66: Lucky | N66: 支持财务用户特定的角色和访问权限 | O66: 用户展示特定功能数据 | P66: Front-end Developer & Product Designer & Back-end Developer & Quality Assurance & Product Manager & Delivery Manager | R66: 待确定 | S66: 10 | T66: =$S66*DE_Cost!$B$1*8 -> 96 | U66: =$S66*DE_Cost!$B$1 -> 12 | X66: =IF(TRIM(P66)="", 0, LEN(P66) - LEN(SUBSTITUTE(P66, "&", "")) + 1) -> 6 | Y66: =S66 * X66 -> 60 | Z66: Y | AE66: =(Y66 / $AE$2) * $AC$2 -> 21936.266
A67: 1(Minimum scope) | B67: 2. Foundation operational functions 基础运营功能 | C67: 2.11 Finance Processing and Configuration 财务处理和配置 | D67: 2.11.4 Finance Reports and Logs| Longview Integration 集成Longview | E67: 2.11.4.4 As a Finance operator, I want NewPOS transactions to be sent to Longview (financial forcast & planning) system according to longview interface specifications, so that I can conduct financial forcast & planning for Merch and Fnb. | G67: Finance | H67: 2.11.4.4 作为财务操作员，我希望根据 Longview 接口规范将 NewPOS 交易发送到 Longview（财务预测与规划）系统，以便我可以对商户和餐饮业务进行财务预测与规划。 | K67: Lucky & Vetas | N67: 发送交易数据到 Longview | O67: 后端对接联调 | P67: Back-end Developer & Quality Assurance & Product Manager & Delivery Manager | S67: 10 | T67: =$S67*DE_Cost!$B$1*8 -> 96 | U67: =$S67*DE_Cost!$B$1 -> 12 | X67: =IF(TRIM(P67)="", 0, LEN(P67) - LEN(SUBSTITUTE(P67, "&", "")) + 1) -> 4 | Y67: =S67 * X67 -> 40 | Z67: Y | AE67: =(Y67 / $AE$2) * $AC$2 -> 14624.177
A68: 1(Minimum scope) | B68: 2. Foundation operational functions 基础运营功能 | C68: 2.11 Finance Processing and Configuration 财务处理和配置 | D68: 2.11.4 Finance Reports and Logs| Store Inventory report 门店库存报表 | E68: 2.11.4.5 As a Finance operator, I want to have inventory information in NEW POS report, so that I can conduct Merch item revenue and cost. | G68: Finance & Report | H68: 2.11.4.5 作为财务操作员，我希望 NEW POS 报告中包含库存信息，以便我能进行商品项目的收入和成本核算。 | K68: Lucky | N68: 报表与日志-包含库存信息 | O68: 库存数据同步单独工时 | P68: Front-end Developer & Product Designer & Back-end Developer & Quality Assurance & Product Manager & Delivery Manager | R68: 待确定 | S68: 10 | T68: =$S68*DE_Cost!$B$1*8 -> 96 | U68: =$S68*DE_Cost!$B$1 -> 12 | X68: =IF(TRIM(P68)="", 0, LEN(P68) - LEN(SUBSTITUTE(P68, "&", "")) + 1) -> 6 | Y68: =S68 * X68 -> 60 | Z68: Y | AE68: =(Y68 / $AE$2) * $AC$2 -> 21936.266
A69: 1(Minimum scope) | B69: 2. Foundation operational functions 基础运营功能 | C69: 2.2 Non-coupon promotion and discount(POS promotion) (非优惠券类)促销与折扣 | D69: 2.2.1 Non-coupon promotion configuration|Setup POS promotion type 定义促销类型 | E69: 2.2.1.1 As Ops admin, I need New POS will be able to configure POS promotion type which available in the store, and publish promotion after approval, as to define promotion in ordering. | F69: 1. Include: GWP (Gift with Purchase), PWP (Purchase with Purchase), Bundle, Discount, Tier Discount, and coupon availability. Promotion from SIMBA include： A. Item Level Offers (PWP/Purchase with purchase, GWP/Gift with Purchase) Simple Discount - Get Y for Discount - 25% off all summer products Purchase with purchase - Buy X, Get Discount - Buy any 3 kids’ T-shirts, get CNY 10 off Purchase with purchase - Spend X, Get Discount - Spend CNY 50 in Toys, get CNY 5 off Purchase with purchase - Buy X, Get Y for Discount -Buy 2 T-shirts; get a toy for 50% off Purchase with purchase - Spend X, Get Y for Discount - Spend CNY 100 on jewelry, get 25% off any 2 toys Purchase with purchase - Buy X of Single Item for Discount -Buy 2 bags for CNY 50 Purchase with purchase - Buy X and Y, Get Discount -Buy a plush, keychain, and backpack for CNY 20.00 Purchase with purchase - Buy X and Y, Get Z for Discount - Buy a scarf and hat, get 50% off gloves Gift with Purchase - Buy X, Get Gift with Purchase -Buy any 2 Duffy items, get a free beach towel B. Transaction Level Offers Simple Discount - Get Discount -10% off your purchase today only Buy/Get -Buy X, Get Discount -Buy 3 t-shirts, get CNY 10 off on your purchase Buy/Get -Spend X, Get Discount - Spend CNY 100 on Toy’s sets, get 5% off your purchase C. Conflicts – Controlled via POS option Promotion on an item that is on clearance Overlapping promotions When there are overlapping promotions, POS dictates what takes priority. 2. Enable to define by batch upload/modify, administrator authorized approval. | G69: New Simba | H69: 2.2.1.1 作为运营管理员，我需要新的POS系统能够配置门店可用的促销类型，并在审批通过后发布促销活动，以便在订单处理过程中实现促销规则的定义。 | I69: 1. 包含以下类型：赠品促销、加价购、捆绑销售、折扣、阶梯折扣以及优惠券可用性。来自SIMBA系统的促销包括： A. 商品层级促销 ▪简单折扣 - 指定商品享受折扣 - 夏季商品全场25% off ▪购买条件折扣 - 买X，享折扣 - 任意购买3件儿童T恤，立减10元 ▪购买条件折扣 - 消费满X，享折扣 - 玩具类消费满50元，立减5元 ▪购买条件折扣 - 买X，Y商品享折扣 - 购买2件T恤，一件玩具享受5折 ▪购买条件折扣 - 消费满X，Y商品享折扣 - 珠宝消费满100元，任意2件玩具享受75折 ▪购买条件折扣 - 单商品买X件享折扣 - 2个包包售价50元 ▪购买条件折扣 - 买X和Y，享折扣 - 购买一个毛绒玩具、一个钥匙扣和一个背包，售价20元 ▪购买条件折扣 - 买X和Y，Z商品享折扣 - 购买一条围巾和一顶帽子，手套享受5折 ▪赠品促销 - 买X，获赠品 - 任意购买2件达菲商品，免费获赠一条沙滩毛巾 B. 交易层级促销 ▪简单折扣 - 享折扣 - 仅限今日，全场9折 ▪买/获 - 买X，享折扣 - 购买3件T恤，整单立减10元 ▪买/获 - 消费满X，享折扣 - 玩具套装消费满100元，整单享受95折 C. 冲突 – 通过POS选项控制 ▪清仓商品参与促销 ▪重叠促销 ▪当出现重叠促销时，由POS系统决定优先级。 2. 支持通过批量上传/修改进行定义，并需经管理员授权批准。 | J69: 从Simba同步门店促销类型 B里的折扣包含coupon和促销 | K69: F&B | M69: MO需要了解供应商关于促销的solution | N69: 配置-促销类型-配置商店中 | O69: 1.同步SIMBA的促销信息,并发布促销活动 A商品层级促销 B交易层级促销 C重叠的促销活动，POS决定优先级 D发布促销。 2能够通过批量上传/修改定义，管理员授权。 | P69: Android Developer & Front-end Developer & Product Designer & Back-end Developer & Quality Assurance & Product Manager & Delivery Manager | S69: 30 | T69: =$S69*DE_Cost!$B$1*8 -> 288 | U69: =$S69*DE_Cost!$B$1 -> 36 | X69: =IF(TRIM(P69)="", 0, LEN(P69) - LEN(SUBSTITUTE(P69, "&", "")) + 1) -> 7 | Y69: =S69 * X69 -> 210 | Z69: Y | AE69: =(Y69 / $AE$2) * $AC$2 -> 76776.93
A70: 1(Minimum scope) | B70: 2. Foundation operational functions 基础运营功能 | C70: 2.2 Non-coupon promotion and discount(POS promotion) (非优惠券类)促销与折扣 | D70: 2.2.1 Non-coupon promotion configuration|Configure POS promotion rules 配置促销规则 | E70: 2.2.1.2 As Ops admin, I need New POS will be able to configure POS promotion detail as effective/priority/repeat for each type, as to define promotion in ordering. | F70: A store will be able to support multiple promotions, and these promotions could be batch upload in file or sync from SIMBA. Include: 1)effective time/store/identity, 2) priority, overlay, exclusion rules | G70: New Simba | H70: 2.2.1.2 作为运维管理员，我需要新 POS 能够为每种类型配置 POS 促销详情，包括有效/优先级/重复设置，以便在订单中定义促销。 | I70: 一家商店将能够支持多个促销活动，并且这些促销活动可以通过文件批量上传或从SIMBA同步。 包括：1) 有效时间/商店/身份，2) 优先级、叠加、排除规则 | J70: 可从Simba同步门店促销规则 New POS设置好促销规则与Simba一一对应 促销的优级级冲突怎么配置--3.4.5.1 | N70: 配置-促销详情 | O70: 1配置+文件上传(2) | P70: Front-end Developer & Product Designer & Back-end Developer & Quality Assurance & Product Manager & Delivery Manager | S70: 10 | T70: =$S70*DE_Cost!$B$1*8 -> 96 | U70: =$S70*DE_Cost!$B$1 -> 12 | X70: =IF(TRIM(P70)="", 0, LEN(P70) - LEN(SUBSTITUTE(P70, "&", "")) + 1) -> 6 | Y70: =S70 * X70 -> 60 | Z70: Y | AE70: =(Y70 / $AE$2) * $AC$2 -> 21936.266
A71: 1(Minimum scope) | B71: 2. Foundation operational functions 基础运营功能 | C71: 2.2 Non-coupon promotion and discount(POS promotion) (非优惠券类)促销与折扣 | D71: 2.2.1 Non-coupon promotion configuration|Configure POS promotion available period 配置促销生效时间 | E71: 2.2.1.3 As Ops admin, I need New POS will be able to configure POS promotion available period, as to define promotion in ordering. | F71: The period can be define by start & end date timestamp with repeat cycle(monthly, weekly, daily), enable a reminder for ending/extension. | H71: 2.2.1.3 作为运维管理员，我需要新 POS 系统能够配置 POS 促销活动可用期限，以便在订单中定义促销。 | I71: 该期间可以通过开始和结束日期时间戳定义，并具有重复周期（每月、每周、每天），并为结束/延期启用提醒。 | N71: 配置-促销活动-可用期限 | O71: admin配置（2） | P71: Front-end Developer & Product Designer & Back-end Developer & Quality Assurance & Product Manager & Delivery Manager | S71: 3 | T71: =$S71*DE_Cost!$B$1*8 -> 28.8 | U71: =$S71*DE_Cost!$B$1 -> 3.6 | X71: =IF(TRIM(P71)="", 0, LEN(P71) - LEN(SUBSTITUTE(P71, "&", "")) + 1) -> 6 | Y71: =S71 * X71 -> 18 | Z71: Y | AE71: =(Y71 / $AE$2) * $AC$2 -> 6580.8797
A72: 1(Minimum scope) | B72: 2. Foundation operational functions 基础运营功能 | C72: 2.2 Non-coupon promotion and discount(POS promotion) (非优惠券类)促销与折扣 | D72: 2.2.2 Non-coupon promotion execution|Auto-apply POS promotion 自动添加促销折扣 | E72: 2.2.2.1 As Ops cashier, I need New POS will be able to auto-apply available POS promotion when conditions are met in ordering in priority, as to process promotion benefit/discount in ordering. | F72: POS is not applicable to calculate the max discount as "best offer” in multiple promotions/discounts applied, but it can only calculate the amount by promotion/ discount pre-defined priority, no matter the sequence of these promotions applied. | H72: 2.2.2.1 作为收银员，我需要新 POS 系统能够在满足条件时按优先级自动应用可用的 POS 促销，以便在订单处理中应用促销优惠/折扣。 | I72: POS不适用于计算应用多个促销/折扣时的“最佳优惠”最大折扣，但它只能按促销/折扣预定义的优先级计算金额，无论这些促销的应用顺序如何。 | N72: 配置-促销活动-优先级设定 | O72: admin配置（2） | P72: Android Developer & Front-end Developer & Product Designer & Back-end Developer & Quality Assurance & Product Manager & Delivery Manager | S72: 5 | T72: =$S72*DE_Cost!$B$1*8 -> 48 | U72: =$S72*DE_Cost!$B$1 -> 6 | X72: =IF(TRIM(P72)="", 0, LEN(P72) - LEN(SUBSTITUTE(P72, "&", "")) + 1) -> 7 | Y72: =S72 * X72 -> 35 | Z72: Y | AE72: =(Y72 / $AE$2) * $AC$2 -> 12796.155
A73: 1(Minimum scope) | B73: 2. Foundation operational functions 基础运营功能 | C73: 2.2 Non-coupon promotion and discount(POS promotion) (非优惠券类)促销与折扣 | D73: 2.2.2 Non-coupon promotion execution|Manual apply POS promotion 手动添加促销 | E73: 2.2.2.2 As Ops cashier, I need New POS will be able to manual apply POS promotion by cast selection, as to process promotion benefit/discount in ordering. | F73: Show a list of available promotions in this store, then cashiers can select to apply | H73: 2.2.2.2 作为收银员，我需要新 POS 系统能够通过选择商品手动应用 POS 促销，以便在订单处理中应用促销优惠/折扣。 | I73: 显示此商店中可用促销活动的列表，然后收银员可以选择应用 | N73: 配置-促销活动-选择商品应用促销 | O73: 显示此商店中可用促销活动的列表，然后收银员可以选择应用 | P73: Android Developer & Front-end Developer & Product Designer & Back-end Developer & Quality Assurance & Product Manager & Delivery Manager | S73: 3 | T73: =$S73*DE_Cost!$B$1*8 -> 28.8 | U73: =$S73*DE_Cost!$B$1 -> 3.6 | X73: =IF(TRIM(P73)="", 0, LEN(P73) - LEN(SUBSTITUTE(P73, "&", "")) + 1) -> 7 | Y73: =S73 * X73 -> 21 | Z73: Y | AE73: =(Y73 / $AE$2) * $AC$2 -> 7677.693
A74: 1(Minimum scope) | B74: 2. Foundation operational functions 基础运营功能 | C74: 2.2 Non-coupon promotion and discount(POS promotion) (非优惠券类)促销与折扣 | D74: 2.2.2 Non-coupon promotion execution|Add remark on POS promotion 填写促销附加信息 | E74: 2.2.2.3 As Ops cashier, I need New POS will be able to input promotion information as additional fields by cashier as supporting. E.g. CEA discount, as to fulfill promotion benefit/discount info in ordering. | F74: Cashier may need to enter guest identity code(E.g. ETKT code for CEA discount) into additional fields by verify and scan guest identification document. | H74: 2.2.2.3 作为收银员，我需要新 POS 系统能够让收银员通过附加字段输入促销信息作为支持。例如 CEA 折扣，以便在订单中实现促销优惠/折扣信息。 | I74: 收银员可能需要通过验证和扫描客人身份证明文件，将客人身份代码（例如，CEA折扣的ETKT代码）输入到附加字段中。 | N74: 促销活动-收银员操作 | O74: POS Android Developer端附加字段，能够实现订单优惠信息 | P74: Android Developer & Front-end Developer & Product Designer & Back-end Developer & Quality Assurance & Product Manager & Delivery Manager | S74: 3 | T74: =$S74*DE_Cost!$B$1*8 -> 28.8 | U74: =$S74*DE_Cost!$B$1 -> 3.6 | X74: =IF(TRIM(P74)="", 0, LEN(P74) - LEN(SUBSTITUTE(P74, "&", "")) + 1) -> 7 | Y74: =S74 * X74 -> 21 | Z74: Y | AE74: =(Y74 / $AE$2) * $AC$2 -> 7677.693
A75: 1(Minimum scope) | B75: 2. Foundation operational functions 基础运营功能 | C75: 2.2 Non-coupon promotion and discount(POS promotion) (非优惠券类)促销与折扣 | D75: 2.2.2 Non-coupon promotion execution|Cancel applied POS promotion 取消已添加的促销 | E75: 2.2.2.4 As Ops cashier, I need New POS will be able to remove a selected promotion when guest would like to pay without promotion, as to process promotion benefit/discount in ordering. | H75: 2.2.2.4 作为收银员，我需要新 POS 系统能够在客人选择不使用促销时移除所选促销，以便在点单过程中处理促销优惠/折扣。 | N75: 促销活动-移除促销 | O75: POS Android Developer端 移除所选促销信息 | P75: Android Developer & Front-end Developer & Product Designer & Back-end Developer & Quality Assurance & Product Manager & Delivery Manager | S75: 2 | T75: =$S75*DE_Cost!$B$1*8 -> 19.2 | U75: =$S75*DE_Cost!$B$1 -> 2.4 | X75: =IF(TRIM(P75)="", 0, LEN(P75) - LEN(SUBSTITUTE(P75, "&", "")) + 1) -> 7 | Y75: =S75 * X75 -> 14 | Z75: Y | AE75: =(Y75 / $AE$2) * $AC$2 -> 5118.462
A76: 1(Minimum scope) | B76: 2. Foundation operational functions 基础运营功能 | C76: 2.3 Checkout and payment 支付与结账 | D76: 2.3.1 Payment method Configuration|Configure payment method 设置支付方式 | E76: 2.3.1.1 As Ops admin, I need New POS will be able to configure payment method in store/stores group level on payment screen, as to define payment in ordering. | F76: Include: payment method name, payment method ranking, enable/disable | H76: 2.3.1.1 作为运维管理员，我需要新 POS 能够在支付屏幕上配置门店/门店组级别的支付方式，以便在订单中定义支付方式。 | I76: 包括：支付方式名称、支付方式排名、启用/禁用 | N76: 配置-支付屏幕-配置门店级别支付方式 | O76: POS Android Developer端 支付方式展示 （1） 后台 配置（1） | P76: Front-end Developer & Product Designer & Back-end Developer & Quality Assurance & Product Manager & Delivery Manager | S76: 2 | T76: =$S76*DE_Cost!$B$1*8 -> 19.2 | U76: =$S76*DE_Cost!$B$1 -> 2.4 | X76: =IF(TRIM(P76)="", 0, LEN(P76) - LEN(SUBSTITUTE(P76, "&", "")) + 1) -> 6 | Y76: =S76 * X76 -> 12 | Z76: Y | AE76: =(Y76 / $AE$2) * $AC$2 -> 4387.2532
A77: 1(Minimum scope) | B77: 2. Foundation operational functions 基础运营功能 | C77: 2.3 Checkout and payment 支付与结账 | D77: 2.3.1 Payment method Configuration|Identify scan payment 配置扫码支付 | E77: 2.3.1.2 As Ops cashier, I need New POS will be able to identify scan payment channel by QR code, as to define payment in ordering. | F77: Include: 1)WeChat Pay, 2) Alipay, 3) Gift card-will be retired after 2026 Aug., 4) e - CNY, 5) Union Pay | H77: 2.3.1.2 作为运营管理员，我需要新的POS系统能够通过二维码识别扫码支付渠道，以便在订单处理中定义支付方式。 | I77: 支持的支付渠道包括： 1. 微信支付 2. 支付宝 3. 礼品卡（将于2026年8月后停用） 4. 数字人民币 5. 云闪付 | N77: POS Android Developer 扫码识别支付方式 | O77: Android Developer | P77: Android Developer & Front-end Developer & Product Designer & Quality Assurance & Product Manager & Delivery Manager | Q77: Ops Admin扫QR Code，再去定义支付方式，无法理解这个场景 扫码之后才能确认支付方式吗？ 不是OPS，是Cashier，扫多种码可以识别出微信或支付宝 | S77: 10 | T77: =$S77*DE_Cost!$B$1*8 -> 96 | U77: =$S77*DE_Cost!$B$1 -> 12 | X77: =IF(TRIM(P77)="", 0, LEN(P77) - LEN(SUBSTITUTE(P77, "&", "")) + 1) -> 6 | Y77: =S77 * X77 -> 60 | Z77: Y | AB77: 1103 | AE77: =(Y77 / $AE$2) * $AC$2 -> 21936.266
A78: 1(Minimum scope) | B78: 2. Foundation operational functions 基础运营功能 | C78: 2.3 Checkout and payment 支付与结账 | D78: 2.3.1 Payment method Configuration|Configure cash payment and change 配置现金支付与找零 | E78: 2.3.1.3 As Ops admin, I need New POS will be able to configure RMB cash payment and change with cash drawer, as to define payment in ordering. | F78: 1. Set RMB cash payment as quick access button, and also able to manual input in 元角分(current practice will round down to 元, not need to input 角 and 分) 2. Link to drawer and calculate/prompt change, log all cash payment actions. | H78: 2.3.1.3 作为运维管理员，我需要新 POS 系统能够配置人民币现金支付和现金找零，以便在订单中定义支付方式。 | I78: 1. 将人民币现金支付设置为快速访问按钮，并能够以元角分手动输入（目前的做法将向下舍入到元，不需要输入角和分） 2. 连接到钱箱并计算/提示找零，记录所有现金支付操作。 | N78: 配置-现金/现金找零-付款方式 | O78: POS Android Developer 支付方式展示 （1） 后台 配置（1） | P78: Android Developer & Front-end Developer & Back-end Developer & Quality Assurance & Product Manager & Delivery Manager | S78: 2 | T78: =$S78*DE_Cost!$B$1*8 -> 19.2 | U78: =$S78*DE_Cost!$B$1 -> 2.4 | X78: =IF(TRIM(P78)="", 0, LEN(P78) - LEN(SUBSTITUTE(P78, "&", "")) + 1) -> 6 | Y78: =S78 * X78 -> 12 | Z78: Y | AE78: =(Y78 / $AE$2) * $AC$2 -> 4387.2532
A79: 1(Minimum scope) | B79: 2. Foundation operational functions 基础运营功能 | C79: 2.3 Checkout and payment 支付与结账 | D79: 2.3.1 Payment method Configuration|Configure bankcard payment 配置银行卡支付 | E79: 2.3.1.4 As Ops admin, I need New POS will be able to configure bankcard payment, as to define payment in ordering. | F79: Include: domestic bankcard and foreign bankcard on BOT | H79: 2.3.1.4 作为运维管理员，我需要新 POS 系统能够配置银行卡支付，以便在订单中定义支付方式。 | I79: 包括：BOT上的国内银行卡和国外银行卡 | N79: 配置-银行卡-付款方式 | O79: POS Android Developer 支付方式展示 （1） 后台 配置（1） | P79: Android Developer & Front-end Developer & Back-end Developer & Quality Assurance & Product Manager & Delivery Manager | S79: 2 | T79: =$S79*DE_Cost!$B$1*8 -> 19.2 | U79: =$S79*DE_Cost!$B$1 -> 2.4 | X79: =IF(TRIM(P79)="", 0, LEN(P79) - LEN(SUBSTITUTE(P79, "&", "")) + 1) -> 6 | Y79: =S79 * X79 -> 12 | Z79: Y | AE79: =(Y79 / $AE$2) * $AC$2 -> 4387.2532
A80: 1(Minimum scope) | B80: 2. Foundation operational functions 基础运营功能 | C80: 2.3 Checkout and payment 支付与结账 | D80: 2.3.1 Payment method Configuration|Configure voucher payment 配置兑换券支付 | E80: 2.3.1.5 As Ops admin, I need New POS will be able to configure voucher as a non-cash payment by pre-defined code, as to define payment in ordering. | F80: 1. Configure existing non-cash payment codes into buttons, like 181, 182, 183, 184, 1828, 1829, also able to customize non-cash code. 2. Configure non-cash voucher payment as create, edit, enable/disable. | H80: 2.3.1.5 作为运维管理员，我需要新 POS 系统能够通过预定义代码将优惠券配置为非现金支付方式，以便在订单中定义支付。 | I80: 1. 将现有的非现金支付代码配置为按钮，如181、182、183、184、1828、1829，也能够自定义非现金代码。 2. 将非现金代金券支付配置为创建、编辑、启用/禁用。 | N80: 配置-预定义代码-非现金支付方式 | O80: POS Android Developer 支付方式展示 （1） 后台 配置（1） | P80: Android Developer & Front-end Developer & Back-end Developer & Quality Assurance & Product Manager & Delivery Manager | S80: 2 | T80: =$S80*DE_Cost!$B$1*8 -> 19.2 | U80: =$S80*DE_Cost!$B$1 -> 2.4 | X80: =IF(TRIM(P80)="", 0, LEN(P80) - LEN(SUBSTITUTE(P80, "&", "")) + 1) -> 6 | Y80: =S80 * X80 -> 12 | Z80: Y | AE80: =(Y80 / $AE$2) * $AC$2 -> 4387.2532
A81: 1(Minimum scope) | B81: 2. Foundation operational functions 基础运营功能 | C81: 2.3 Checkout and payment 支付与结账 | D81: 2.3.2 Payment process Configuration|Process order payment 执行订单支付 | E81: 2.3.2.1 As Ops cashier, I need New POS will be able to process payment with multiple payment methods combination, and print receipt after payment is completed, as to process payment in ordering. | F81: Include: scan to pay, RMB Cash, bank card, non-cash(voucher), contingency payment, etc. | H81: 2.3.2.1 作为收银员，我需要新 POS 系统能够处理多种支付方式的组合支付，并在支付完成后打印收据，以便在点单过程中完成支付。 | I81: 包括：扫码支付、人民币现金、银行卡、非现金（代金券）、应急支付等。 | N81: 执行订单支付-多种组合支付方式 | O81: POS Android Developer 组合支付调起（1） 服务端接收参数信息和PIS对接（2） | P81: Android Developer & Front-end Developer & Product Designer & Back-end Developer & Quality Assurance & Product Manager & Delivery Manager | S81: 10 | T81: =$S81*DE_Cost!$B$1*8 -> 96 | U81: =$S81*DE_Cost!$B$1 -> 12 | X81: =IF(TRIM(P81)="", 0, LEN(P81) - LEN(SUBSTITUTE(P81, "&", "")) + 1) -> 7 | Y81: =S81 * X81 -> 70 | Z81: Y | AE81: =(Y81 / $AE$2) * $AC$2 -> 25592.31
A82: 1(Minimum scope) | B82: 2. Foundation operational functions 基础运营功能 | C82: 2.3 Checkout and payment 支付与结账 | D82: 2.3.2 Payment process Configuration|Modify payment method in checkout 修改支付方式 | E82: 2.3.2.2 As Ops cashier, I need New POS will be able to modify the payment among configured methods, as to process payment in ordering. | F82: Payment method can be modified or cancelled before paid | H82: 2.3.2.2 作为运营收银员，我需要新 POS 系统能够在配置的支付方式之间修改支付，以便在订单处理过程中完成支付。 | I82: 支付方式可以在支付前修改或取消 | N82: 执行订单支付-切换支付方式 | O82: POS Android Developer 切换支付方式 | P82: Android Developer & Front-end Developer & Product Designer & Quality Assurance & Product Manager & Delivery Manager | S82: 2 | T82: =$S82*DE_Cost!$B$1*8 -> 19.2 | U82: =$S82*DE_Cost!$B$1 -> 2.4 | X82: =IF(TRIM(P82)="", 0, LEN(P82) - LEN(SUBSTITUTE(P82, "&", "")) + 1) -> 6 | Y82: =S82 * X82 -> 12 | Z82: Y | AE82: =(Y82 / $AE$2) * $AC$2 -> 4387.2532
A83: 1(Minimum scope) | B83: 2. Foundation operational functions 基础运营功能 | C83: 2.3 Checkout and payment 支付与结账 | D83: 2.3.2 Payment process Configuration|Enable combine payment 合并付款 | E83: 2.3.2.3 As Ops cashier, I need New POS will be able to process a payment with multiple products in a order, as to process payment in ordering. | H83: 2.3.2.3 作为收银员，我需要新 POS 系统能够处理订单中包含多个产品的支付，以便在订购过程中完成支付。 | N83: 执行订单支付-多商品支付 | O83: POS Android Developer 多个商品结算支付 | P83: Android Developer & Front-end Developer & Product Designer & Quality Assurance & Product Manager & Delivery Manager | S83: 2 | T83: =$S83*DE_Cost!$B$1*8 -> 19.2 | U83: =$S83*DE_Cost!$B$1 -> 2.4 | X83: =IF(TRIM(P83)="", 0, LEN(P83) - LEN(SUBSTITUTE(P83, "&", "")) + 1) -> 6 | Y83: =S83 * X83 -> 12 | Z83: Y | AE83: =(Y83 / $AE$2) * $AC$2 -> 4387.2532
A84: 1(Minimum scope) | B84: 2. Foundation operational functions 基础运营功能 | C84: 2.3 Checkout and payment 支付与结账 | D84: 2.3.2 Payment process Configuration|Charge to hotel room 挂房账支付 | E84: 2.3.2.4 As Ops cashier, I need New POS will be able to charge transaction to hotel room, as to fulfill guest payment request in hotel shopping or dinning. | F84: 1. The charging to room need to be checked-in and have enough deposit. 2. Store/Restaurant cast should be able to easily check if there is deposit or not via system. 3. Room charging is able to refund via guest original payment method in hotel payment. | G84: PMS-Opera | H84: 2.3.2.4 作为收银员，我需要新 POS 系统能够将交易费用计入酒店房间，以满足客人在酒店购物或用餐时的付款需求。 | I84: 1. 记入房费需要客人已办理入住且有足够的押金。 2. 商店/餐厅收银员应该能够通过系统轻松查看是否有押金。 3. 房费记账可以通过客人在酒店支付时使用的原始支付方式进行退款。 | J84: 同一个接口处理挂房帐付款和退款 | N84: 执行订单支付-挂房支付 | P84: Android Developer & Front-end Developer & Product Designer & Back-end Developer & Quality Assurance & Product Manager & Delivery Manager | S84: 10 | T84: =$S84*DE_Cost!$B$1*8 -> 96 | U84: =$S84*DE_Cost!$B$1 -> 12 | X84: =IF(TRIM(P84)="", 0, LEN(P84) - LEN(SUBSTITUTE(P84, "&", "")) + 1) -> 7 | Y84: =S84 * X84 -> 70 | Z84: Y | AE84: =(Y84 / $AE$2) * $AC$2 -> 25592.31
